Workbook
Name _Hlk104232410: CONTRATOS!$M$603
Name _Hlk112011606: CONTRATOS!$L$717
Name _Hlk113616823: CONTRATOS!$I$674
Name _Hlk118841670: PROCESOS!$E$844
Name _Hlk161317399: PROCESOS!$E$815
Name _Hlk91169232: CONTRATOS!$L$704
Name _Hlk94027716: PROCESOS!$E$412
Name _Hlk99553524: CONTRATOS!$L$589
Name AREA_ORDENADORA: Listas!$A$2:$A$14
Name AREA_SOLICITANTE: Listas!$E$2:$E$19
Name OFICINA_ASESORA_DE_COMUNICACIONES: Listas!$S$2:$S$3
Name OFICINA_ASESORA_DE_PLANEACIÓN: Listas!$M$2:$M$3
Name OFICINA_ASESORA_JURÍDICA: Listas!$N$2:$N$3
Name OFICINA_COMERCIAL_Y_DE_MERCADEO: Listas!$R$2:$R$5
Name OFICINA_DE_CONTROL_INTERNO: Listas!$O$2:$O$3
Name OFICINA_DE_RELACIONES_INTERNACIONALES: Listas!$P$2:$P$3
Name OFICINA_DE_RIESGOS: Listas!$Q$2:$Q$5
Name PRESIDENCIA: Listas!$G$2
Name SECRETARÍA_GENERAL: Listas!$H$2:$H$11
Name TERRITORIAL_CENTRO: Listas!$T$2
Name TERRITORIAL_NOROCCIDENTE: Listas!$U$2
Name TERRITORIAL_NORTE: Listas!$W$2
Name TERRITORIAL_ORIENTE: Listas!$X$2
Name TERRITORIAL_SUROCCIDENTE: Listas!$V$2
Name VICEPRESIDENCIA_DE_CRÉDITO_Y_COBRANZA: Listas!$I$2:$I$4
Name VICEPRESIDENCIA_DE_FONDOS_EN_ADMINISTRACIÓN: Listas!$J$2:$J$8
Name VICEPRESIDENCIA_DE_OPERACIONES_Y_TECNOLOGÍA: Listas!$K$2:$K$19
Name VICEPRESIDENCIA_FINANCIERA: Listas!$L$2:$L$11

Sheet MENU
B2: MENU
B4: BASE CONTRATOS
B6: BASE PROCESOS
B8: BASE OTROSÍ CONVENIOS
B10: BASE OTROSÍ CONTRATOS
B12: BASE LIQUIDACIONES

Sheet Hoja1

Sheet Hoja2

Sheet Hoja3

Sheet CONTRATOS
A1: i | B1: No. Cto | C1: TIPO DE CONTRATO | D1: NÚMERO DEL PROCESO DE SELECCIÓN TAL CUAL APARECE EN LA MINUTA Y COMO FUE PUBLICADO EN EL SECOP | E1: CLASE DE CONTRATO | F1: CONTRATISTA: NATURALEZA | G1: CONTRATISTA: TIPO IDENTIFICACIÓN | H1: CONTRATISTA: NÚMERO DE IDENTIFICACIÓN | I1: CONTRATISTA : NOMBRE COMPLETO O RAZON SOCIAL | J1: CONTRATISTA: NOMBRE DEL REPRESENTANTE LEGAL | K1: CONTRATISTA: REPRESENTANTE LEGAL - NÚMERO DE CÉDULA | L1: OBJETO DEL CONTRATO Y/O CONVENIO | M1: LUGAR DE EJECUCIÓN DEL CONTRATO (MUNICIPIO) | N1: FECHA DE SUSCRIPCIÓN | O1: FECHA DE INICIO | P1: FECHA DE TERMINACIÓN INICIAL | Q1: PLAZO INICIAL DEL CONTRATO | R1: AFECTACIÓN DEL RECURSO | S1: Nº CDP: Disp.presupuestal | T1: PROYECTO | U1: CDP: Valor | V1: RP - Rubro | W1: VALOR INICIAL CONTRATO | X1: FORMA DE PAGO: HONORARIOS MENSUALES PACTADOS PARA PRESTACIÓN DE SERVICIO ASISTENCIAL O PROFESIONAL | Y1: VALOR CONVENIO | Z1: No PÓLIZA | AA1: ÁREA ORDENADORA DEL GASTO | AB1: ORDENADOR: NOMBRE COMPLETO | AC1: ORDENADOR: NÚMERO DE CÉDULA | AD1: ÁREA SOLICITANTE | AE1: SUPERVISOR: CARGO DEL SUPERVISOR | AF1: SUPERVISOR: NOMBRE COMPLETO | AG1: SUPERVISOR: NÚMERO DE CÉDULA | AH1: MODALIDAD DE SELECCIÓN | AI1: OBLIGACIONES ESPECIFICAS | AJ1: VINCULACIÓN SIGEP | AK1: PUBLICACIÓN PROACTIVA DECLARACIÓN DE BIENES Y RENTAS Y REGISTRO DE CONFLICTOS DE INTERÉS | AL1: DECLARACIÓN DE RENTA | AM1: CURSO DE TRANSPARENCIA | AN1: FECHA DE NACIMIENTO (PRESTACIÓN DE SERVICIOS PERSONA NATURAL) | AO1: EDAD | AP1: GRUPO TRAMITADOR | AQ1: ABOGADO | AR1: CESIÓN 1: FECHA DE SUSCRIPCIÓN | AS1: CESIÓN 1: NOMBRE COMPLETO | AT1: CESIÓN 1: No. IDENTIFICACIÓN | AU1: CESIÓN 1: OBJETO | AV1: CESIÓN 1: VALOR CESIONADO | AW1: CESIÓN 2: FECHA DE SUSCRIPCIÓN | AX1: CESIÓN 2: NOMBRE COMPLETO | AY1: CESIÓN 2: No. IDENTIFICACIÓN | AZ1: CESIÓN 2: OBJETO | BA1: CESIÓN 2: VALOR CESIONADO | BB1: PRORROGA 1: FECHA SUSCRIPCION | BC1: PRORROGA 1: PLAZO | BD1: PRORROGA 2: FECHA | BE1: PRORROGA 2: PLAZO | BF1: TOTAL DÍAS PRORROGADOS | BG1: DISMINUCIÓN DE NÚMERO DE DIASTERMINACIÓN ANTICIPADA | BH1: FECHA TERMINACIÓN ANTICIPADA | BI1: PLAZO TOTAL DEL CONTRATO | BJ1: FECHA DE TERMINACIÓN FINAL | BK1: MODIFICACIÓN 1: FECHA DE SUSCRIPCIÓN | BL1: MODIFICIACIÓN 1: OBJETO | BM1: MODIFICACIÓN 2: FECHA DE SUSCRIPCIÓN | BN1: MODIFICIACIÓN 2: OBJETO | BO1: MODIFICACIÓN 3: FECHA DE SUSCRIPCIÓN | BP1: MODIFICIACIÓN 3: OBJETO | BQ1: ADICIÓN 1: FECHA DE SUSCRIPCIÓN | BR1: ADICIÓN 1: VALOR | BS1: CDP ADICIÓN 1 | BT1: ADICIÓN 1: OBJETO | BU1: ADICIÓN 2: FECHA DE SUSCRIPCIÓN | BV1: ADICIÓN 2: VALOR | BW1: CDP ADICIÓN 2 | BX1: ADICIÓN 2: OBJETO | BY1: ADICIÓN 3: FECHA DE SUSCRIPCIÓN | BZ1: ADICIÓN 3: VALOR | CA1: CDP ADICIÓN 3 | CB1: ADICIÓN 3: OBJETO | CC1: ADICIÓN: VALOR TOTAL | CD1: DISMINUCION: VALOR | CE1: VALOR FINAL DEL CONTRATO DESPUES DE MODIFICACIONES | CF1: VALOR EJECUTADO (DILIGENCIA FINANCIERA) | CG1: VALOR PAGADO PROGRAMADO | CH1: PORCENTAJE DE AVANCE FÍSICO PROGRAMADO | CI1: PORCENTAJE DE AVANCE FÍSICO REAL | CJ1: PORCENTAJE AVANCE PRESUPUESTAL PROGRAMADO | CK1: PORCENTAJE AVANCE PRESUPUESTAL REAL | CL1: FECHA DE LIQUIDACIÓN DEL CONTRATO | CM1: ESTADO | CN1: OBSERVACIONES | CO1: NUMERO DE RADICADO | CP1: GENERO | CQ1: NUMERO DE REGISTRO PRESUPUESTAL | CR1: NUMERO DE REGISTRO PRESUPUESTAL ADICION / CESION
A2: 13.38 | B2: 2024-0001 | C2: CTO | D2: CD-001-2024 | E2: 9 PRESTACIÓN DE SERVICIOS | F2: 1 PERSONA NATURAL | G2: 3 CÉDULA DE CIUDADANÍA | H2: 52935588 | I2: GIOHANA CATARINE GONZALES TURIZO | L2: 13.38 PRESTACIÓN DE SERVICIOS PROFESIONALES COMO ABOGADO PARA APOYAR EL DESARROLLO Y SEGUIMIENTO DE LA ACTIVIDAD CONTRACTUAL EN EL MARCO DEL PROYECTO DE FORTALECIMIENTO ORGANIZACIONAL Y LA IMPLEMENTACIÓN DE LA POLÍTICA DE COMPRAS PÚBLICAS Y DE CONTRATACIÓN DEL ICETEX | M2: BOGOTA | N2: 45294 | O2: 45294 | P2: 45475 | Q2: =P2-O2 -> 181 | R2: 2 INVERSIÓN | S2: CDEF-24-2024 | T2: FORTALECIMIENTO ORGANIZACIONAL | U2: 105619200 | V2: IG 332901003 | W2: 105619200 | X2: 8801600 | AA2: SECRETARÍA_GENERAL | AB2: =IFERROR(VLOOKUP(AA2,Listas!$A$1:$C$14,2,FALSE),"") -> FREDY CÉSPEDES VILLA | AC2: =IFERROR(VLOOKUP(AA2,Listas!$A$1:$C$14,3,FALSE),"") -> 93363483 | AD2: SECRETARÍA_GENERAL | AE2: COORDINADOR(A) GRUPO DE CONTRATACIÓN | AF2: =IFERROR(VLOOKUP(AE2,Listas!$AD$1:$AF$66,2,FALSE),"") -> DIANA BARRERA MEDINA | AG2: =IFERROR(VLOOKUP(AE2,Listas!$AD$1:$AF$65,3,FALSE),"") -> 52964360 | AH2: 1 CONTRATACION DIRECTA | AJ2: 1 SI | AK2: 1 PUBLICADO | AL2: 1 PUBLICADO | AM2: 1 SI | AN2: 30552 | AO2: =IF(YEAR(TODAY())-YEAR(AN2)>100," ",YEAR(TODAY())-YEAR(AN2)) -> 42 | AP2: GRUPO_DE_CONTRATACIÓN | AQ2: LAURA NARANJO | BF2: =BC2+BE2 -> 0 | BI2: =BF2+Q2 -> 181 | BJ2: =IF(BH2="",P2+BF2,BH2) -> 45475 | CC2: =BR2+BV2+BZ2 -> 0 | CE2: =IF(Y2=0,(W2+CC2)-CD2,IF(Y2>0,(Y2+CC2)-CD2)) -> 105619200 | CG2: =IFERROR(IF(((CE2/BI2)*(TODAY()-N2))>CE2,CE2,((CE2/BI2)*(TODAY()-N2))),"") -> 105619200 | CH2: =IF(TODAY()>BJ2,1,+(DAYS360(O2,TODAY())/DAYS360(O2,BJ2))) -> 1 | CI2: =+IF(CL2>0,DAYS360(O2,CL2)/DAYS360(O2,BJ2),CH2) -> 1 | CJ2: =IFERROR(IF(((CG2/CE2)*100)>100,100,((CG2/CE2)*100)),"") -> 100 | CK2: =IFERROR((CF2/CE2)*100,"") -> 0 | CM2: =IF(CL2>1/1/6,"LIQUIDADO",IF(BJ2=0,"",IF(BJ2>=TODAY(),"VIGENTE",IF(BJ2<TODAY(),"TERMINADO",)))) -> TERMINADO | CP2: FEMENINO
A3: 13.25 | B3: 2024-0002 | C3: CTO | D3: CD-002-2024 | E3: 9 PRESTACIÓN DE SERVICIOS | F3: 1 PERSONA NATURAL | G3: 3 CÉDULA DE CIUDADANÍA | H3: 1031129528 | I3: AMANDA CATALINA CARREÑO BUITRAGO | L3: 13.25 PRESTACIÓN DE SERVICIOS PROFESIONALES EN DERECHO PARA BRINDAR ASESORÍA JURÍDICA EN LAS DIFERENTES ETAPAS DE LA ACTIVIDAD CONTRACTUAL DE ACUERDO CON LAS POLÍTICAS DE CELEBRACIÓN Y EJECUCIÓN DE CONTRATOS EN EL MARCO DEL "PROYECTO DE FORTALECIMIENTO ORGANIZACIONAL" DEL ICETEX. | M3: BOGOTA | N3: 45294 | O3: 45295 | P3: 45656 | Q3: =P3-O3 -> 361 | R3: 2 INVERSIÓN | S3: CDEF-117-2024 | T3: FORTALECIMIENTO ORGANIZACIONAL | U3: 136518928 | V3: IG 332901003 | W3: 136518928 | X3: 11376578 | AA3: SECRETARÍA_GENERAL | AB3: =IFERROR(VLOOKUP(AA3,Listas!$A$1:$C$14,2,FALSE),"") -> FREDY CÉSPEDES VILLA | AC3: =IFERROR(VLOOKUP(AA3,Listas!$A$1:$C$14,3,FALSE),"") -> 93363483 | AD3: SECRETARÍA_GENERAL | AE3: COORDINADOR(A) GRUPO DE CONTRATACIÓN | AF3: =IFERROR(VLOOKUP(AE3,Listas!$AD$1:$AF$66,2,FALSE),"") -> DIANA BARRERA MEDINA | AG3: =IFERROR(VLOOKUP(AE3,Listas!$AD$1:$AF$65,3,FALSE),"") -> 52964360 | AH3: 1 CONTRATACION DIRECTA | AJ3: 1 SI | AK3: 1 PUBLICADO | AL3: 1 PUBLICADO | AM3: 1 SI | AN3: 33143 | AO3: =IF(YEAR(TODAY())-YEAR(AN3)>100," ",YEAR(TODAY())-YEAR(AN3)) -> 35 | AP3: GRUPO_DE_CONTRATACIÓN | AQ3: LAURA NARANJO | BF3: =BC3+BE3 -> 0 | BI3: =BF3+Q3 -> 361 | BJ3: =IF(BH3="",P3+BF3,BH3) -> 45656 | CC3: =BR3+BV3+BZ3 -> 0 | CE3: =IF(Y3=0,(W3+CC3)-CD3,IF(Y3>0,(Y3+CC3)-CD3)) -> 136518928 | CG3: =IFERROR(IF(((CE3/BI3)*(TODAY()-N3))>CE3,CE3,((CE3/BI3)*(TODAY()-N3))),"") -> 136518928 | CH3: =IF(TODAY()>BJ3,1,+(DAYS360(O3,TODAY())/DAYS360(O3,BJ3))) -> 1 | CI3: =+IF(CL3>0,DAYS360(O3,CL3)/DAYS360(O3,BJ3),CH3) -> 1 | CJ3: =IFERROR(IF(((CG3/CE3)*100)>100,100,((CG3/CE3)*100)),"") -> 100 | CK3: =IFERROR((CF3/CE3)*100,"") -> 0 | CM3: =IF(CL3>1/1/6,"LIQUIDADO",IF(BJ3=0,"",IF(BJ3>=TODAY(),"VIGENTE",IF(BJ3<TODAY(),"TERMINADO",)))) -> TERMINADO | CP3: FEMENINO
A4: 13.24 | B4: 2024-0003 | C4: CTO | D4: CD-003-2024 | E4: 9 PRESTACIÓN DE SERVICIOS | F4: 1 PERSONA NATURAL | G4: 3 CÉDULA DE CIUDADANÍA | H4: 1090501792 | I4: LAURA MARCELA LUQUE PINEDO | L4: 13.24 PRESTACIÓN DE SERVICIOS PROFESIONALES EN DERECHO PARA BRINDAR ASESORÍA JURÍDICA EN LAS DIFERENTES ETAPAS DE LA ACTIVIDAD CONTRACTUAL DE ACUERDO CON LAS POLÍTICAS DE CELEBRACIÓN Y EJECUCIÓN DE CONTRATOS EN EL MARCO DEL "PROYECTO DE FORTALECIMIENTO ORGANIZACIONAL" DEL ICETEX. | M4: BOGOTA | N4: 45294 | O4: 45294 | P4: 45656 | Q4: =P4-O4 -> 362 | R4: 2 INVERSIÓN | S4: CDEF-12-2024 | T4: FORTALECIMIENTO ORGANIZACIONAL | U4: 117702036 | V4: IG 332901003 | W4: 117702036 | X4: 9808503 | AA4: SECRETARÍA_GENERAL | AB4: =IFERROR(VLOOKUP(AA4,Listas!$A$1:$C$14,2,FALSE),"") -> FREDY CÉSPEDES VILLA | AC4: =IFERROR(VLOOKUP(AA4,Listas!$A$1:$C$14,3,FALSE),"") -> 93363483 | AD4: SECRETARÍA_GENERAL | AE4: COORDINADOR(A) GRUPO DE CONTRATACIÓN | AF4: =IFERROR(VLOOKUP(AE4,Listas!$AD$1:$AF$66,2,FALSE),"") -> DIANA BARRERA MEDINA | AG4: =IFERROR(VLOOKUP(AE4,Listas!$AD$1:$AF$65,3,FALSE),"") -> 52964360 | AH4: 1 CONTRATACION DIRECTA | AJ4: 1 SI | AK4: 1 PUBLICADO | AL4: 1 PUBLICADO | AM4: 1 SI | AN4: 35377 | AO4: =IF(YEAR(TODAY())-YEAR(AN4)>100," ",YEAR(TODAY())-YEAR(AN4)) -> 29 | AP4: GRUPO_DE_CONTRATACIÓN | AQ4: LAURA NARANJO | BF4: =BC4+BE4 -> 0 | BI4: =BF4+Q4 -> 362 | BJ4: =IF(BH4="",P4+BF4,BH4) -> 45656 | CC4: =BR4+BV4+BZ4 -> 0 | CE4: =IF(Y4=0,(W4+CC4)-CD4,IF(Y4>0,(Y4+CC4)-CD4)) -> 117702036 | CG4: =IFERROR(IF(((CE4/BI4)*(TODAY()-N4))>CE4,CE4,((CE4/BI4)*(TODAY()-N4))),"") -> 117702036 | CH4: =IF(TODAY()>BJ4,1,+(DAYS360(O4,TODAY())/DAYS360(O4,BJ4))) -> 1 | CI4: =+IF(CL4>0,DAYS360(O4,CL4)/DAYS360(O4,BJ4),CH4) -> 1 | CJ4: =IFERROR(IF(((CG4/CE4)*100)>100,100,((CG4/CE4)*100)),"") -> 100 | CK4: =IFERROR((CF4/CE4)*100,"") -> 0 | CM4: =IF(CL4>1/1/6,"LIQUIDADO",IF(BJ4=0,"",IF(BJ4>=TODAY(),"VIGENTE",IF(BJ4<TODAY(),"TERMINADO",)))) -> TERMINADO | CP4: FEMENINO
A5: 13.43 | B5: 2024-0004 | C5: CTO | D5: CD-004-2024 | E5: 9 PRESTACIÓN DE SERVICIOS | F5: 1 PERSONA NATURAL | G5: 3 CÉDULA DE CIUDADANÍA | H5: 1026294532 | I5: LUIS ESTEBAN REYES ARIAS | L5: 13.43 PRESTACIÓN DE SERVICIOS PROFESIONALES PARA APOYAR EL IMPULSO DE LOS PROCESOS, PROCEDIMIENTOS Y TRÁMITE EN LA GESTIÓN DE LA POLÍTICA DE COMPRAS PÚBLICAS Y DE CONTRATACIÓN EN EL MARCO DEL PROYECTO DE "FORTALECIMIENTO ORGANIZACIONAL" DEL ICETEX | M5: BOGOTA | N5: 45294 | O5: 45295 | P5: 45656 | Q5: =P5-O5 -> 361 | R5: 2 INVERSIÓN | S5: CDEF-28-2024 | T5: FORTALECIMIENTO ORGANIZACIONAL | U5: 69144665 | V5: IG 332901003 | W5: 69144665 | X5: 5762055 | AA5: SECRETARÍA_GENERAL | AB5: =IFERROR(VLOOKUP(AA5,Listas!$A$1:$C$14,2,FALSE),"") -> FREDY CÉSPEDES VILLA | AC5: =IFERROR(VLOOKUP(AA5,Listas!$A$1:$C$14,3,FALSE),"") -> 93363483 | AD5: SECRETARÍA_GENERAL | AE5: COORDINADOR(A) GRUPO DE CONTRATACIÓN | AF5: =IFERROR(VLOOKUP(AE5,Listas!$AD$1:$AF$66,2,FALSE),"") -> DIANA BARRERA MEDINA | AG5: =IFERROR(VLOOKUP(AE5,Listas!$AD$1:$AF$65,3,FALSE),"") -> 52964360 | AH5: 1 CONTRATACION DIRECTA | AJ5: 1 SI | AK5: 1 PUBLICADO | AL5: 1 PUBLICADO | AM5: 1 SI | AN5: 35135 | AO5: =IF(YEAR(TODAY())-YEAR(AN5)>100," ",YEAR(TODAY())-YEAR(AN5)) -> 29 | AP5: GRUPO_DE_CONTRATACIÓN | AQ5: LAURA NARANJO | BF5: =BC5+BE5 -> 0 | BI5: =BF5+Q5 -> 361 | BJ5: =IF(BH5="",P5+BF5,BH5) -> 45656 | CC5: =BR5+BV5+BZ5 -> 0 | CE5: =IF(Y5=0,(W5+CC5)-CD5,IF(Y5>0,(Y5+CC5)-CD5)) -> 69144665 | CG5: =IFERROR(IF(((CE5/BI5)*(TODAY()-N5))>CE5,CE5,((CE5/BI5)*(TODAY()-N5))),"") -> 69144665 | CH5: =IF(TODAY()>BJ5,1,+(DAYS360(O5,TODAY())/DAYS360(O5,BJ5))) -> 1 | CI5: =+IF(CL5>0,DAYS360(O5,CL5)/DAYS360(O5,BJ5),CH5) -> 1 | CJ5: =IFERROR(IF(((CG5/CE5)*100)>100,100,((CG5/CE5)*100)),"") -> 100 | CK5: =IFERROR((CF5/CE5)*100,"") -> 0 | CM5: =IF(CL5>1/1/6,"LIQUIDADO",IF(BJ5=0,"",IF(BJ5>=TODAY(),"VIGENTE",IF(BJ5<TODAY(),"TERMINADO",)))) -> TERMINADO | CP5: MASCULINO
A6: 13.33 | B6: 2024-0005 | C6: CTO | D6: CD-005-2024 | E6: 9 PRESTACIÓN DE SERVICIOS | F6: 1 PERSONA NATURAL | G6: 3 CÉDULA DE CIUDADANÍA | H6: 1094927338 | I6: LAURA NARANJO JARAMILLO | L6: 13.33 PRESTACIÓN DE SERVICIOS PROFESIONALES COMO ABOGADO PARA APOYAR EL DESARROLLO Y SEGUIMIENTO DE LA ACTIVIDAD CONTRACTUAL EN EL MARCO DEL PROYECTO DE FORTALECIMIENTO ORGANIZACIONAL Y LA IMPLEMENTACIÓN DE LA POLÍTICA DE COMPRAS PÚBLICAS Y DE CONTRATACIÓN DEL ICETEX | M6: BOGOTA | N6: 45294 | O6: 45294 | P6: 45656 | Q6: =P6-O6 -> 362 | R6: 2 INVERSIÓN | S6: CDEF-19-2024 | T6: FORTALECIMIENTO ORGANIZACIONAL | U6: 102790731 | V6: IG 332901003 | W6: 102790731 | X6: 8565894 | AA6: SECRETARÍA_GENERAL | AB6: =IFERROR(VLOOKUP(AA6,Listas!$A$1:$C$14,2,FALSE),"") -> FREDY CÉSPEDES VILLA | AC6: =IFERROR(VLOOKUP(AA6,Listas!$A$1:$C$14,3,FALSE),"") -> 93363483 | AD6: SECRETARÍA_GENERAL | AE6: COORDINADOR(A) GRUPO DE CONTRATACIÓN | AF6: =IFERROR(VLOOKUP(AE6,Listas!$AD$1:$AF$66,2,FALSE),"") -> DIANA BARRERA MEDINA | AG6: =IFERROR(VLOOKUP(AE6,Listas!$AD$1:$AF$65,3,FALSE),"") -> 52964360 | AH6: 1 CONTRATACION DIRECTA | AJ6: 1 SI | AK6: 1 PUBLICADO | AL6: 1 PUBLICADO | AM6: 1 SI | AN6: 33732 | AO6: =IF(YEAR(TODAY())-YEAR(AN6)>100," ",YEAR(TODAY())-YEAR(AN6)) -> 33 | AP6: GRUPO_DE_CONTRATACIÓN | AQ6: LAURA NARANJO | BF6: =BC6+BE6 -> 0 | BI6: =BF6+Q6 -> 362 | BJ6: =IF(BH6="",P6+BF6,BH6) -> 45656 | CC6: =BR6+BV6+BZ6 -> 0 | CE6: =IF(Y6=0,(W6+CC6)-CD6,IF(Y6>0,(Y6+CC6)-CD6)) -> 102790731 | CG6: =IFERROR(IF(((CE6/BI6)*(TODAY()-N6))>CE6,CE6,((CE6/BI6)*(TODAY()-N6))),"") -> 102790731 | CH6: =IF(TODAY()>BJ6,1,+(DAYS360(O6,TODAY())/DAYS360(O6,BJ6))) -> 1 | CI6: =+IF(CL6>0,DAYS360(O6,CL6)/DAYS360(O6,BJ6),CH6) -> 1 | CJ6: =IFERROR(IF(((CG6/CE6)*100)>100,100,((CG6/CE6)*100)),"") -> 100 | CK6: =IFERROR((CF6/CE6)*100,"") -> 0 | CM6: =IF(CL6>1/1/6,"LIQUIDADO",IF(BJ6=0,"",IF(BJ6>=TODAY(),"VIGENTE",IF(BJ6<TODAY(),"TERMINADO",)))) -> TERMINADO | CP6: FEMENINO
A7: 13.28 | B7: 2024-0006 | C7: CTO | D7: CD-006-2024 | E7: 9 PRESTACIÓN DE SERVICIOS | F7: 1 PERSONA NATURAL | G7: 3 CÉDULA DE CIUDADANÍA | H7: 1026288361 | I7: DAHYANNA JIMENA ANGARITA SALAZAR | L7: 13.28 PRESTACIÓN DE SERVICIOS PROFESIONALES COMO ABOGADO PARA APOYAR EL DESARROLLO Y SEGUIMIENTO DE LA ACTIVIDAD CONTRACTUAL EN EL MARCO DEL PROYECTO DE FORTALECIMIENTO ORGANIZACIONAL Y LA IMPLEMENTACIÓN DE LA POLÍTICA DE COMPRAS PÚBLICAS Y DE CONTRATACIÓN DEL ICETEX | M7: BOGOTA | N7: 45294 | O7: 45295 | P7: 45656 | Q7: =P7-O7 -> 361 | R7: 2 INVERSIÓN | S7: CDEF-15-2024 | T7: FORTALECIMIENTO ORGANIZACIONAL | U7: 102790731 | V7: IG 332901003 | W7: 102790731 | X7: 8565894 | AA7: SECRETARÍA_GENERAL | AB7: =IFERROR(VLOOKUP(AA7,Listas!$A$1:$C$14,2,FALSE),"") -> FREDY CÉSPEDES VILLA | AC7: =IFERROR(VLOOKUP(AA7,Listas!$A$1:$C$14,3,FALSE),"") -> 93363483 | AD7: SECRETARÍA_GENERAL | AE7: COORDINADOR(A) GRUPO DE CONTRATACIÓN | AF7: =IFERROR(VLOOKUP(AE7,Listas!$AD$1:$AF$66,2,FALSE),"") -> DIANA BARRERA MEDINA | AG7: =IFERROR(VLOOKUP(AE7,Listas!$AD$1:$AF$65,3,FALSE),"") -> 52964360 | AH7: 1 CONTRATACION DIRECTA | AJ7: 1 SI | AK7: 1 PUBLICADO | AL7: 1 PUBLICADO | AM7: 1 SI | AN7: 34492 | AO7: =IF(YEAR(TODAY())-YEAR(AN7)>100," ",YEAR(TODAY())-YEAR(AN7)) -> 31 | AP7: GRUPO_DE_CONTRATACIÓN | AQ7: LAURA NARANJO | BF7: =BC7+BE7 -> 0 | BI7: =BF7+Q7 -> 361 | BJ7: =IF(BH7="",P7+BF7,BH7) -> 45656 | CC7: =BR7+BV7+BZ7 -> 0 | CE7: =IF(Y7=0,(W7+CC7)-CD7,IF(Y7>0,(Y7+CC7)-CD7)) -> 102790731 | CG7: =IFERROR(IF(((CE7/BI7)*(TODAY()-N7))>CE7,CE7,((CE7/BI7)*(TODAY()-N7))),"") -> 102790731 | CH7: =IF(TODAY()>BJ7,1,+(DAYS360(O7,TODAY())/DAYS360(O7,BJ7))) -> 1 | CI7: =+IF(CL7>0,DAYS360(O7,CL7)/DAYS360(O7,BJ7),CH7) -> 1 | CJ7: =IFERROR(IF(((CG7/CE7)*100)>100,100,((CG7/CE7)*100)),"") -> 100 | CK7: =IFERROR((CF7/CE7)*100,"") -> 0 | CM7: =IF(CL7>1/1/6,"LIQUIDADO",IF(BJ7=0,"",IF(BJ7>=TODAY(),"VIGENTE",IF(BJ7<TODAY(),"TERMINADO",)))) -> TERMINADO | CP7: FEMENINO
A8: 13.27 | B8: 2024-0007 | C8: CTO | D8: CD-007-2024 | E8: 9 PRESTACIÓN DE SERVICIOS | F8: 1 PERSONA NATURAL | G8: 3 CÉDULA DE CIUDADANÍA | H8: 65748384 | I8: INGRID ZULIN PINEDO TOCORA | L8: 13.27 PRESTACIÓN DE SERVICIOS PROFESIONALES COMO ABOGADO PARA APOYAR EL DESARROLLO Y SEGUIMIENTO DE LA ACTIVIDAD CONTRACTUAL EN EL MARCO DEL PROYECTO DE FORTALECIMIENTO ORGANIZACIONAL Y LA IMPLEMENTACIÓN DE LA POLÍTICA DE COMPRAS PÚBLICAS Y DE CONTRATACIÓN DEL ICETEX | M8: BOGOTA | N8: 45294 | O8: 45294 | P8: 45656 | Q8: =P8-O8 -> 362 | R8: 2 INVERSIÓN | S8: CDEF-14-2024 | T8: FORTALECIMIENTO ORGANIZACIONAL | U8: 102790731 | V8: IG 332901003 | W8: 102790731 | X8: 8565894 | AA8: SECRETARÍA_GENERAL | AB8: =IFERROR(VLOOKUP(AA8,Listas!$A$1:$C$14,2,FALSE),"") -> FREDY CÉSPEDES VILLA | AC8: =IFERROR(VLOOKUP(AA8,Listas!$A$1:$C$14,3,FALSE),"") -> 93363483 | AD8: SECRETARÍA_GENERAL | AE8: COORDINADOR(A) GRUPO DE CONTRATACIÓN | AF8: =IFERROR(VLOOKUP(AE8,Listas!$AD$1:$AF$66,2,FALSE),"") -> DIANA BARRERA MEDINA | AG8: =IFERROR(VLOOKUP(AE8,Listas!$AD$1:$AF$65,3,FALSE),"") -> 52964360 | AH8: 1 CONTRATACION DIRECTA | AJ8: 1 SI | AK8: 1 PUBLICADO | AL8: 1 PUBLICADO | AM8: 1 SI | AN8: 25891 | AO8: =IF(YEAR(TODAY())-YEAR(AN8)>100," ",YEAR(TODAY())-YEAR(AN8)) -> 55 | AP8: GRUPO_DE_CONTRATACIÓN | AQ8: LAURA NARANJO | BF8: =BC8+BE8 -> 0 | BI8: =BF8+Q8 -> 362 | BJ8: =IF(BH8="",P8+BF8,BH8) -> 45656 | CC8: =BR8+BV8+BZ8 -> 0 | CE8: =IF(Y8=0,(W8+CC8)-CD8,IF(Y8>0,(Y8+CC8)-CD8)) -> 102790731 | CG8: =IFERROR(IF(((CE8/BI8)*(TODAY()-N8))>CE8,CE8,((CE8/BI8)*(TODAY()-N8))),"") -> 102790731 | CH8: =IF(TODAY()>BJ8,1,+(DAYS360(O8,TODAY())/DAYS360(O8,BJ8))) -> 1 | CI8: =+IF(CL8>0,DAYS360(O8,CL8)/DAYS360(O8,BJ8),CH8) -> 1 | CJ8: =IFERROR(IF(((CG8/CE8)*100)>100,100,((CG8/CE8)*100)),"") -> 100 | CK8: =IFERROR((CF8/CE8)*100,"") -> 0 | CM8: =IF(CL8>1/1/6,"LIQUIDADO",IF(BJ8=0,"",IF(BJ8>=TODAY(),"VIGENTE",IF(BJ8<TODAY(),"TERMINADO",)))) -> TERMINADO | CP8: FEMENINO
A9: 13.29 | B9: 2024-0008 | C9: CTO | D9: CD-008-2024 | E9: 9 PRESTACIÓN DE SERVICIOS | F9: 1 PERSONA NATURAL | G9: 3 CÉDULA DE CIUDADANÍA | H9: 37898247 | I9: DIANA MARÍA GONZALEZ GORDILLO | L9: 13.29 PRESTACIÓN DE SERVICIOS PROFESIONALES COMO ABOGADO PARA APOYAR EL DESARROLLO Y SEGUIMIENTO DE LA ACTIVIDAD CONTRACTUAL EN EL MARCO DEL PROYECTO DE FORTALECIMIENTO ORGANIZACIONAL Y LA IMPLEMENTACIÓN DE LA POLÍTICA DE COMPRAS PÚBLICAS Y DE CONTRATACIÓN DEL ICETEX | M9: BOGOTA | N9: 45294 | O9: 45294 | P9: 45475 | Q9: =P9-O9 -> 181 | R9: 2 INVERSIÓN | S9: CDEF-16-2024 | T9: FORTALECIMIENTO ORGANIZACIONAL | U9: 102790731 | V9: IG 332901003 | W9: 102790731 | X9: 8565894 | AA9: SECRETARÍA_GENERAL | AB9: =IFERROR(VLOOKUP(AA9,Listas!$A$1:$C$14,2,FALSE),"") -> FREDY CÉSPEDES VILLA | AC9: =IFERROR(VLOOKUP(AA9,Listas!$A$1:$C$14,3,FALSE),"") -> 93363483 | AD9: SECRETARÍA_GENERAL | AE9: COORDINADOR(A) GRUPO DE CONTRATACIÓN | AF9: =IFERROR(VLOOKUP(AE9,Listas!$AD$1:$AF$66,2,FALSE),"") -> DIANA BARRERA MEDINA | AG9: =IFERROR(VLOOKUP(AE9,Listas!$AD$1:$AF$65,3,FALSE),"") -> 52964360 | AH9: 1 CONTRATACION DIRECTA | AJ9: 1 SI | AK9: 1 PUBLICADO | AL9: 1 PUBLICADO | AM9: 1 SI | AN9: 29128 | AO9: =IF(YEAR(TODAY())-YEAR(AN9)>100," ",YEAR(TODAY())-YEAR(AN9)) -> 46 | AP9: GRUPO_DE_CONTRATACIÓN | AQ9: LAURA NARANJO | BF9: =BC9+BE9 -> 0 | BI9: =BF9+Q9 -> 181 | BJ9: =IF(BH9="",P9+BF9,BH9) -> 45475 | CC9: =BR9+BV9+BZ9 -> 0 | CE9: =IF(Y9=0,(W9+CC9)-CD9,IF(Y9>0,(Y9+CC9)-CD9)) -> 102790731 | CG9: =IFERROR(IF(((CE9/BI9)*(TODAY()-N9))>CE9,CE9,((CE9/BI9)*(TODAY()-N9))),"") -> 102790731 | CH9: =IF(TODAY()>BJ9,1,+(DAYS360(O9,TODAY())/DAYS360(O9,BJ9))) -> 1 | CI9: =+IF(CL9>0,DAYS360(O9,CL9)/DAYS360(O9,BJ9),CH9) -> 1 | CJ9: =IFERROR(IF(((CG9/CE9)*100)>100,100,((CG9/CE9)*100)),"") -> 100 | CK9: =IFERROR((CF9/CE9)*100,"") -> 0 | CM9: =IF(CL9>1/1/6,"LIQUIDADO",IF(BJ9=0,"",IF(BJ9>=TODAY(),"VIGENTE",IF(BJ9<TODAY(),"TERMINADO",)))) -> TERMINADO | CP9: FEMENINO
A10: 13.30 | B10: 2024-0009 | C10: CTO | D10: CD-009-2024 | E10: 9 PRESTACIÓN DE SERVICIOS | F10: 1 PERSONA NATURAL | G10: 3 CÉDULA DE CIUDADANÍA | H10: 1018405589 | I10: DIANA CAROLINA GUEVARA ESCOBAR | L10: 13.30 PRESTACIÓN DE SERVICIOS PROFESIONALES COMO ABOGADO PARA APOYAR EL DESARROLLO Y SEGUIMIENTO DE LA ACTIVIDAD CONTRACTUAL EN EL MARCO DEL PROYECTO DE FORTALECIMIENTO ORGANIZACIONAL Y LA IMPLEMENTACIÓN DE LA POLÍTICA DE COMPRAS PÚBLICAS Y DE CONTRATACIÓN DEL ICETEX | M10: BOGOTA | N10: 45294 | O10: 45295 | P10: 45656 | Q10: =P10-O10 -> 361 | R10: 2 INVERSIÓN | S10: CDEF-17-2024 | T10: FORTALECIMIENTO ORGANIZACIONAL | U10: 102790731 | V10: IG 332901003 | W10: 102790731 | X10: 8565894 | AA10: SECRETARÍA_GENERAL | AB10: =IFERROR(VLOOKUP(AA10,Listas!$A$1:$C$14,2,FALSE),"") -> FREDY CÉSPEDES VILLA | AC10: =IFERROR(VLOOKUP(AA10,Listas!$A$1:$C$14,3,FALSE),"") -> 93363483 | AD10: SECRETARÍA_GENERAL | AE10: COORDINADOR(A) GRUPO DE CONTRATACIÓN | AF10: =IFERROR(VLOOKUP(AE10,Listas!$AD$1:$AF$66,2,FALSE),"") -> DIANA BARRERA MEDINA | AG10: =IFERROR(VLOOKUP(AE10,Listas!$AD$1:$AF$65,3,FALSE),"") -> 52964360 | AH10: 1 CONTRATACION DIRECTA | AJ10: 1 SI | AK10: 1 PUBLICADO | AL10: 1 PUBLICADO | AM10: 1 SI | AN10: 28650 | AO10: =IF(YEAR(TODAY())-YEAR(AN10)>100," ",YEAR(TODAY())-YEAR(AN10)) -> 47 | AP10: GRUPO_DE_CONTRATACIÓN | AQ10: LAURA NARANJO | BF10: =BC10+BE10 -> 0 | BI10: =BF10+Q10 -> 361 | BJ10: =IF(BH10="",P10+BF10,BH10) -> 45656 | CC10: =BR10+BV10+BZ10 -> 0 | CE10: =IF(Y10=0,(W10+CC10)-CD10,IF(Y10>0,(Y10+CC10)-CD10)) -> 102790731 | CG10: =IFERROR(IF(((CE10/BI10)*(TODAY()-N10))>CE10,CE10,((CE10/BI10)*(TODAY()-N10))),"") -> 102790731 | CH10: =IF(TODAY()>BJ10,1,+(DAYS360(O10,TODAY())/DAYS360(O10,BJ10))) -> 1 | CI10: =+IF(CL10>0,DAYS360(O10,CL10)/DAYS360(O10,BJ10),CH10) -> 1 | CJ10: =IFERROR(IF(((CG10/CE10)*100)>100,100,((CG10/CE10)*100)),"") -> 100 | CK10: =IFERROR((CF10/CE10)*100,"") -> 0 | CM10: =IF(CL10>1/1/6,"LIQUIDADO",IF(BJ10=0,"",IF(BJ10>=TODAY(),"VIGENTE",IF(BJ10<TODAY(),"TERMINADO",)))) -> TERMINADO | CP10: FEMENINO
A11: 13.34 | B11: 2024-0010 | C11: CTO | D11: CD-010-2024 | E11: 9 PRESTACIÓN DE SERVICIOS | F11: 1 PERSONA NATURAL | G11: 3 CÉDULA DE CIUDADANÍA | H11: 79855988 | I11: JOSE GREGORIO SARMIENTO ORTIZ | L11: 13.34 PRESTACIÓN DE SERVICIOS PROFESIONALES COMO ABOGADO PARA APOYAR EL DESARROLLO Y SEGUIMIENTO DE LA ACTIVIDAD CONTRACTUAL EN EL MARCO DEL PROYECTO DE FORTALECIMIENTO ORGANIZACIONAL Y LA IMPLEMENTACIÓN DE LA POLÍTICA DE COMPRAS PÚBLICAS Y DE CONTRATACIÓN DEL ICETEX | M11: BOGOTA | N11: 45293 | O11: 45294 | P11: 45656 | Q11: =P11-O11 -> 362 | R11: 2 INVERSIÓN | S11: CDEF-20-2024 | T11: FORTALECIMIENTO ORGANIZACIONAL | U11: 102790731 | V11: IG 332901003 | W11: 102790731 | X11: 8565894 | AA11: SECRETARÍA_GENERAL | AB11: =IFERROR(VLOOKUP(AA11,Listas!$A$1:$C$14,2,FALSE),"") -> FREDY CÉSPEDES VILLA | AC11: =IFERROR(VLOOKUP(AA11,Listas!$A$1:$C$14,3,FALSE),"") -> 93363483 | AD11: SECRETARÍA_GENERAL | AE11: COORDINADOR(A) GRUPO DE CONTRATACIÓN | AF11: =IFERROR(VLOOKUP(AE11,Listas!$AD$1:$AF$66,2,FALSE),"") -> DIANA BARRERA MEDINA | AG11: =IFERROR(VLOOKUP(AE11,Listas!$AD$1:$AF$65,3,FALSE),"") -> 52964360 | AH11: 1 CONTRATACION DIRECTA | AJ11: 1 SI | AK11: 1 PUBLICADO | AL11: 1 PUBLICADO | AM11: 1 SI | AN11: 28874 | AO11: =IF(YEAR(TODAY())-YEAR(AN11)>100," ",YEAR(TODAY())-YEAR(AN11)) -> 46 | AP11: GRUPO_DE_CONTRATACIÓN | AQ11: LAURA NARANJO | BF11: =BC11+BE11 -> 0 | BI11: =BF11+Q11 -> 362 | BJ11: =IF(BH11="",P11+BF11,BH11) -> 45656 | CC11: =BR11+BV11+BZ11 -> 0 | CE11: =IF(Y11=0,(W11+CC11)-CD11,IF(Y11>0,(Y11+CC11)-CD11)) -> 102790731 | CG11: =IFERROR(IF(((CE11/BI11)*(TODAY()-N11))>CE11,CE11,((CE11/BI11)*(TODAY()-N11))),"") -> 102790731 | CH11: =IF(TODAY()>BJ11,1,+(DAYS360(O11,TODAY())/DAYS360(O11,BJ11))) -> 1 | CI11: =+IF(CL11>0,DAYS360(O11,CL11)/DAYS360(O11,BJ11),CH11) -> 1 | CJ11: =IFERROR(IF(((CG11/CE11)*100)>100,100,((CG11/CE11)*100)),"") -> 100 | CK11: =IFERROR((CF11/CE11)*100,"") -> 0 | CM11: =IF(CL11>1/1/6,"LIQUIDADO",IF(BJ11=0,"",IF(BJ11>=TODAY(),"VIGENTE",IF(BJ11<TODAY(),"TERMINADO",)))) -> TERMINADO | CP11: MASCULINO
A12: 13.35 | B12: 2024-0011 | C12: CTO | D12: CD-011-2024 | E12: 9 PRESTACIÓN DE SERVICIOS | F12: 1 PERSONA NATURAL | G12: 3 CÉDULA DE CIUDADANÍA | H12: 1075291011 | I12: JUAN CAMILO CEDIEL BORRERO | L12: 13.35 PRESTACIÓN DE SERVICIOS PROFESIONALES COMO ABOGADO PARA APOYAR EL DESARROLLO Y SEGUIMIENTO DE LA ACTIVIDAD CONTRACTUAL EN EL MARCO DEL PROYECTO DE FORTALECIMIENTO ORGANIZACIONAL Y LA IMPLEMENTACIÓN DE LA POLÍTICA DE COMPRAS PÚBLICAS Y DE CONTRATACIÓN DEL ICETEX | M12: BOGOTA | N12: 45293 | O12: 45294 | P12: 45656 | Q12: =P12-O12 -> 362 | R12: 2 INVERSIÓN | S12: CDEF-21-2024 | T12: FORTALECIMIENTO ORGANIZACIONAL | U12: 102790731 | V12: IG 332901003 | W12: 102790731 | X12: 8565894 | AA12: SECRETARÍA_GENERAL | AB12: =IFERROR(VLOOKUP(AA12,Listas!$A$1:$C$14,2,FALSE),"") -> FREDY CÉSPEDES VILLA | AC12: =IFERROR(VLOOKUP(AA12,Listas!$A$1:$C$14,3,FALSE),"") -> 93363483 | AD12: SECRETARÍA_GENERAL | AE12: COORDINADOR(A) GRUPO DE CONTRATACIÓN | AF12: =IFERROR(VLOOKUP(AE12,Listas!$AD$1:$AF$66,2,FALSE),"") -> DIANA BARRERA MEDINA | AG12: =IFERROR(VLOOKUP(AE12,Listas!$AD$1:$AF$65,3,FALSE),"") -> 52964360 | AH12: 1 CONTRATACION DIRECTA | AJ12: 1 SI | AK12: 1 PUBLICADO | AL12: 1 PUBLICADO | AM12: 1 SI | AN12: 34943 | AO12: =IF(YEAR(TODAY())-YEAR(AN12)>100," ",YEAR(TODAY())-YEAR(AN12)) -> 30 | AP12: GRUPO_DE_CONTRATACIÓN | AQ12: LAURA NARANJO | BF12: =BC12+BE12 -> 0 | BI12: =BF12+Q12 -> 362 | BJ12: =IF(BH12="",P12+BF12,BH12) -> 45656 | CC12: =BR12+BV12+BZ12 -> 0 | CE12: =IF(Y12=0,(W12+CC12)-CD12,IF(Y12>0,(Y12+CC12)-CD12)) -> 102790731 | CG12: =IFERROR(IF(((CE12/BI12)*(TODAY()-N12))>CE12,CE12,((CE12/BI12)*(TODAY()-N12))),"") -> 102790731 | CH12: =IF(TODAY()>BJ12,1,+(DAYS360(O12,TODAY())/DAYS360(O12,BJ12))) -> 1 | CI12: =+IF(CL12>0,DAYS360(O12,CL12)/DAYS360(O12,BJ12),CH12) -> 1 | CJ12: =IFERROR(IF(((CG12/CE12)*100)>100,100,((CG12/CE12)*100)),"") -> 100 | CK12: =IFERROR((CF12/CE12)*100,"") -> 0 | CM12: =IF(CL12>1/1/6,"LIQUIDADO",IF(BJ12=0,"",IF(BJ12>=TODAY(),"VIGENTE",IF(BJ12<TODAY(),"TERMINADO",)))) -> TERMINADO | CP12: MASCULINO
A13: 13.36 | B13: 2024-0012 | C13: CTO | D13: CD-012-2024 | E13: 9 PRESTACIÓN DE SERVICIOS | F13: 1 PERSONA NATURAL | G13: 3 CÉDULA DE CIUDADANÍA | H13: 80161275 | I13: BRESMAN GUSTAVO SANCHEZ OSPINA | L13: 13.36 PRESTACIÓN DE SERVICIOS PROFESIONALES COMO ABOGADO PARA APOYAR EL DESARROLLO Y SEGUIMIENTO DE LA ACTIVIDAD CONTRACTUAL EN EL MARCO DEL PROYECTO DE FORTALECIMIENTO ORGANIZACIONAL Y LA IMPLEMENTACIÓN DE LA POLÍTICA DE COMPRAS PÚBLICAS Y DE CONTRATACIÓN DEL ICETEX | M13: BOGOTA | N13: 45293 | O13: 45294 | P13: 45656 | Q13: =P13-O13 -> 362 | R13: 2 INVERSIÓN | S13: CDEF-22-2024 | T13: FORTALECIMIENTO ORGANIZACIONAL | U13: 102790731 | V13: IG 332901003 | W13: 102790731 | X13: 8565894 | AA13: SECRETARÍA_GENERAL | AB13: =IFERROR(VLOOKUP(AA13,Listas!$A$1:$C$14,2,FALSE),"") -> FREDY CÉSPEDES VILLA | AC13: =IFERROR(VLOOKUP(AA13,Listas!$A$1:$C$14,3,FALSE),"") -> 93363483 | AD13: SECRETARÍA_GENERAL | AE13: COORDINADOR(A) GRUPO DE CONTRATACIÓN | AF13: =IFERROR(VLOOKUP(AE13,Listas!$AD$1:$AF$66,2,FALSE),"") -> DIANA BARRERA MEDINA | AG13: =IFERROR(VLOOKUP(AE13,Listas!$AD$1:$AF$65,3,FALSE),"") -> 52964360 | AH13: 1 CONTRATACION DIRECTA | AJ13: 1 SI | AK13: 1 PUBLICADO | AL13: 1 PUBLICADO | AM13: 1 SI | AN13: 30344 | AO13: =IF(YEAR(TODAY())-YEAR(AN13)>100," ",YEAR(TODAY())-YEAR(AN13)) -> 42 | AP13: GRUPO_DE_CONTRATACIÓN | AQ13: LAURA NARANJO | BF13: =BC13+BE13 -> 0 | BI13: =BF13+Q13 -> 362 | BJ13: =IF(BH13="",P13+BF13,BH13) -> 45656 | CC13: =BR13+BV13+BZ13 -> 0 | CE13: =IF(Y13=0,(W13+CC13)-CD13,IF(Y13>0,(Y13+CC13)-CD13)) -> 102790731 | CG13: =IFERROR(IF(((CE13/BI13)*(TODAY()-N13))>CE13,CE13,((CE13/BI13)*(TODAY()-N13))),"") -> 102790731 | CH13: =IF(TODAY()>BJ13,1,+(DAYS360(O13,TODAY())/DAYS360(O13,BJ13))) -> 1 | CI13: =+IF(CL13>0,DAYS360(O13,CL13)/DAYS360(O13,BJ13),CH13) -> 1 | CJ13: =IFERROR(IF(((CG13/CE13)*100)>100,100,((CG13/CE13)*100)),"") -> 100 | CK13: =IFERROR((CF13/CE13)*100,"") -> 0 | CM13: =IF(CL13>1/1/6,"LIQUIDADO",IF(BJ13=0,"",IF(BJ13>=TODAY(),"VIGENTE",IF(BJ13<TODAY(),"TERMINADO",)))) -> TERMINADO | CP13: MASCULINO
... A16: 13.26 | B16: 2024-0015 | C16: CTO | D16: CD-015-2024 | E16: 9 PRESTACIÓN DE SERVICIOS | F16: 1 PERSONA NATURAL | G16: 3 CÉDULA DE CIUDADANÍA | H16: 1128063454 | I16: DIANA PATRICIA JALLER BUSTILLO | L16: 13.26 PRESTACIÓN DE SERVICIOS PROFESIONALES COMO ABOGADO PARA APOYAR EL DESARROLLO Y SEGUIMIENTO DE LA ACTIVIDAD CONTRACTUAL EN EL MARCO DEL PROYECTO DE FORTALECIMIENTO ORGANIZACIONAL Y LA IMPLEMENTACIÓN DE LA POLÍTICA DE COMPRAS PÚBLICAS Y DE CONTRATACIÓN DEL ICETEX | M16: BOGOTA | N16: 45294 | O16: 45294 | P16: 45476 | Q16: =P16-O16 -> 182 | R16: 2 INVERSIÓN | S16: CDEF-13-2024 | T16: FORTALECIMIENTO ORGANIZACIONAL | U16: 102790731 | V16: IG 332901003 | W16: 102790731 | X16: 8565894 | AA16: SECRETARÍA_GENERAL | AB16: =IFERROR(VLOOKUP(AA16,Listas!$A$1:$C$14,2,FALSE),"") -> FREDY CÉSPEDES VILLA | AC16: =IFERROR(VLOOKUP(AA16,Listas!$A$1:$C$14,3,FALSE),"") -> 93363483 | AD16: SECRETARÍA_GENERAL | AE16: COORDINADOR(A) GRUPO DE CONTRATACIÓN | AF16: =IFERROR(VLOOKUP(AE16,Listas!$AD$1:$AF$66,2,FALSE),"") -> DIANA BARRERA MEDINA | AG16: =IFERROR(VLOOKUP(AE16,Listas!$AD$1:$AF$65,3,FALSE),"") -> 52964360 | AH16: 1 CONTRATACION DIRECTA | AJ16: 1 SI | AK16: 1 PUBLICADO | AL16: 1 PUBLICADO | AM16: 1 SI | AN16: 32393 | AO16: =IF(YEAR(TODAY())-YEAR(AN16)>100," ",YEAR(TODAY())-YEAR(AN16)) -> 37 | AP16: GRUPO_DE_CONTRATACIÓN | AQ16: LAURA NARANJO | BF16: =BC16+BE16 -> 0 | BI16: =BF16+Q16 -> 182 | BJ16: =IF(BH16="",P16+BF16,BH16) -> 45476 | CC16: =BR16+BV16+BZ16 -> 0 | CE16: =IF(Y16=0,(W16+CC16)-CD16,IF(Y16>0,(Y16+CC16)-CD16)) -> 102790731 | CG16: =IFERROR(IF(((CE16/BI16)*(TODAY()-N16))>CE16,CE16,((CE16/BI16)*(TODAY()-N16))),"") -> 102790731 | CH16: =IF(TODAY()>BJ16,1,+(DAYS360(O16,TODAY())/DAYS360(O16,BJ16))) -> 1 | CI16: =+IF(CL16>0,DAYS360(O16,CL16)/DAYS360(O16,BJ16),CH16) -> 1 | CJ16: =IFERROR(IF(((CG16/CE16)*100)>100,100,((CG16/CE16)*100)),"") -> 100 | CK16: =IFERROR((CF16/CE16)*100,"") -> 0 | CM16: =IF(CL16>1/1/6,"LIQUIDADO",IF(BJ16=0,"",IF(BJ16>=TODAY(),"VIGENTE",IF(BJ16<TODAY(),"TERMINADO",)))) -> TERMINADO | CP16: FEMENINO
A17: 12.20 | B17: 2024-0016 | C17: CTO | D17: CD-016-2024 | E17: 9 PRESTACIÓN DE SERVICIOS | F17: 1 PERSONA NATURAL | G17: 3 CÉDULA DE CIUDADANÍA | H17: 1015408521 | I17: GISSET XIMENA BARRETO VILLAMIL | L17: PRESTAR LOS SERVICIOS PROFESIONALES ESPECIALIZADOS EN LA MEJORA DE LOS PROCESOS PRESUPUESTALES ENFOCADOS EN LA PLANEACIÓN, DISEÑO Y DESARROLLO DE MECANISMOS QUE PERMITAN LA INTEGRACIÓN Y EL ANÁLISIS DE INFORMACIÓN PRESUPUESTAL EN EL MARCO DEL PROYECTO DE INVERSIÓN DE BANCA ABIERTA Y TRANSPARENTE E INHOUSE BANKING. | M17: BOGOTA | N17: 45294 | O17: 45294 | P17: 45657 | Q17: =P17-O17 -> 363 | R17: 2 INVERSIÓN | S17: CDEF-05-2024 | T17: BANCA ABIERTA Y TRANSPARENTE E INHOUSE B | U17: 92883552 | V17: IG332902005 | W17: 92883552 | X17: 7740296 | AA17: SECRETARÍA_GENERAL | AB17: =IFERROR(VLOOKUP(AA17,Listas!$A$1:$C$14,2,FALSE),"") -> FREDY CÉSPEDES VILLA | AC17: =IFERROR(VLOOKUP(AA17,Listas!$A$1:$C$14,3,FALSE),"") -> 93363483 | AD17: VICEPRESIDENCIA_FINANCIERA | AE17: COORDINADOR(A) GRUPO DE PRESUPUESTO | AF17: =IFERROR(VLOOKUP(AE17,Listas!$AD$1:$AF$66,2,FALSE),"") -> GISSET XIMENA BARRETO VILLAMIL | AG17: =IFERROR(VLOOKUP(AE17,Listas!$AD$1:$AF$65,3,FALSE),"") -> 1015408521 | AH17: 1 CONTRATACION DIRECTA | AI17: Apoyar en la estructuración de mecanismos de registro, seguimiento y control de operaciones presupuestales relacionadas con vigencias futuras, acorde a los procedimientos establecidos y requeridos en el marco de la modernización de las funciones financieras del Instituto. 2. Proponer iniciativas que propendan por la articulación de actores para la apropiación e implementación de mecanismos para la optimización de los procesos que soportan la operación financiera del Instituto, con especial énfasis en el seguimiento y control de vigencias futuras. 3. Apoyar en el seguimiento y control de los requerimientos relacionados con la mitigación de riesgos del proceso de Gestión Presupuestal, los planes de mejoramiento y los lineamientos impartidos en el marco del proyecto de inversión de banca abierta y transparente. 4. Apoyar la estructuración de insumos técnicos para dar respuesta a los requerimientos de información solicitados por entes internos y/o externos en el marco de los proyectos de inversión Inhouse Banking, 5. Apoyar en la estructuración y conceptualización técnica de iniciativas que permitan la simplificación, estandarización e integración de procesos de la gestión presupuestal del ICETEX en el marco del proyecto de inversión de banca abierta y transparente e In House Banking. 6. Apoyar el diseño, apropiación e implementación de mecanismos para la optimización de los procesos presupuestales que se adelantan en el marco de la modernización de las funciones financieras del Instituto. 7. Apoyar la apropiación e implementación de esquemas de reporte y control a la gestión presupuestal del Instituto en el marco del proyecto de inversión de banca abierta y Código: F451 ESTUDIO PREVIO SIMPLIFICADO Versión: 3 Fecha: 04/12/2023 Página 7 de 13 transparente. 8. Analizar la información generada a partir de las bases de datos presupuestales con el fin de verificar su fidelidad. 9. Las demás obligaciones que se requieran para el cumplimiento a cabalidad del objeto contractual y que sean inherentes a la naturaleza del contrato. 10. Cumplir con los indicadores de gestión establecidos. | AJ17: 1 SI | AK17: 1 PUBLICADO | AL17: 1 PUBLICADO | AM17: 1 SI | AO17: =IF(YEAR(TODAY())-YEAR(AN17)>100," ",YEAR(TODAY())-YEAR(AN17)) | AP17: GRUPO_DE_CONTRATACIÓN | AQ17: SEBASTIAN AYALA | AR17: 45552 | AS17: WILLIAM ALEXANDER VALENCIA NEMOCON | AT17: 80119997 | AU17: PRESTAR LOS SERVICIOS PROFESIONALES ESPECIALIZADOS EN LA MEJORA DE LOS PROCESOS PRESUPUESTALES ENFOCADOS EN LA PLANEACIÓN, DISEÑO Y DESARROLLO DE MECANISMOS QUE PERMITAN LA INTEGRACIÓN Y EL ANÁLISIS DE INFORMACIÓN PRESUPUESTAL EN EL MARCO DEL PROYECTO DE INVERSIÓN DE BANCA ABIERTA Y TRANSPARENTE E INHOUSE BANKING. | AV17: 27091036 | BF17: =BC17+BE17 -> 0 | BI17: =BF17+Q17 -> 363 | BJ17: =IF(BH17="",P17+BF17,BH17) -> 45657 | CC17: =BR17+BV17+BZ17 -> 0 | CE17: =IF(Y17=0,(W17+CC17)-CD17,IF(Y17>0,(Y17+CC17)-CD17)) -> 92883552 | CG17: =IFERROR(IF(((CE17/BI17)*(TODAY()-N17))>CE17,CE17,((CE17/BI17)*(TODAY()-N17))),"") -> 92883552 | CH17: =IF(TODAY()>BJ17,1,+(DAYS360(O17,TODAY())/DAYS360(O17,BJ17))) -> 1 | CI17: =+IF(CL17>0,DAYS360(O17,CL17)/DAYS360(O17,BJ17),CH17) -> 1 | CJ17: =IFERROR(IF(((CG17/CE17)*100)>100,100,((CG17/CE17)*100)),"") -> 100 | CK17: =IFERROR((CF17/CE17)*100,"") -> 0 | CM17: =IF(CL17>1/1/6,"LIQUIDADO",IF(BJ17=0,"",IF(BJ17>=TODAY(),"VIGENTE",IF(BJ17<TODAY(),"TERMINADO",)))) -> TERMINADO | CO17: 20243030000152-I Id: 4085611 | CP17: FEMENINO
A18: 12.19 | B18: 2024-0017 | C18: CTO | D18: CD-017-2024 | E18: 9 PRESTACIÓN DE SERVICIOS | F18: 1 PERSONA NATURAL | G18: 3 CÉDULA DE CIUDADANÍA | H18: 80119997 | I18: WILLIAM ALEXANDER VALENCIA NEMOCON | L18: PRESTAR LOS SERVICIOS PROFESIONALES EN LA ESTRUCTURACIÓN DE INICIATIVAS PARA LA OPTIMIZACIÓN DE MECANISMOS DE ADMINISTRACIÓN DE LOS SISTEMAS DE GESTIÓN PRESUPUESTAL Y SUS BASES DE DATOS EN EL MARCO DEL PROYECTO DE INVERSIÓN DE BANCA ABIERTA Y TRANSPARENTE E INHOUSE BANKING. | M18: BOGOTA | N18: 45294 | O18: 45294 | P18: 45657 | Q18: =P18-O18 -> 363 | R18: 2 INVERSIÓN | S18: CDEF-04-2024 | T18: BANCA ABIERTA Y TRANSPARENTE E INHOUSE B | U18: 66012000 | V18: IG332902005 | W18: 66012000 | X18: 5501000 | AA18: SECRETARÍA_GENERAL | AB18: =IFERROR(VLOOKUP(AA18,Listas!$A$1:$C$14,2,FALSE),"") -> FREDY CÉSPEDES VILLA | AC18: =IFERROR(VLOOKUP(AA18,Listas!$A$1:$C$14,3,FALSE),"") -> 93363483 | AD18: VICEPRESIDENCIA_FINANCIERA | AE18: COORDINADOR(A) GRUPO DE PRESUPUESTO | AF18: =IFERROR(VLOOKUP(AE18,Listas!$AD$1:$AF$66,2,FALSE),"") -> GISSET XIMENA BARRETO VILLAMIL | AG18: =IFERROR(VLOOKUP(AE18,Listas!$AD$1:$AF$65,3,FALSE),"") -> 1015408521 | AH18: 1 CONTRATACION DIRECTA | AI18: 1. Apoyar en la estructuración de mecanismos de registro, seguimiento y control de operaciones presupuestales relacionadas con vigencias futuras, acorde a los procedimientos establecidos y requeridos en el marco de la modernización de las funciones financieras del Instituto. 2. Proponer iniciativas que propendan por la articulación de actores para la apropiación e implementación de mecanismos para la optimización de los procesos que soportan la operación financiera del Instituto, con especial énfasis en el seguimiento y control de vigencias futuras. 3. Apoyar en el seguimiento y control de los requerimientos relacionados con la mitigación de riesgos del proceso de Gestión Presupuestal, los planes de mejoramiento y los lineamientos impartidos en el marco del proyecto de inversión de banca abierta y transparente. 4. Apoyar la estructuración de insumos técnicos para dar respuesta a los requerimientos de información solicitados por entes internos y/o externos en el marco de los proyectos de inversión Inhouse Banking, 5. Apoyar en la estructuración y conceptualización técnica de iniciativas que permitan la simplificación, estandarización e integración de procesos de la gestión presupuestal del ICETEX en el marco del proyecto de inversión de banca abierta y transparente e In House Banking. 6. Apoyar el diseño, apropiación e implementación de mecanismos para la optimización de los procesos presupuestales que se adelantan en el marco de la modernización de las funciones financieras del Instituto. 7. Apoyar la apropiación e implementación de esquemas de reporte y control a la gestión presupuestal del Instituto en el marco del proyecto de inversión de banca abierta y transparente. 8. Analizar la información generada a partir de las bases de datos presupuestales con el fin de verificar su fidelidad. 9. Las demás obligaciones que se requieran para el cumplimiento a cabalidad del objeto contractual y que sean inherentes a la naturaleza del contrato. 10. Cumplir con los indicadores de gestión establecidos | AJ18: 1 SI | AK18: 1 PUBLICADO | AL18: 1 PUBLICADO | AM18: 1 SI | AO18: =IF(YEAR(TODAY())-YEAR(AN18)>100," ",YEAR(TODAY())-YEAR(AN18)) | AP18: GRUPO_DE_CONTRATACIÓN | AQ18: SEBASTIAN AYALA | BF18: =BC18+BE18 -> 0 | BH18: 45555 | BI18: =BF18+Q18 -> 363 | BJ18: =IF(BH18="",P18+BF18,BH18) -> 45555 | CC18: =BR18+BV18+BZ18 -> 0 | CE18: =IF(Y18=0,(W18+CC18)-CD18,IF(Y18>0,(Y18+CC18)-CD18)) -> 66012000 | CF18: 49645388 | CG18: =IFERROR(IF(((CE18/BI18)*(TODAY()-N18))>CE18,CE18,((CE18/BI18)*(TODAY()-N18))),"") -> 66012000 | CH18: =IF(TODAY()>BJ18,1,+(DAYS360(O18,TODAY())/DAYS360(O18,BJ18))) -> 1 | CI18: =+IF(CL18>0,DAYS360(O18,CL18)/DAYS360(O18,BJ18),CH18) -> 1 | CJ18: =IFERROR(IF(((CG18/CE18)*100)>100,100,((CG18/CE18)*100)),"") -> 100 | CK18: =IFERROR((CF18/CE18)*100,"") -> 75.206611 | CM18: =IF(CL18>1/1/6,"LIQUIDADO",IF(BJ18=0,"",IF(BJ18>=TODAY(),"VIGENTE",IF(BJ18<TODAY(),"TERMINADO",)))) -> TERMINADO | CO18: 20243030000154-I Id: 4085614 | CP18: MASCULINO
A19: 13.39 | B19: 2024-0018 | C19: CTO | D19: CD-018-2024 | E19: 9 PRESTACIÓN DE SERVICIOS | F19: 1 PERSONA NATURAL | G19: 3 CÉDULA DE CIUDADANÍA | H19: 1077940566 | I19: RAUL ALFREDO QUEVEDO | L19: PRESTACIÓN DE SERVICIOS DE APOYO TÉCNICO A LA GESTIÓN DE LA POLÍTICA DE COMPRAS PÚBLICAS Y DE CONTRATACIÓN EN EL MARCO DEL PROYECTO DENOMINADO “FORTALECIMIENTO ORGANIZACIONAL" DEL ICETEX | M19: BOGOTA | N19: 45294 | O19: 45294 | P19: 45656 | Q19: =P19-O19 -> 362 | R19: 2 INVERSIÓN | S19: CDEF-25-2024 | T19: FORTALECIMIENTO ORGANIZACIONAL | U19: 51759243 | V19: IG 332901003 | W19: 51759240 | X19: 4313270 | AA19: SECRETARÍA_GENERAL | AB19: =IFERROR(VLOOKUP(AA19,Listas!$A$1:$C$14,2,FALSE),"") -> FREDY CÉSPEDES VILLA | AC19: =IFERROR(VLOOKUP(AA19,Listas!$A$1:$C$14,3,FALSE),"") -> 93363483 | AD19: SECRETARÍA_GENERAL | AE19: COORDINADOR(A) GRUPO DE CONTRATACIÓN | AF19: =IFERROR(VLOOKUP(AE19,Listas!$AD$1:$AF$66,2,FALSE),"") -> DIANA BARRERA MEDINA | AG19: =IFERROR(VLOOKUP(AE19,Listas!$AD$1:$AF$65,3,FALSE),"") -> 52964360 | AH19: 1 CONTRATACION DIRECTA | AI19: 1. Proyectar comunicaciones para atender los requerimientos internos y externos relacionados con las actividades desarrolladas por el grupo de contratos, así como los requerimientos de los entes de control, en el marco del proyecto de inversión. 2. Realizar la radicación de documentos, así́ como el direccionamiento respectivo, de conformidad con lo establecido en los procedimientos del Grupo de Contratación de acuerdo con el objeto contractual. 3. Servir como canal de comunicación con el área de gestión documental para gestionar la consecución de expedientes, documentos y de toda la información que requiera el Grupo de Contratación y en general de la Secretaria General en cumplimiento de la política de MIPG. 4. Apoyar en la actualización, clasificación y organización de los documentos físicos y virtuales propios de los procesos del grupo de contratos y en la actualización de la base de datos del grupo de contratos, así como brindar información respecto de la misma, de conformidad con las metas y objetivos del proyecto de inversión. 5. Apoyar en la vinculación, creación y revisión de las hojas de vida del SIGEP, alineados con las metas del proyecto de inversión en pro del fortalecimiento organizacional. 6. Elaborar los informes y reportes previa coordinación con el supervisor del contrato de acuerdo con las actividades y procesos realizados en el Grupo de Contratación en el marco del objeto contractual. 7. Adelantar los tramites a cargo, en el marco del proyecto de fortalecimiento organizacional y la implementación de la política de compras públicas y de contratación, promoviendo el cierre de brechas que se presenten. 8. Las demás obligaciones que sean asignadas por quien ejerza la función de la supervisión del contrato. | AJ19: 1 SI | AK19: 1 PUBLICADO | AL19: 1 PUBLICADO | AM19: 1 SI | AN19: 31906 | AO19: =IF(YEAR(TODAY())-YEAR(AN19)>100," ",YEAR(TODAY())-YEAR(AN19)) -> 38 | AP19: GRUPO_DE_CONTRATACIÓN | AQ19: LAURA NARANJO | BF19: =BC19+BE19 -> 0 | BI19: =BF19+Q19 -> 362 | BJ19: =IF(BH19="",P19+BF19,BH19) -> 45656 | CC19: =BR19+BV19+BZ19 -> 0 | CE19: =IF(Y19=0,(W19+CC19)-CD19,IF(Y19>0,(Y19+CC19)-CD19)) -> 51759240 | CG19: =IFERROR(IF(((CE19/BI19)*(TODAY()-N19))>CE19,CE19,((CE19/BI19)*(TODAY()-N19))),"") -> 51759240 | CH19: =IF(TODAY()>BJ19,1,+(DAYS360(O19,TODAY())/DAYS360(O19,BJ19))) -> 1 | CI19: =+IF(CL19>0,DAYS360(O19,CL19)/DAYS360(O19,BJ19),CH19) -> 1 | CJ19: =IFERROR(IF(((CG19/CE19)*100)>100,100,((CG19/CE19)*100)),"") -> 100 | CK19: =IFERROR((CF19/CE19)*100,"") -> 0 | CM19: =IF(CL19>1/1/6,"LIQUIDADO",IF(BJ19=0,"",IF(BJ19>=TODAY(),"VIGENTE",IF(BJ19<TODAY(),"TERMINADO",)))) -> TERMINADO | CP19: MASCULINO
A20: 12.18 | B20: 2024-0019 | C20: CTO | D20: CD-019-2024 | E20: 9 PRESTACIÓN DE SERVICIOS | F20: 1 PERSONA NATURAL | G20: 3 CÉDULA DE CIUDADANÍA | H20: 53030016 | I20: MARITZA ALEXANDRA CAICEDO GONZALEZ | L20: PRESTAR LOS SERVICIOS PROFESIONALES EN LA ACTUALIZACIÓN DE LOS SISTEMAS DE GESTIÓN PRESUPUESTAL DE LOS RECURSOS DE FONDOS Y PROPIOS Y EN EL PROCESO DE VALIDACIÓN DE LA EJECUCIÓN DEL PRESUPUESTO A PARTIR DEL PROCESAMIENTO Y ANÁLISIS DE LA INFORMACIÓN A CARGO DEL GRUPO DE PRESUPUESTO. | M20: BOGOTA | N20: 45294 | O20: 45294 | P20: 45657 | Q20: =P20-O20 -> 363 | R20: 1 FUNCIONAMIENTO | S20: CDEF-03-2024 | T20: HONORARIOS - VFN | U20: 55908468 | V20: IG312001020400012 | W20: 55908468 | X20: 4659039 | AA20: SECRETARÍA_GENERAL | AB20: =IFERROR(VLOOKUP(AA20,Listas!$A$1:$C$14,2,FALSE),"") -> FREDY CÉSPEDES VILLA | AC20: =IFERROR(VLOOKUP(AA20,Listas!$A$1:$C$14,3,FALSE),"") -> 93363483 | AD20: VICEPRESIDENCIA_FINANCIERA | AE20: COORDINADOR(A) GRUPO DE PRESUPUESTO | AF20: =IFERROR(VLOOKUP(AE20,Listas!$AD$1:$AF$66,2,FALSE),"") -> GISSET XIMENA BARRETO VILLAMIL | AG20: =IFERROR(VLOOKUP(AE20,Listas!$AD$1:$AF$65,3,FALSE),"") -> 1015408521 | AH20: 1 CONTRATACION DIRECTA | AI20: 1. Apoyar la actualización, sistematización y soporte a las bases de datos de los sistemas o aplicativos de información relacionados con la gestión presupuestal de los recursos de fondos y propios. 2. Apoyar la gestión de seguimiento y control de la información relacionada con los recursos en administración y propios en tiempo real para la generación de estadísticas de la operación. 3. Apoyar en el seguimiento a la ejecución presupuestal de los contratos del Instituto en las bases de datos del Grupo de Presupuesto frente a los registros en el aplicativo financiero, a través de la generación de reportes, depuración y validación de información. 4. Apoyar la gestión de los registros presupuestales requeridos relacionados con los recursos de propios y de fondos acorde a los procedimientos establecidos, con el objetivo de garantizar la calidad de la información. 5. Apoyar la implementación y apropiación de las solicitudes de los aplicativos que soportan la gestión presupuestal del Instituto. 6. Apoyar en la verificación de los contratos y condiciones de fondos en administración con el fin de obtener la información fuente para la gestión presupuestal de la mencionada fuente de recursos. 7. Apoyar la gestión de seguimiento y control de la información a través de la validación y registro de órdenes de pago de recursos propios y de fondos. 8. Apoyar la gestión de seguimiento y control de la información relacionada a recursos Propios acorde a los procedimientos establecidos, requeridos en el marco de la modernización de las funciones financieras del Instituto para garantizar el adecuado manejo de los registros presupuestales correspondientes. 9. Apoyar la gestión de seguimiento y control presupuestal de los giros a través de la confirmación de las resoluciones cargadas en el sistema. 10. Cumplir con los indicadores de gestión establecidos. | AJ20: 1 SI | AK20: 1 PUBLICADO | AL20: 1 PUBLICADO | AM20: 1 SI | AN20: 31111 | AO20: =IF(YEAR(TODAY())-YEAR(AN20)>100," ",YEAR(TODAY())-YEAR(AN20)) -> 40 | AP20: GRUPO_DE_CONTRATACIÓN | AQ20: SEBASTIAN AYALA | BF20: =BC20+BE20 -> 0 | BI20: =BF20+Q20 -> 363 | BJ20: =IF(BH20="",P20+BF20,BH20) -> 45657 | CC20: =BR20+BV20+BZ20 -> 0 | CE20: =IF(Y20=0,(W20+CC20)-CD20,IF(Y20>0,(Y20+CC20)-CD20)) -> 55908468 | CG20: =IFERROR(IF(((CE20/BI20)*(TODAY()-N20))>CE20,CE20,((CE20/BI20)*(TODAY()-N20))),"") -> 55908468 | CH20: =IF(TODAY()>BJ20,1,+(DAYS360(O20,TODAY())/DAYS360(O20,BJ20))) -> 1 | CI20: =+IF(CL20>0,DAYS360(O20,CL20)/DAYS360(O20,BJ20),CH20) -> 1 | CJ20: =IFERROR(IF(((CG20/CE20)*100)>100,100,((CG20/CE20)*100)),"") -> 100 | CK20: =IFERROR((CF20/CE20)*100,"") -> 0 | CM20: =IF(CL20>1/1/6,"LIQUIDADO",IF(BJ20=0,"",IF(BJ20>=TODAY(),"VIGENTE",IF(BJ20<TODAY(),"TERMINADO",)))) -> TERMINADO | CO20: 20243030000170-I Id: 4085637 | CP20: FEMENINO
A21: 12.16 | B21: 2024-0020 | C21: CTO | D21: CD-020-2024 | E21: 9 PRESTACIÓN DE SERVICIOS | F21: 1 PERSONA NATURAL | G21: 3 CÉDULA DE CIUDADANÍA | H21: 1015476312 | I21: JULIETH SOSA ROMERO | L21: PRESTAR SERVICIOS TÉCNICOS PARA APOYAR LA MEJORA DE PROCESOS PRESUPUESTALES, GESTIONANDO LA EN LA IMPLEMENTACIÓN DE LOS SISTEMAS DE GESTIÓN PRESUPUESTAL REALIZANDO EL DEBIDO ACOMPAÑAMIENTO PARA LA APROPIACIÓN DE LOS MISMOS EN EL MARCO DEL PROYECTO DE INVERSIÓN DE BANCA ABIERTA Y TRANSPARENTE E INHOUSE BANKING. | M21: BOGOTA | N21: 45294 | O21: 45294 | P21: 45657 | Q21: =P21-O21 -> 363 | R21: 2 INVERSIÓN | S21: CDEF-30-2024 | T21: BANCA ABIERTA Y TRANSPARENTE E INHOUSE B | U21: 46643904 | V21: IG332902005 | W21: 46643904 | X21: 3886992 | AA21: SECRETARÍA_GENERAL | AB21: =IFERROR(VLOOKUP(AA21,Listas!$A$1:$C$14,2,FALSE),"") -> FREDY CÉSPEDES VILLA | AC21: =IFERROR(VLOOKUP(AA21,Listas!$A$1:$C$14,3,FALSE),"") -> 93363483 | AD21: VICEPRESIDENCIA_FINANCIERA | AE21: COORDINADOR(A) GRUPO DE PRESUPUESTO | AF21: =IFERROR(VLOOKUP(AE21,Listas!$AD$1:$AF$66,2,FALSE),"") -> GISSET XIMENA BARRETO VILLAMIL | AG21: =IFERROR(VLOOKUP(AE21,Listas!$AD$1:$AF$65,3,FALSE),"") -> 1015408521 | AH21: 1 CONTRATACION DIRECTA | AI21: 1. Apoyar la sistematización, simplificación y optimización de procesos presupuestales que se adelantan en el marco de la modernización de las funciones financieras del Instituto y del proyecto de inversión In House Banking. 2. Apoyar en la apropiación de lineamientos para optimizar la gestión financiera y presupuestal, a partir del soporte operativo a los sistemas y bases de datos, en el marco de la implementación del proyecto de banca abierta y transparente e inhouse banking. 3. Apoyar en la gestión, validación y seguimiento de las solicitudes de índole presupuestal radicadas mediante los aplicativos de gestión adoptados por el Instituto para la generación de datos en tiempo real. 4. Apoyar en la gestión de requerimientos relacionados con las oportunidades de mejora de los aplicativos financieros del ICETEX, a través de la producción de informes, reportes y/o tableros de control. 5. Apoyar el despliegue, apropiación y estabilización e integración de aplicativos con los que cuenta el ICETEX para la gestión presupuestal. 6. Apoyar en la estructuración insumos para el seguimiento de la gestión de pagos de la entidad y la gestión de alertas tempranas que permitan la implementación de los más altos estándares y buenas prácticas en banca abierta y transparente e inhouse banking 7. Apoyar en la gestión de pagos, requeridos por los ordenadores del gasto, ejecutores y órganos de vigilancia y control, a través de la producción de informes, reportes y/o tableros de control. 8. Apoyar la administración y registros presupuestales relacionados con recursos Propios acorde a los procedimientos y lineamientos establecidos, que permitan garantizar la calidad de la información y la producción de información en tiempo real. 9. Apoyar al Grupo de Presupuesto en los procesos de administración, sistematización y validación de la información presupuestal para la generación de estadísticas de la operación. 10. Las demás obligaciones que se requieran para el cumplimiento a cabalidad del objeto contractual y que sean inherentes a la naturaleza del contrato. 11. Cumplir con los indicadores de gestión establecidos. | AJ21: 1 SI | AK21: 1 PUBLICADO | AL21: 1 PUBLICADO | AM21: 1 SI | AN21: 36018 | AO21: =IF(YEAR(TODAY())-YEAR(AN21)>100," ",YEAR(TODAY())-YEAR(AN21)) -> 27 | AP21: GRUPO_DE_CONTRATACIÓN | AQ21: SEBASTIAN AYALA | BF21: =BC21+BE21 -> 0 | BI21: =BF21+Q21 -> 363 | BJ21: =IF(BH21="",P21+BF21,BH21) -> 45657 | CC21: =BR21+BV21+BZ21 -> 0 | CE21: =IF(Y21=0,(W21+CC21)-CD21,IF(Y21>0,(Y21+CC21)-CD21)) -> 46643904 | CG21: =IFERROR(IF(((CE21/BI21)*(TODAY()-N21))>CE21,CE21,((CE21/BI21)*(TODAY()-N21))),"") -> 46643904 | CH21: =IF(TODAY()>BJ21,1,+(DAYS360(O21,TODAY())/DAYS360(O21,BJ21))) -> 1 | CI21: =+IF(CL21>0,DAYS360(O21,CL21)/DAYS360(O21,BJ21),CH21) -> 1 | CJ21: =IFERROR(IF(((CG21/CE21)*100)>100,100,((CG21/CE21)*100)),"") -> 100 | CK21: =IFERROR((CF21/CE21)*100,"") -> 0 | CM21: =IF(CL21>1/1/6,"LIQUIDADO",IF(BJ21=0,"",IF(BJ21>=TODAY(),"VIGENTE",IF(BJ21<TODAY(),"TERMINADO",)))) -> TERMINADO | CO21: 20243030000172-I Id: 4085640 | CP21: FEMENINO
A22: 12.2 | B22: 2024-0021 | C22: CTO | D22: CD-021-2024 | E22: 9 PRESTACIÓN DE SERVICIOS | F22: 1 PERSONA NATURAL | G22: 3 CÉDULA DE CIUDADANÍA | H22: 1049624779 | I22: JENNIFER VIVIANA DÍAZ CARO | L22: PRESTAR LOS SERVICIOS PROFESIONALES ESPECIALIZADOS PARA LA ESTRUCTURACIÓN, SEGUIMIENTO Y CONTROL TÉCNICO Y PRESUPUESTAL DE INICIATIVAS RELACIONADAS CON LA EJECUCIÓN DE PROYECTOS ESTRATÉGICOS Y DE INVERSIÓN A CARGO DE LA VICEPRESIDENCIA FINANCIERA, BASADOS EN LA OPTIMIZACIÓN DE PROCEDIMIENTOS PARA LA GENERACIÓN DE SOLUCIONES FINANCIERAS ACORDES A LAS NECESIDADES DE LOS GRUPOS DE INCIDENCIA PARA LA OPTIMIZACIÓN DE LA ESTRUCTURA PASIVO Y DIVERSIFICACIÓN DE LAS FUENTES DE FONDEO. | M22: BOGOTA | N22: 45294 | O22: 45295 | P22: 45657 | Q22: =P22-O22 -> 362 | R22: 2 INVERSIÓN | S22: CDEF-07-2024 | T22: OPTIMIZACIÓN DEL PASIVO Y DIVERSIFICACIÓ | U22: 167142384 | V22: IG332902004 | W22: 167142384 | X22: 13928532 | AA22: SECRETARÍA_GENERAL | AB22: =IFERROR(VLOOKUP(AA22,Listas!$A$1:$C$14,2,FALSE),"") -> FREDY CÉSPEDES VILLA | AC22: =IFERROR(VLOOKUP(AA22,Listas!$A$1:$C$14,3,FALSE),"") -> 93363483 | AD22: VICEPRESIDENCIA_FINANCIERA | AE22: VICEPRESIDENTE FINANCIERO | AF22: =IFERROR(VLOOKUP(AE22,Listas!$AD$1:$AF$66,2,FALSE),"") -> EDGAR ANTONIO GÓMEZ ÁLVAREZ | AG22: =IFERROR(VLOOKUP(AE22,Listas!$AD$1:$AF$65,3,FALSE),"") -> 2231755 | AH22: 1 CONTRATACION DIRECTA | AI22: 1. Apoyar en la coordinación de la implementación y apropiación de mecanismos y herramientas de seguimiento, control y reporte de los proyectos, planes e iniciativas contemplados en el plan estratégico del Instituto, a cargo de la dependencia según la metodología establecida por la Oficina Asesora de Planeación. 2. Apoyar en la coordinación de la estabilización, apropiación y despliegue de procesos optimizados para la administración, seguimiento y gestión de las fuentes de fondeo que permitan generar eficiencias financieras a los grupos de incidencia. 3. Articular las diferentes instancias para la implementación de iniciativas de la Vicepresidencia Financiera con el objetivo de consolidar a adopción de buenas prácticas, lineamientos y estándares que permitan fortalecer las capacidades operativas y la cultura de control, mitigación de riesgos y eficiencia administrativa. 4. Apoyar en la formulación y apropiación de indicadores que permitan mejorar la oportunidad de seguimiento y reporte relacionados con las funciones financieras del Instituto, a través de la articulación del seguimiento y control de KPI´s (key performance indicators) de la Vicepresidencia Financiera y del Instituto. 5. Estructurar documentos técnicos, reglamentación o actos administrativos requeridos para la implementación de lineamientos, estándares y buenas prácticas en el marco del despliegue de proyectos estratégicos y de inversión a cargo de la Vicepresidencia Financiera. 6. Apoyar en la estructuración de los insumos técnicos para el análisis, gestión y consecución de aliados estratégicos que apalanquen el proyecto de transformación del Instituto, y especialmente lo relacionado con la diversificación de fuentes de fondeo en la búsqueda permanente de esquemas de financiación que permitan optimizar la estructura financiera del ICETEX. 7. Apoyar en la coordinación del despliegue de iniciativas, planes, proyectos, iniciativas y estrategias asignadas, y que se encaminen al cumplimiento de metas y despliegue de servicios financieros de calidad, eficientes e innovadores que fortalezca la apropiación de los principios de banca abierta y transparente adoptado por la entidad 8. Gestionar acciones que permitan la simplificación, estandarización y optimización de procesos asociados al sistema de calidad y que permitan modernización de las funciones financieras del ICETEX. 9. Estructurar los estudios, análisis del sector económico, matriz de riesgos y demás insumos requeridos por la normatividad vigente, que permita adelantar los procesos en el marco de la implementación de los proyectos de inversión a cargo de la Vicepresidencia Financiera. 10. Articular con instancias internas y externas el despliegue e implementación de los proyectos de inversión de la Vicepresidencia Financiera, a partir de un esquema por áreas de gestión en el marco de implementación de los principios de banca abierta y transparente. 11. Cumplir con los indicadores de gestión establecidos. 12. Las demás obligaciones que se requieran para el cumplimiento a cabalidad del objeto contractual y que sean inherentes a la naturaleza del contrato. | AJ22: 1 SI | AK22: 1 PUBLICADO | AL22: 1 PUBLICADO | AM22: 1 SI | AN22: 33290 | AO22: =IF(YEAR(TODAY())-YEAR(AN22)>100," ",YEAR(TODAY())-YEAR(AN22)) -> 34 | AP22: GRUPO_DE_CONTRATACIÓN | AQ22: SEBASTIAN AYALA | BF22: =BC22+BE22 -> 0 | BI22: =BF22+Q22 -> 362 | BJ22: =IF(BH22="",P22+BF22,BH22) -> 45657 | CC22: =BR22+BV22+BZ22 -> 0 | CE22: =IF(Y22=0,(W22+CC22)-CD22,IF(Y22>0,(Y22+CC22)-CD22)) -> 167142384 | CG22: =IFERROR(IF(((CE22/BI22)*(TODAY()-N22))>CE22,CE22,((CE22/BI22)*(TODAY()-N22))),"") -> 167142384 | CH22: =IF(TODAY()>BJ22,1,+(DAYS360(O22,TODAY())/DAYS360(O22,BJ22))) -> 1 | CI22: =+IF(CL22>0,DAYS360(O22,CL22)/DAYS360(O22,BJ22),CH22) -> 1 | CJ22: =IFERROR(IF(((CG22/CE22)*100)>100,100,((CG22/CE22)*100)),"") -> 100 | CK22: =IFERROR((CF22/CE22)*100,"") -> 0 | CM22: =IF(CL22>1/1/6,"LIQUIDADO",IF(BJ22=0,"",IF(BJ22>=TODAY(),"VIGENTE",IF(BJ22<TODAY(),"TERMINADO",)))) -> TERMINADO | CO22: 20243030000202-I Id: 4085701 | CP22: FEMENINO
A23: 13.40 | B23: 2024-0022 | C23: CTO | D23: CD-022-2024 | E23: 9 PRESTACIÓN DE SERVICIOS | F23: 1 PERSONA NATURAL | G23: 3 CÉDULA DE CIUDADANÍA | H23: 1098131056 | I23: YUDY ROCIO ORDUZ PEREZ | L23: PRESTACIÓN DE SERVICIOS DE APOYO TÉCNICO A LA GESTIÓN DE LA POLÍTICA DE COMPRAS PÚBLICAS Y DE CONTRATACIÓN EN EL MARCO DEL PROYECTO DENOMINADO “FORTALECIMIENTO ORGANIZACIONAL" DEL ICETEX | M23: BOGOTA | N23: 45295 | O23: 45296 | P23: 45656 | Q23: =P23-O23 -> 360 | R23: 2 INVERSIÓN | S23: CDEF-26-2024 | T23: FORTALECIMIENTO ORGANIZACIONAL | U23: 48552084 | V23: IG 332901003 | W23: 48552084 | X23: 4046007 | AA23: SECRETARÍA_GENERAL | AB23: =IFERROR(VLOOKUP(AA23,Listas!$A$1:$C$14,2,FALSE),"") -> FREDY CÉSPEDES VILLA | AC23: =IFERROR(VLOOKUP(AA23,Listas!$A$1:$C$14,3,FALSE),"") -> 93363483 | AD23: SECRETARÍA_GENERAL | AE23: COORDINADOR(A) GRUPO DE CONTRATACIÓN | AF23: =IFERROR(VLOOKUP(AE23,Listas!$AD$1:$AF$66,2,FALSE),"") -> DIANA BARRERA MEDINA | AG23: =IFERROR(VLOOKUP(AE23,Listas!$AD$1:$AF$65,3,FALSE),"") -> 52964360 | AH23: 1 CONTRATACION DIRECTA | AI23: Proyectar comunicaciones para atender los requerimientos internos y externos relacionados con las actividades desarrolladas por el grupo de contratos, así como los requerimientos de los entes de Código: F451 ESTUDIO PREVIO SIMPLIFICADO Versión: 3 Fecha: 04/12/2023 Página 8 de 15 control, en el marco del proyecto de inversión. 2. Realizar la radicación de documentos, así́ como el direccionamiento respectivo, de conformidad con lo establecido en los procedimientos del Grupo de Contratación de acuerdo con el objeto contractual. 3. Servir como canal de comunicación con el área de gestión documental para gestionar la consecución de expedientes, documentos y de toda la información que requiera el Grupo de Contratación y en general de la secretaria general en cumplimiento de la política de MIPG. 4. Apoyar en la actualización, clasificación y organización de los documentos físicos y virtuales propios de los procesos del grupo de contratos y en la actualización de la base de datos del grupo de contratos, así como brindar información respecto de la misma, de conformidad con las metas y objetivos del proyecto de inversión. 5. Apoyar en la vinculación, creación y revisión de las hojas de vida del SIGEP, alineados con las metas del proyecto de inversión en pro del fortalecimiento organizacional. 6. Elaborar los informes y reportes previa coordinación con el supervisor del contrato de acuerdo con las actividades y procesos realizados en el Grupo de Contratación en el marco del objeto contractual. 7. Adelantar los tramites a cargo, en el marco del proyecto de fortalecimiento organizacional y la implementación de la política de compras públicas y de contratación, promoviendo el cierre de brechas que se presenten 8. Las demás obligaciones que sean asignadas por quien ejerza la función de la supervisión del contrato. | AJ23: 1 SI | AK23: 1 PUBLICADO | AL23: 1 PUBLICADO | AM23: 1 SI | AN23: 33534 | AO23: =IF(YEAR(TODAY())-YEAR(AN23)>100," ",YEAR(TODAY())-YEAR(AN23)) -> 34 | AP23: GRUPO_DE_CONTRATACIÓN | AQ23: LAURA NARANJO | BF23: =BC23+BE23 -> 0 | BI23: =BF23+Q23 -> 360 | BJ23: =IF(BH23="",P23+BF23,BH23) -> 45656 | CC23: =BR23+BV23+BZ23 -> 0 | CE23: =IF(Y23=0,(W23+CC23)-CD23,IF(Y23>0,(Y23+CC23)-CD23)) -> 48552084 | CG23: =IFERROR(IF(((CE23/BI23)*(TODAY()-N23))>CE23,CE23,((CE23/BI23)*(TODAY()-N23))),"") -> 48552084 | CH23: =IF(TODAY()>BJ23,1,+(DAYS360(O23,TODAY())/DAYS360(O23,BJ23))) -> 1 | CI23: =+IF(CL23>0,DAYS360(O23,CL23)/DAYS360(O23,BJ23),CH23) -> 1 | CJ23: =IFERROR(IF(((CG23/CE23)*100)>100,100,((CG23/CE23)*100)),"") -> 100 | CK23: =IFERROR((CF23/CE23)*100,"") -> 0 | CM23: =IF(CL23>1/1/6,"LIQUIDADO",IF(BJ23=0,"",IF(BJ23>=TODAY(),"VIGENTE",IF(BJ23<TODAY(),"TERMINADO",)))) -> TERMINADO | CP23: FEMENINO
A24: 7.2 | B24: 2024-0023 | C24: CTO | D24: CD-023-2024 | E24: 9 PRESTACIÓN DE SERVICIOS | F24: 1 PERSONA NATURAL | G24: 3 CÉDULA DE CIUDADANÍA | H24: 1018500881 | I24: JUAN SEBASTIAN MARTINEZ CONEJO | L24: "PRESTAR LOS SERVICIOS PROFESIONALES; PARA LA CONSTRUCCIÓN DE BASES HISTÓRICAS QUE PERMITAN LA EVALUACIÓN, SEGUIMIENTO Y ANÁLISIS DE LOS DIFERENTES COMPONENTES DE LOS MODELOS DE LOS SISTEMAS DE RIESGOS QUE SE ADMINISTRAN EN EL ICETEX." | M24: BOGOTA | N24: 45295 | O24: 45296 | P24: 45656 | Q24: =P24-O24 -> 360 | R24: 1 FUNCIONAMIENTO | S24: CDEF-011-2024 | T24: HONORARIOS - ODR | U24: 69149952 | V24: IG 312001020250012 | W24: 69149952 | X24: 5762496 | AA24: SECRETARÍA_GENERAL | AB24: =IFERROR(VLOOKUP(AA24,Listas!$A$1:$C$14,2,FALSE),"") -> FREDY CÉSPEDES VILLA | AC24: =IFERROR(VLOOKUP(AA24,Listas!$A$1:$C$14,3,FALSE),"") -> 93363483 | AD24: OFICINA_DE_RIESGOS | AE24: COORDINADOR(A) GRUPO DE RIESGOS FINANCIEROS | AF24: =IFERROR(VLOOKUP(AE24,Listas!$AD$1:$AF$66,2,FALSE),"") -> MARÍA STELLA CARREÑO JURADO | AG24: =IFERROR(VLOOKUP(AE24,Listas!$AD$1:$AF$65,3,FALSE),"") -> 51774925 | AH24: 1 CONTRATACION DIRECTA | AI24: 1. Construir el tablero de indicadores de riesgos establecidos bajo la alineación con el SIAR. 2. Construir la base histórica, y actualizar según periodicidad establecida los indicadores seleccionados en el SIAR. 3. Ejecutar los modelos de riesgo construidos y/o calibrados para la gestión de riesgo de crédito. 4. Apoyar en la elaboración de informes y presentaciones requeridas dentro de la gestión y administración de los riesgos financieros. 5. Apoyar en la implementación de los procedimientos que se generan en el marco de alineación con el SIAR. 6. Verificar los resultados de la aplicación de los modelos como control dual para la confirmación de resultados establecidos en los respectivos manuales de implementación de los respectivos modelos. 7. Apoyar en la articulación de los modelos desarrollados o calibrados en la herramienta MODELER y/o SPSS. 8. Elaborar las macros de los modelos nuevos, así como las mejoras que se realicen con las respectivas guías para el paso a paso de la aplicación por parte del área misional. 9. Acompañar la verificación de los resultados que entregue la Dirección de Tecnología en la fase de puesta en producción de los modelos que se implementen conforme la necesidad de la Entidad. 10. Consolidación y/o construcción de bases de datos históricas y/o de fuentes externas que se requieran para atender requerimientos internos y de originados por propuestas de nuevas líneas de crédito o beneficios a usuarios. 11. Apoyo en el análisis, estudios, mejoras y aspectos de valor agregado referente a otros riesgos que gestione la Oficina de Riesgos. 11, Capacitar al equipo en la administración y ejecución de los modelos que se construyan y/o calibran en el marco de la gestión de los riesgos que administra la Oficina de Riesgos. | AJ24: 1 SI | AK24: 1 PUBLICADO | AL24: 1 PUBLICADO | AM24: 1 SI | AN24: 35830 | AO24: =IF(YEAR(TODAY())-YEAR(AN24)>100," ",YEAR(TODAY())-YEAR(AN24)) -> 27 | AP24: GRUPO_DE_CONTRATACIÓN | AQ24: NATALIA MURCIA | BF24: =BC24+BE24 -> 0 | BI24: =BF24+Q24 -> 360 | BJ24: =IF(BH24="",P24+BF24,BH24) -> 45656 | CC24: =BR24+BV24+BZ24 -> 0 | CE24: =IF(Y24=0,(W24+CC24)-CD24,IF(Y24>0,(Y24+CC24)-CD24)) -> 69149952 | CG24: =IFERROR(IF(((CE24/BI24)*(TODAY()-N24))>CE24,CE24,((CE24/BI24)*(TODAY()-N24))),"") -> 69149952 | CH24: =IF(TODAY()>BJ24,1,+(DAYS360(O24,TODAY())/DAYS360(O24,BJ24))) -> 1 | CI24: =+IF(CL24>0,DAYS360(O24,CL24)/DAYS360(O24,BJ24),CH24) -> 1 | CJ24: =IFERROR(IF(((CG24/CE24)*100)>100,100,((CG24/CE24)*100)),"") -> 100 | CK24: =IFERROR((CF24/CE24)*100,"") -> 0 | CM24: =IF(CL24>1/1/6,"LIQUIDADO",IF(BJ24=0,"",IF(BJ24>=TODAY(),"VIGENTE",IF(BJ24<TODAY(),"TERMINADO",)))) -> TERMINADO | CO24: 20242510000216-I | CP24: MASCULINO
A25: 7.5 | B25: 2024-0024 | C25: CTO | D25: CD-024-2024 | E25: 9 PRESTACIÓN DE SERVICIOS | F25: 1 PERSONA NATURAL | G25: 3 CÉDULA DE CIUDADANÍA | H25: 79788275 | I25: GUSTAVO ADOLFO BELTRAN SABOGAL | L25: PRESTAR SERVICIOS PROFESIONALES COMO OFICIAL DE SEGURIDAD DE LA INFORMACIÓN Y PRIVACIDAD, PARA ADMINISTRAR EL SISTEMA DE GESTIÓN DE SEGURIDAD DE LA INFORMACIÓN Y DE LA PROTECCIÓN DE DATOS, CUMPLIENDO LOS LINEAMIENTOS EN EL MARCO NORMATIVO INTERNO Y EXTERNO EN LA MATERIA. | M25: BOGOTA | N25: 45295 | O25: 45296 | P25: 45656 | Q25: =P25-O25 -> 360 | R25: 1 FUNCIONAMIENTO | S25: CDEF-010-2024 | T25: HONORARIOS - ODR | U25: 125058408 | V25: IG 312001020250012 | W25: 125058408 | X25: 10421534 | AA25: SECRETARÍA_GENERAL | AB25: =IFERROR(VLOOKUP(AA25,Listas!$A$1:$C$14,2,FALSE),"") -> FREDY CÉSPEDES VILLA | AC25: =IFERROR(VLOOKUP(AA25,Listas!$A$1:$C$14,3,FALSE),"") -> 93363483 | AD25: OFICINA_DE_RIESGOS | AE25: COORDINADOR(A) GRUPO DE RIESGOS NO FINANCIEROS | AF25: =IFERROR(VLOOKUP(AE25,Listas!$AD$1:$AF$66,2,FALSE),"") -> MÓNICA PINTO GARCÍA | AG25: =IFERROR(VLOOKUP(AE25,Listas!$AD$1:$AF$65,3,FALSE),"") -> 52867207 | AH25: 1 CONTRATACION DIRECTA | AI25: OBLIGACIONES ESPECÍFICAS DEL CONTRATISTA 1. Coordinar la operación del Sistema de Gestion de Seguridad de la Información (SGSI) de la Entidad, alineado con la norma NTC ISO 27001:20013 y el Modelo de Seguridad y Privacidad de MinTIC a través, de la emisión de planes de: estratégicos y control operacional, de seguimiento del SGSD, de capacitación y sensibilización y seguimiento al cronograma de trabajo del equipo de seguridad. 2. Desarrollar y mantener el Programa de Protección de Datos Personales, con el fin de velar por el respeto a los derechos de los titulares de los datos personales, Informar y asesorar en las obligaciones de la regulación colombiana en la materia, supervisar el cumplimiento de la regulación, así como el principio de la responsabilidad demostrada. 3. Actualizar las políticas y procedimientos de seguridad digital y de protección de datos personales, con base en las necesidades de la entidad y los cambios normativos. 4. Presentación de informe a Junta Directiva, con la gestión realizada sobre el SGSD, las alertas sobre el SGSD y la actualización de políticas de seguridad digital y de protección de datos personales 5. Establecer cronograma y hacer seguimiento a la revisión de la actualización del Inventario y clasificación de los Activos de Información. 6. Establecer cronograma y hacer seguimiento del monitoreo de riesgos de seguridad digital, ciberseguridad y protección de datos personales asistiendo a las diferentes áreas del Icetex en el análisis, evaluación y tratamiento de los riesgos de la Seguridad de la Información. 7. Hacer seguimiento a la gestión de los incidentes de seguridad digital con el respectivo plan de acción para garantizar su no repetición. 8. Revisar las alertas de seguridad generadas por las herramientas de monitoreo (SOC) y establecer posibles incidentes de seguridad. 9. Planear, probar y hacer seguimiento a la revisión del diseño y eficacia de los controles de la ISO 27001 y seguimiento a los planes de acción generados por oportunidades de mejora. 10. Acompañar y hacer seguimiento en la definición, ejecución y revisión de las pruebas de Ethical Hacking y re-test sobre los diferentes servicios tecnológicos y hacer seguimiento a los cierres de vulnerabilidades detectadas, a fin de proteger la plataforma tecnológica. 11. Promover una cultura de seguridad de la información que incluya actividades de difusión y capacitación para funcionarios, contratistas, proveedores y beneficiarios. 12. Apoyar en el desarrollo de actividades de divulgación y promoción de la importancia del SGSI, mediante campañas de sensibilización y comunicación. 13. Revisar y atender los conceptos de seguridad relacionados con seguridad digital y protección de datos personales requeridos por las áreas de la Entidad. 14. Participar en los proyectos de integración de sistemas de gestión, gestión de cambios, nuevos productos, procesos, proyectos tecnológicos y recuperación de desastres. 15. Atender a requerimientos de acuerdos estratégicos y/o contratación en materia de seguridad digital. 16. Proyectar el Comité de Riesgos con los temas de Seguridad de la Información con el fin de dar avance sobre la atención a la Política de Seguridad Digital a la alta dirección de la Entidad. 17. Hacer seguimiento al cumplimiento del Sistema de Gestión de Seguridad Digital con respecto de las normas colombianas en materia de seguridad y privacidad digital, así como las buenas prácticas, realizando seguimiento a las acciones de mejora. 18. Realizar mejora continua al sistema de gestión de seguridad digital a través de atención a hallazgos y oportunidades de mejora emitidos por la Oficina de Control Interno y Entes de Control. 19. Atender los requerimientos normativos bajo las normas Ley 1712, Ley 1581, de MinTic, buena práctica ISO 27001, normas de Superfinanciera y demás que se generen y aquellos que soliciten los Entes de Control como son MEN, CSIRT, COLCERT y demás entidades que requieran la participación del Icetex. 20. Revisión y seguimiento de cumplimiento de seguridad de proveedores (Seguimiento a revisión de seguridad en proveedores y Seguimiento a las respuestas de revisión de seguridad por los proveedores). 21. Gestionar y revisar los usuarios de los sistemas de información. 22. Participar en los comités de tecnología de Control de cambios, log y vulnerabilidades. 23. Apoyar fundamentalmente en el CIO de la entidad para mitigar los riesgos asociados a la tecnología (Seguridad Informática o Ciberseguridad). 24. Establecer la relación con otras entidades del sector público, educación y financiero, así como entes líderes en temas de ciberseguridad y seguridad digital: ColCERT, Ministerio de Tecnologías y Sistemas de Información, Escuela Superior de Guerra, Comando Conjunto Cibernético, Centro cibernético policial, etc. 25. Las demás obligaciones que sean acordes con el objeto contractual asignado por la supervisión del contrato. 26. Elaborar informes relacionados con la ejecución de su objeto contractual y obligaciones, cuando le sean solicitados. | AJ25: 1 SI | AK25: 1 PUBLICADO | AL25: 1 PUBLICADO | AM25: 1 SI | AN25: 27803 | AO25: =IF(YEAR(TODAY())-YEAR(AN25)>100," ",YEAR(TODAY())-YEAR(AN25)) -> 49 | AP25: GRUPO_DE_CONTRATACIÓN | AQ25: NATALIA MURCIA | BF25: =BC25+BE25 -> 0 | BI25: =BF25+Q25 -> 360 | BJ25: =IF(BH25="",P25+BF25,BH25) -> 45656 | CC25: =BR25+BV25+BZ25 -> 0 | CE25: =IF(Y25=0,(W25+CC25)-CD25,IF(Y25>0,(Y25+CC25)-CD25)) -> 125058408 | CG25: =IFERROR(IF(((CE25/BI25)*(TODAY()-N25))>CE25,CE25,((CE25/BI25)*(TODAY()-N25))),"") -> 125058408 | CH25: =IF(TODAY()>BJ25,1,+(DAYS360(O25,TODAY())/DAYS360(O25,BJ25))) -> 1 | CI25: =+IF(CL25>0,DAYS360(O25,CL25)/DAYS360(O25,BJ25),CH25) -> 1 | CJ25: =IFERROR(IF(((CG25/CE25)*100)>100,100,((CG25/CE25)*100)),"") -> 100 | CK25: =IFERROR((CF25/CE25)*100,"") -> 0 | CM25: =IF(CL25>1/1/6,"LIQUIDADO",IF(BJ25=0,"",IF(BJ25>=TODAY(),"VIGENTE",IF(BJ25<TODAY(),"TERMINADO",)))) -> TERMINADO | CO25: 20242520000217-I | CP25: MASCULINO
A26: 8.1 | B26: 2024-0025 | C26: CTO | D26: CD-025-2024 | E26: 9 PRESTACIÓN DE SERVICIOS | F26: 1 PERSONA NATURAL | G26: 3 CÉDULA DE CIUDADANÍA | H26: 52228100 | I26: SANDRA GISELA TRIANA | L26: PRESTAR SERVICIOS DE APOYO TÉCNICO AL DESARROLLO DE LOS PROCESOS Y ACTIVIDADES RELACIONADOS CON LAS GESTIONES ADMINISTRATIVAS DE LA PRESIDENCIA DEL ICETEX | M26: BOGOTA | N26: 45295 | O26: 45296 | P26: 45656 | Q26: =P26-O26 -> 360 | R26: 1 FUNCIONAMIENTO | S26: CDEF-079-2024 | T26: REMUNERACION SERVICIOS | U26: 52358605 | V26: IG312001020200014 | W26: 52358605 | X26: 4412242 | AA26: SECRETARÍA_GENERAL | AB26: =IFERROR(VLOOKUP(AA26,Listas!$A$1:$C$14,2,FALSE),"") -> FREDY CÉSPEDES VILLA | AC26: =IFERROR(VLOOKUP(AA26,Listas!$A$1:$C$14,3,FALSE),"") -> 93363483 | AD26: PRESIDENCIA | AE26: PRESIDENTE | AF26: =IFERROR(VLOOKUP(AE26,Listas!$AD$1:$AF$66,2,FALSE),"") -> ALVARO HERNAN URQUIJO GOMEZ | AG26: 80505520 | AH26: 1 CONTRATACION DIRECTA | AI26: Apoyar en la digitalización requerida dentro del proceso de gestión documental y registrar en los sistemas o herramientas la información requerida como apoyo al proceso de gestión documental. 2. Efectuar el alistamiento, traslado, registro, consulta, préstamo y seguimiento de las unidades documentales solicitadas por las áreas o funcionarios del ICETEX. 3. Apoyar las acciones y proceso de transferencias primarias que realiza el Grupo de Gestión Documental. 4. Apoyar acciones de tipo operativo y gestiones administrativas del despacho que se desarrollen en el marco del respectivo proyecto de inversión relacionado con el fortalecimiento de la entidad. 5. Cumplir con los indicadores de medición establecidos para el presente contrato 6. Gestionar la creación de usuarios en los sistemas de información, para el personal directo y contratistas del Despacho, a través del diligenciamiento y entrega de los formatos respectivos al área encargada. 7. Consolidar y clasificar por áreas los documentos enviados para revisión y posterior firma del Presidente. 8. Las demás obligaciones que sean acordes con el objeto contractual y que sean asignadas por quien ejerza la función de supervisión del contrato. | AJ26: 1 SI | AK26: 1 PUBLICADO | AL26: 1 PUBLICADO | AM26: 1 SI | AN26: 27616 | AO26: =IF(YEAR(TODAY())-YEAR(AN26)>100," ",YEAR(TODAY())-YEAR(AN26)) -> 50 | AP26: GRUPO_DE_CONTRATACIÓN | AQ26: LAURA NARANJO | BF26: =BC26+BE26 -> 0 | BI26: =BF26+Q26 -> 360 | BJ26: =IF(BH26="",P26+BF26,BH26) -> 45656 | CC26: =BR26+BV26+BZ26 -> 0 | CE26: =IF(Y26=0,(W26+CC26)-CD26,IF(Y26>0,(Y26+CC26)-CD26)) -> 52358605 | CG26: =IFERROR(IF(((CE26/BI26)*(TODAY()-N26))>CE26,CE26,((CE26/BI26)*(TODAY()-N26))),"") -> 52358605 | CH26: =IF(TODAY()>BJ26,1,+(DAYS360(O26,TODAY())/DAYS360(O26,BJ26))) -> 1 | CI26: =+IF(CL26>0,DAYS360(O26,CL26)/DAYS360(O26,BJ26),CH26) -> 1 | CJ26: =IFERROR(IF(((CG26/CE26)*100)>100,100,((CG26/CE26)*100)),"") -> 100 | CK26: =IFERROR((CF26/CE26)*100,"") -> 0 | CM26: =IF(CL26>1/1/6,"LIQUIDADO",IF(BJ26=0,"",IF(BJ26>=TODAY(),"VIGENTE",IF(BJ26<TODAY(),"TERMINADO",)))) -> TERMINADO | CO26: 20243030000221-I Id: 4085780 | CP26: FEMENINO
A27: 8.2 | B27: 2024-0026 | C27: CTO | D27: CD-026-2024 | E27: 9 PRESTACIÓN DE SERVICIOS | F27: 1 PERSONA NATURAL | G27: 3 CÉDULA DE CIUDADANÍA | H27: 1136882812 | I27: MARIA CRISTINA TOBON CAMACHO | L27: PRESTAR LOS SERVICIOS PROFESIONALES ESPECIALIZADOS EN LA ARTICULACIÓN CON DIFERENTES ACTORES Y ACOMPAÑAMIENTO DE LAS ACTIVIDADES QUE REALIZA EL PRESIDENTE DE LA ENTIDAD, ASÍ COMO LA REVISIÓN DE LOS DOCUMENTOS. | M27: BOGOTA | N27: 45295 | O27: 45364 | P27: 45651 | Q27: =P27-O27 -> 287 | R27: 1 FUNCIONAMIENTO | S27: CDEF-078-2024 | T27: HONORARIOS PRE | U27: 137895647 | V27: IG312001020200012 | W27: 137895647 | X27: 11643417 | AA27: SECRETARÍA_GENERAL | AB27: =IFERROR(VLOOKUP(AA27,Listas!$A$1:$C$14,2,FALSE),"") -> FREDY CÉSPEDES VILLA | AC27: =IFERROR(VLOOKUP(AA27,Listas!$A$1:$C$14,3,FALSE),"") -> 93363483 | AD27: PRESIDENCIA | AE27: PRESIDENTE | AF27: =IFERROR(VLOOKUP(AE27,Listas!$AD$1:$AF$66,2,FALSE),"") -> ALVARO HERNAN URQUIJO GOMEZ | AG27: 80505520 | AH27: 1 CONTRATACION DIRECTA | AI27: 1. Desarrollar actividades profesionales para el control y seguimiento de la ejecución y avance de la implementación de planes, programas, estrategias y herramientas que faciliten el cumplimiento del objeto misional del ICETEX, de conformidad con las directrices impartidas por la presidencia. 2. Elaborar y preparar informes que sean requeridos por la Presidencia del ICETEX, para adelantar actividad, reunión u encuentro externo. 3. Revisar jurídicamente todas las actas, comisiones, peticiones y demás documentos que sean firmados por el presidente o requieran su aval. 4. Elaborar las bases de datos o matriz para el control y seguimiento de los compromisos que sean asignados a Presidencia, con el fin de poder implementar los objetivos institucionales de ICETEX. 5. Apoyar en la en la preparación de los temas a presentar al comité de Presidencia, así como participar de los mismos que le sean delegados por el supervisor y hacer seguimiento de los compromisos 6. Proyectar, los documentos que se relacionen con las actividades que le sean encomendadas por el supervisor del contrato, en el marco del objeto contractual. 7. Realizar aportes a las diferentes respuestas a los requerimientos internos y externos, así como a derechos de petición, consultas y demás solicitudes relacionadas con la Presidencia. 8. Acompañar los comités, mesas de trabajo y reuniones de coordinación, seguimiento o información que se programen en el marco de las actividades del presidente de la entidad, efectuando los reportes e informes pertinentes que le sean solicitados. 9. Realizar los viajes nacionales e internacionales autorizados por el supervisor en cumplimiento del contrato, cuando las necesidades del servicio lo requieran. 10. Las demás obligaciones que sean acordes con el objeto contractual asignado por quien ejerza la función de la Supervisión del Contrato y/o el Presidente de la Entidad | AJ27: 1 SI | AK27: 1 PUBLICADO | AL27: 1 PUBLICADO | AM27: 1 SI | AN27: 33233 | AO27: =IF(YEAR(TODAY())-YEAR(AN27)>100," ",YEAR(TODAY())-YEAR(AN27)) -> 35 | AP27: GRUPO_DE_CONTRATACIÓN | AQ27: LAURA NARANJO | BF27: =BC27+BE27 -> 0 | BH27: 45364 | BI27: =BF27+Q27 -> 287 | BJ27: =IF(BH27="",P27+BF27,BH27) -> 45364 | CC27: =BR27+BV27+BZ27 -> 0 | CE27: =IF(Y27=0,(W27+CC27)-CD27,IF(Y27>0,(Y27+CC27)-CD27)) -> 137895647 | CG27: =IFERROR(IF(((CE27/BI27)*(TODAY()-N27))>CE27,CE27,((CE27/BI27)*(TODAY()-N27))),"") -> 137895647 | CH27: =IF(TODAY()>BJ27,1,+(DAYS360(O27,TODAY())/DAYS360(O27,BJ27))) -> 1 | CI27: =+IF(CL27>0,DAYS360(O27,CL27)/DAYS360(O27,BJ27),CH27) -> 1 | CJ27: =IFERROR(IF(((CG27/CE27)*100)>100,100,((CG27/CE27)*100)),"") -> 100 | CK27: =IFERROR((CF27/CE27)*100,"") -> 0 | CM27: =IF(CL27>1/1/6,"LIQUIDADO",IF(BJ27=0,"",IF(BJ27>=TODAY(),"VIGENTE",IF(BJ27<TODAY(),"TERMINADO",)))) -> TERMINADO | CO27: 20243030000220-I Id: 4085774 | CP27: FEMENINO
A28: 13.75 | B28: 2024-0027 | C28: CTO | D28: CD-027-2024 | E28: 9 PRESTACIÓN DE SERVICIOS | F28: 1 PERSONA NATURAL | G28: 3 CÉDULA DE CIUDADANÍA | H28: 1031135865 | I28: LADY CATHERINE BARBOSA HENRIQUEZ | L28: PRESTAR SERVICIOS TÉCNICOS PARA APOYAR Y GESTIONAR EL DESARROLLO DE ACTIVIDADES Y PROCEDIMIENTOS RELACIONADOS CON LAS GESTIONES ADMINISTRATIVAS Y DOCUMENTALES DEL GRUPO DE ACUERDOS ESTRATÉGICOS QUE SE REQUIERAN EN EL MARCO DEL PROYECTO DE INVERSIÓN DENOMINADO "FORTALECIMIENTO ORGANIZACIONA | M28: BOGOTA | N28: 45295 | O28: 45300 | P28: 45657 | Q28: =P28-O28 -> 357 | R28: 2 INVERSIÓN | S28: CDEF-120-2024 | T28: FORTALECIMIENTO ORGANIZACIONAL | U28: 48182508 | V28: IG332901003 | W28: 48182508 | X28: 4015209 | AA28: SECRETARÍA_GENERAL | AB28: =IFERROR(VLOOKUP(AA28,Listas!$A$1:$C$14,2,FALSE),"") -> FREDY CÉSPEDES VILLA | AC28: =IFERROR(VLOOKUP(AA28,Listas!$A$1:$C$14,3,FALSE),"") -> 93363483 | AD28: SECRETARÍA_GENERAL | AE28: COORDINADOR(A) GRUPO DE ACUERDOS ESTRATÉGICOS | AF28: =IFERROR(VLOOKUP(AE28,Listas!$AD$1:$AF$66,2,FALSE),"") -> SANDRA MILENA MÁRQUEZ PARRA | AG28: =IFERROR(VLOOKUP(AE28,Listas!$AD$1:$AF$65,3,FALSE),"") -> 52487587 | AH28: 1 CONTRATACION DIRECTA | AI28: 1. Proyectar comunicaciones para atender los requerimientos internos y externos relacionados con las actividades desarrolladas por el Grupo de Acuerdos Estratégicos. 2. Llevar a cabo la radicación de los diferentes documentos que se originen al interior del Grupo de Acuerdos Estratégicos, de conformidad con lo establecido en los procedimientos de gestión documental de la entidad. 3. Apoyar los trámites y actividades administrativas del Grupo de Acuerdos Estratégicos en las cuales el supervisor solicite apoyo o sea designado. 4. Apoyar en el diligenciamiento de información en los diferentes aplicativos del ICETEX que le sean asignados por el supervisor del contrato. 5. Apoyar en la actualización, clasificación y organización de los documentos físicos y virtuales propios de los procesos del Grupo de Acuerdos Estratégicos. 6. Apoyar en la creación de los expedientes electrónicos dentro de la herramienta de gestión documental. 7. Elaborar los informes y reportes solicitados por el supervisor de acuerdo con las actividades y procesos realizados en el Grupo de Acuerdos Estratégicos. 8. Desarrollar las actividades relacionadas con la clasificación, consulta y envío al archivo de los documentos requeridos dentro del proceso de gestión documental relacionada con el Grupo de Acuerdos Estratégicos. 9. Apoyar la creación y/o actualización de los expedientes físicos y de los diferentes trámites, acorde con los procedimientos establecidos por la entidad para el manejo documental. 10. Apoyar técnicamente los procesos de organización, ordenación, restauración, inventario documental y descripción archivística de los expedientes pertenecientes al archivo del Grupo de Acuerdos Estratégicos, para su entrega al Archivo de la Entidad. 11. Apoyar la creación, identificación, actualización y control de los expedientes, documentos de los diferentes trámites requeridos para la gestión documental. 12. Apoyar técnicamente los procesos de digitalización de documentos y tramites propios del Grupo de Acuerdos Estratégicos. 13. Asistir a las reuniones a las que sea citado o designado por parte del supervisor del contrato. 14. Las demás obligaciones que sean acordes con el objeto contractual y que sean asignadas por el supervisor del presente contrato. | AJ28: 1 SI | AK28: 1 PUBLICADO | AL28: 1 PUBLICADO | AM28: 1 SI | AN28: 33589 | AO28: =IF(YEAR(TODAY())-YEAR(AN28)>100," ",YEAR(TODAY())-YEAR(AN28)) -> 34 | AP28: GRUPO_DE_CONTRATACIÓN | AQ28: PATRICIA JALLER | BF28: =BC28+BE28 -> 0 | BI28: =BF28+Q28 -> 357 | BJ28: =IF(BH28="",P28+BF28,BH28) -> 45657 | CC28: =BR28+BV28+BZ28 -> 0 | CE28: =IF(Y28=0,(W28+CC28)-CD28,IF(Y28>0,(Y28+CC28)-CD28)) -> 48182508 | CG28: =IFERROR(IF(((CE28/BI28)*(TODAY()-N28))>CE28,CE28,((CE28/BI28)*(TODAY()-N28))),"") -> 48182508 | CH28: =IF(TODAY()>BJ28,1,+(DAYS360(O28,TODAY())/DAYS360(O28,BJ28))) -> 1 | CI28: =+IF(CL28>0,DAYS360(O28,CL28)/DAYS360(O28,BJ28),CH28) -> 1 | CJ28: =IFERROR(IF(((CG28/CE28)*100)>100,100,((CG28/CE28)*100)),"") -> 100 | CK28: =IFERROR((CF28/CE28)*100,"") -> 0 | CM28: =IF(CL28>1/1/6,"LIQUIDADO",IF(BJ28=0,"",IF(BJ28>=TODAY(),"VIGENTE",IF(BJ28<TODAY(),"TERMINADO",)))) -> TERMINADO | CO28: 20243030000255-I Id: 4085844 | CP28: FEMENINO
A29: 12.1 | B29: 2024-0028 | C29: CTO | D29: CD-028-2024 | E29: 9 PRESTACIÓN DE SERVICIOS | F29: 1 PERSONA NATURAL | G29: 3 CÉDULA DE CIUDADANÍA | H29: 80095738 | I29: JUAN CARLOS ACEVEDO DURÁN | L29: PRESTAR LOS SERVICIOS PROFESIONALES FINANCIEROS ESPECIALIZADOS PARA LA ESTRUCTURACIÓN DE MECANISMOS, ESQUEMAS Y ESTÁNDARES QUE PERMITAN FORTALECER LA SIMPLIFICACIÓN, ESTANDARIZACIÓN Y SISTEMATIZACIÓN DE LOS PROCESOS Y EL FLUJO DE INFORMACIÓN QUE SOPORTA LA ADOPCIÓN DE LOS PROYECTOS DE INVERSIÓN BANCA ABIERTA Y TRANSPARENTE E INHOUSE BANKING, Y DE OPTIMIZACIÓN DE LA ESTRUCTURA PASIVO Y DIVERSIFICACIÓN DE LAS FUENTES DE FONDEO | M29: BOGOTA | N29: 45295 | O29: 45296 | P29: 45657 | Q29: =P29-O29 -> 361 | R29: 2 INVERSIÓN | S29: CDEF-120-2024 | T29: OPTIMIZACIÓN DEL PASIVO Y DIVERSIFICACIÓ | U29: 245105064 | V29: IG332902004 | W29: 245105064 | X29: 20425398 | AA29: SECRETARÍA_GENERAL | AB29: =IFERROR(VLOOKUP(AA29,Listas!$A$1:$C$14,2,FALSE),"") -> FREDY CÉSPEDES VILLA | AC29: =IFERROR(VLOOKUP(AA29,Listas!$A$1:$C$14,3,FALSE),"") -> 93363483 | AD29: VICEPRESIDENCIA_FINANCIERA | AE29: VICEPRESIDENTE FINANCIERO | AF29: =IFERROR(VLOOKUP(AE29,Listas!$AD$1:$AF$66,2,FALSE),"") -> EDGAR ANTONIO GÓMEZ ÁLVAREZ | AG29: =IFERROR(VLOOKUP(AE29,Listas!$AD$1:$AF$65,3,FALSE),"") -> 2231755 | AH29: 1 CONTRATACION DIRECTA | AI29: 1. Apoyar la articulación de las instancias correspondientes para la adopción, despliegue y apropiación de metodologías, marcos conceptuales, lineamientos, y estándares que permitan la implementación de iniciativas y proyectos de inversión de la Vicepresidencia Financiera y la transformación del Instituto. 2. Apoyar la estructuración de estudios y análisis de inteligencia de negocios que permitan la adecuada producción de información, y la analítica de datos para la toma de decisiones, la administración y gestión de recursos, y la mitigación de riesgos de la Entidad, en el marco de la modernización de las funciones financieras. 3. Apoyar la adopción, despliegue y apropiación de procesos optimizados, flujos de información y política de datos que fortalezcan la modernización de las funciones financieras del Instituto, a partir de la articulación de indicadores estratégicos e indicadores operativos, entre otros. 4. Apoyar en la estructuración de iniciativas, insumos técnicos, lineamientos, y metodologías para el fortalecimiento de la gestión financiera de la Instituto basado en tecnologías de la información, aplicaciones inteligentes, e innovación. 5. Apoyar la articulación de las instancias correspondientes para implementación metodologías, lineamientos y estándares que permitan la simplificación, estandarización y sistematización de los procesos en el marco de los proyectos de inversión a cargo de la Vicepresidencia financiera y la modernización de las funciones financieras del ICETEX. 6. Apoyar en la articulación de las instancias correspondientes para la apropiación de tableros de control, indicadores e informes que permitan la integración de datos núcleo, fuentes de información, y/o aplicativos para la óptima administración y asignación de recursos, la optimización del ciclo tesoral, y presupuestal, que redunden un cierre contable oportuno. 7. Apoyar la estructuración de los insumos técnicos y estudios requeridos para el despliegue de instrumentos, productos y/o mecanismos financieros que fortalezcan la capacidad operativa del Instituto, bajo metodologías de innovación, open banking e insurtech. 8. Apoyar en la estructuración de convenios, acuerdos, documentos técnicos, reglamentación y/o actos administrativos requeridos para el despliegue de iniciativas, y proyectos de inversión denominados Diversificación de Fuentes de Financiación, y banca abierta y transparente e inhouse banking. 9. Apoyar la estructuración de insumos técnicos necesarios para expedir actos administrativos para el cumplimiento de metas en el marco de los proyectos de inversión de la Vicepresidencia Financiera, y la Transformación del Instituto. 10. Apoyar la estructuración de insumos necesarios para dar respuestas de requerimientos de información solicitados por entes internos y/o externos, en el marco de los proyectos de inversión de la Vicepresidencia Financiera. 11. Cumplir con los indicadores de gestión establecidos. 12. Las demás obligaciones que se requieran para el cumplimiento a cabalidad del objeto contractual y que sean inherentes a la naturaleza del contrato. | AJ29: 1 SI | AK29: 1 PUBLICADO | AL29: 1 PUBLICADO | AM29: 1 SI | AN29: 29977 | AO29: =IF(YEAR(TODAY())-YEAR(AN29)>100," ",YEAR(TODAY())-YEAR(AN29)) -> 43 | AP29: GRUPO_DE_CONTRATACIÓN | AQ29: SEBASTIAN AYALA | BF29: =BC29+BE29 -> 0 | BI29: =BF29+Q29 -> 361 | BJ29: =IF(BH29="",P29+BF29,BH29) -> 45657 | CC29: =BR29+BV29+BZ29 -> 0 | CE29: =IF(Y29=0,(W29+CC29)-CD29,IF(Y29>0,(Y29+CC29)-CD29)) -> 245105064 | CG29: =IFERROR(IF(((CE29/BI29)*(TODAY()-N29))>CE29,CE29,((CE29/BI29)*(TODAY()-N29))),"") -> 245105064 | CH29: =IF(TODAY()>BJ29,1,+(DAYS360(O29,TODAY())/DAYS360(O29,BJ29))) -> 1 | CI29: =+IF(CL29>0,DAYS360(O29,CL29)/DAYS360(O29,BJ29),CH29) -> 1 | CJ29: =IFERROR(IF(((CG29/CE29)*100)>100,100,((CG29/CE29)*100)),"") -> 100 | CK29: =IFERROR((CF29/CE29)*100,"") -> 0 | CM29: =IF(CL29>1/1/6,"LIQUIDADO",IF(BJ29=0,"",IF(BJ29>=TODAY(),"VIGENTE",IF(BJ29<TODAY(),"TERMINADO",)))) -> TERMINADO | CO29: 20243030000230-I Id: 4085795 | CP29: MASCULINO
A30: 4.17 | B30: 2024-0029 | C30: CTO | D30: CD-029-2024 | E30: 9 PRESTACIÓN DE SERVICIOS | F30: 1 PERSONA NATURAL | G30: 3 CÉDULA DE CIUDADANÍA | H30: 1013581478 | I30: YEIMMY MARISOL CASTELLANOS ALVARADO | L30: PRESTAR LOS SERVICIOS PROFESIONALES ESPECIALIZADOS PARA DIRECCIONAR ESTRATÉGICAMENTE LA ESTRUCTURACIÓN, SEGUIMIENTO Y CONTROL DE LOS PROCESOS, POLÍTICAS PÚBLICAS, GESTIÓN DEL RIESGO, GESTIÓN DEL CRÉDITO Y DEMÁS PLANES DE GESTIÓN Y AUTOCONTROL, DE CONFORMIDAD CON LOS REQUERIMIENTOS ORGANIZACIONALES Y NORMATIVOS DEL ICETEX. | M30: BOGOTA | N30: 45295 | O30: 45296 | P30: 45656 | Q30: =P30-O30 -> 360 | R30: 1 FUNCIONAMIENTO | S30: CDEF-40-2024 | T30: HONORARIOS – OCM | U30: 162860039 | V30: IG312001020240012 | W30: 162860039 | X30: 13609474 | AA30: SECRETARÍA_GENERAL | AB30: =IFERROR(VLOOKUP(AA30,Listas!$A$1:$C$14,2,FALSE),"") -> FREDY CÉSPEDES VILLA | AC30: =IFERROR(VLOOKUP(AA30,Listas!$A$1:$C$14,3,FALSE),"") -> 93363483 | AD30: OFICINA_COMERCIAL_Y_DE_MERCADEO | AE30: JEFE OFICINA COMERCIAL Y DE MERCADEO | AF30: =IFERROR(VLOOKUP(AE30,Listas!$AD$1:$AF$66,2,FALSE),"") -> RODOLFO GIOVANNI CANCHILA SUÁREZ | AG30: =IFERROR(VLOOKUP(AE30,Listas!$AD$1:$AF$65,3,FALSE),"") -> 79672493 | AH30: 1 CONTRATACION DIRECTA | AI30: 1. Apoyar la articulación de las instancias correspondientes para la adopción, despliegue y apropiación de metodologías, marcos conceptuales, lineamientos, y estándares que permitan la implementación de iniciativas y proyectos de inversión de la Vicepresidencia Financiera y la transformación del Instituto. 2. Apoyar la estructuración de estudios y análisis de inteligencia de negocios que permitan la adecuada producción de información, y la analítica de datos para la toma de decisiones, la administración y gestión de recursos, y la mitigación de riesgos de la Entidad, en el marco de la modernización de las funciones financieras. 3. Apoyar la adopción, despliegue y apropiación de procesos optimizados, flujos de información y política de datos que fortalezcan la modernización de las funciones financieras del Instituto, a partir de la articulación de indicadores estratégicos e indicadores operativos, entre otros. 4. Apoyar en la estructuración de iniciativas, insumos técnicos, lineamientos, y metodologías para el fortalecimiento de la gestión financiera de la Instituto basado en tecnologías de la información, aplicaciones inteligentes, e innovación. 5. Apoyar la articulación de las instancias correspondientes para implementación metodologías, lineamientos y estándares que permitan la simplificación, estandarización y sistematización de los procesos en el marco de los proyectos de inversión a cargo de la Vicepresidencia financiera y la modernización de las funciones financieras del ICETEX. 6. Apoyar en la articulación de las instancias correspondientes para la apropiación de tableros de control, indicadores e informes que permitan la integración de datos núcleo, fuentes de información, y/o aplicativos para la óptima administración y asignación de recursos, la optimización del ciclo tesoral, y presupuestal, que redunden un cierre contable oportuno. 7. Apoyar la estructuración de los insumos técnicos y estudios requeridos para el despliegue de instrumentos, productos y/o mecanismos financieros que fortalezcan la capacidad operativa del Instituto, bajo metodologías de innovación, open banking e insurtech. 8. Apoyar en la estructuración de convenios, acuerdos, documentos técnicos, reglamentación y/o actos administrativos requeridos para el despliegue de iniciativas, y proyectos de inversión denominados Diversificación de Fuentes de Financiación, y banca abierta y transparente e inhouse banking. 9. Apoyar la estructuración de insumos técnicos necesarios para expedir actos administrativos para el cumplimiento de metas en el marco de los proyectos de inversión de la Vicepresidencia Financiera, y la Transformación del Instituto. 10. Apoyar la estructuración de insumos necesarios para dar respuestas de requerimientos de información solicitados por entes internos y/o externos, en el marco de los proyectos de inversión de la Vicepresidencia Financiera. 11. Cumplir con los indicadores de gestión establecidos. 12. Las demás obligaciones que se requieran para el cumplimiento a cabalidad del objeto contractual y que sean inherentes a la naturaleza del contrato. | AJ30: 1 SI | AK30: 1 PUBLICADO | AL30: 1 PUBLICADO | AM30: 1 SI | AN30: 32382 | AO30: =IF(YEAR(TODAY())-YEAR(AN30)>100," ",YEAR(TODAY())-YEAR(AN30)) -> 37 | AP30: GRUPO_DE_CONTRATACIÓN | AQ30: BRESMAN SANCHEZ | BF30: =BC30+BE30 -> 0 | BI30: =BF30+Q30 -> 360 | BJ30: =IF(BH30="",P30+BF30,BH30) -> 45656 | CC30: =BR30+BV30+BZ30 -> 0 | CE30: =IF(Y30=0,(W30+CC30)-CD30,IF(Y30>0,(Y30+CC30)-CD30)) -> 162860039 | CG30: =IFERROR(IF(((CE30/BI30)*(TODAY()-N30))>CE30,CE30,((CE30/BI30)*(TODAY()-N30))),"") -> 162860039 | CH30: =IF(TODAY()>BJ30,1,+(DAYS360(O30,TODAY())/DAYS360(O30,BJ30))) -> 1 | CI30: =+IF(CL30>0,DAYS360(O30,CL30)/DAYS360(O30,BJ30),CH30) -> 1 | CJ30: =IFERROR(IF(((CG30/CE30)*100)>100,100,((CG30/CE30)*100)),"") -> 100 | CK30: =IFERROR((CF30/CE30)*100,"") -> 0 | CM30: =IF(CL30>1/1/6,"LIQUIDADO",IF(BJ30=0,"",IF(BJ30>=TODAY(),"VIGENTE",IF(BJ30<TODAY(),"TERMINADO",)))) -> TERMINADO | CO30: 20243030000256-I Id: 4085847 | CP30: FEMENINO
A31: 4.2 | B31: 2024-0030 | C31: CTO | D31: CD-030-2024 | E31: 9 PRESTACIÓN DE SERVICIOS | F31: 1 PERSONA NATURAL | G31: 3 CÉDULA DE CIUDADANÍA | H31: 1049628299 | I31: ERIKA DANIELA ROJAS MORENO | L31: PRESTAR SERVICIOS PROFESIONALES ESPECIALIZADOS, PARA ADELANTAR LA GESTIÓN JURÍDICA IDÓNEA DE APOYO Y ACOMPAÑAMIENTO QUE SURJAN CON OCASIÓN AL DESARROLLO ADMINISTRATIVO, OPERATIVO Y CONTRACTUAL DE LOS PROCESOS Y PROYECTOS DE LA OFICINA DE COMERCIAL Y DE MERCADEO Y SUS DIFERENTES EQUIPOS DE TRABAJO | M31: BOGOTA | N31: 45295 | O31: 45296 | P31: 45656 | Q31: =P31-O31 -> 360 | R31: 1 FUNCIONAMIENTO | S31: CDEF-85-2024 | T31: HONORARIOS – OCM | U31: 108571951 | V31: IG312001020240012 | W31: 108571951 | X31: 9072865 | AA31: SECRETARÍA_GENERAL | AB31: =IFERROR(VLOOKUP(AA31,Listas!$A$1:$C$14,2,FALSE),"") -> FREDY CÉSPEDES VILLA | AC31: =IFERROR(VLOOKUP(AA31,Listas!$A$1:$C$14,3,FALSE),"") -> 93363483 | AD31: OFICINA_COMERCIAL_Y_DE_MERCADEO | AE31: JEFE OFICINA COMERCIAL Y DE MERCADEO | AF31: =IFERROR(VLOOKUP(AE31,Listas!$AD$1:$AF$66,2,FALSE),"") -> RODOLFO GIOVANNI CANCHILA SUÁREZ | AG31: =IFERROR(VLOOKUP(AE31,Listas!$AD$1:$AF$65,3,FALSE),"") -> 79672493 | AH31: 1 CONTRATACION DIRECTA | AI31: 1 9. Acompañar, revisar, ajustar, la documentación requerida en el marco del trámite de modificaciones, Prórrogas, adiciones, cesiones etc., de los contratos de la Oficina Comercial y de Mercadeo. 10. Acompañar los tramites que, en los procesos de selección de contratistas adelantados por las oficinas territoriales le sean asignados. 11. Realizar seguimiento al procedimiento de liquidación de contratos velando porque no se pierda competencia legal para realizar las liquidaciones. 12. Acompañar la supervisión de los contratos que le sean asignados, desde el punto de vista jurídico, de conformidad con lo establecido en el Manual de Contratación vigente de la Entidad. . Asesorar jurídicamente a la Oficina Comercial y de Mercadeo en asuntos propios del ordenamiento jurídico, administrativo y contractual, que le sean asignados en el proceso de toma de decisiones. 2. Elaborar o analizar o revisar jurídicamente las comunicaciones, documentos y procesos que deba firmar el jefe de la Oficina Comercial y de Mercadeo, así como a las coordinaciones de dicha Oficina y de las zonas territoriales. 3. Asesorar jurídicamente los temas en reuniones que deba asistir en el marco del contrato y cumplir con los compromisos que le sean asignados para su seguimiento y entrega. 4. Dar aplicación a directrices y normas que en materia contratación deba atender la Oficina Comercial y de Mercadeo. 5. Asesorar a la Oficina Comercial y de Mercadeo en trámites relacionados con requerimientos de entes de control, organismos públicos o privados. 6. Asesorar y/o revisar y/o ajustar, la estructuración, según asignación de la supervisión del contrato, los estudios previos y verificar la documentación allegada para viabilidad de la contratación, con base en las normas en materia de contratación aplicables al ICETEX. 7. Consultar, verificar, realizar, las actividades propias de los procedimientos precontractuales, contractuales y pos contractuales requeridos en el marco de las contrataciones de bienes y servicios que se desarrollen en la Oficina de Comercial y de Mercadeo. 8. Acompañar, revisar, ajustar, la documentación requerida en el marco del trámite de vigencias futuras para la contratación de necesidades de la Oficina Comercial y de Mercadeo. 13. Las demás que sean inherentes para el logro del objeto contratado, asignadas por el supervisor del contrato. | AJ31: 1 SI | AK31: 1 PUBLICADO | AL31: 1 PUBLICADO | AM31: 1 SI | AN31: 33573 | AO31: =IF(YEAR(TODAY())-YEAR(AN31)>100," ",YEAR(TODAY())-YEAR(AN31)) -> 34 | AP31: GRUPO_DE_CONTRATACIÓN | AQ31: BRESMAN SANCHEZ | BF31: =BC31+BE31 -> 0 | BI31: =BF31+Q31 -> 360 | BJ31: =IF(BH31="",P31+BF31,BH31) -> 45656 | CC31: =BR31+BV31+BZ31 -> 0 | CE31: =IF(Y31=0,(W31+CC31)-CD31,IF(Y31>0,(Y31+CC31)-CD31)) -> 108571951 | CG31: =IFERROR(IF(((CE31/BI31)*(TODAY()-N31))>CE31,CE31,((CE31/BI31)*(TODAY()-N31))),"") -> 108571951 | CH31: =IF(TODAY()>BJ31,1,+(DAYS360(O31,TODAY())/DAYS360(O31,BJ31))) -> 1 | CI31: =+IF(CL31>0,DAYS360(O31,CL31)/DAYS360(O31,BJ31),CH31) -> 1 | CJ31: =IFERROR(IF(((CG31/CE31)*100)>100,100,((CG31/CE31)*100)),"") -> 100 | CK31: =IFERROR((CF31/CE31)*100,"") -> 0 | CM31: =IF(CL31>1/1/6,"LIQUIDADO",IF(BJ31=0,"",IF(BJ31>=TODAY(),"VIGENTE",IF(BJ31<TODAY(),"TERMINADO",)))) -> TERMINADO | CO31: 20243030000263-I Id: 4085856 | CP31: FEMENINO
A32: 4.71 | B32: 2024-0031 | C32: CTO | D32: CD-031-2024 | E32: 9 PRESTACIÓN DE SERVICIOS | F32: 1 PERSONA NATURAL | G32: 3 CÉDULA DE CIUDADANÍA | H32: 1070819079 | I32: FERNANDO LUIS BARRIOS ESCOBAR | L32: PRESTAR SERVICIOS PROFESIONALES ESPECIALIZADOS PARA ADMINISTRAR Y COORDINAR ACTIVIDADES CONTRACTUALES Y ADMINISTRATIVAS NECESARIAS EN EL CONTEXTO DEL AVANCE DE PROYECTOS RELACIONADOS CON EL DESARROLLO DEL PLAN ESTRATÉGICO DE LA ENTIDAD Y LA "POLÍTICA DE GUÍA, INFORMACIÓN Y ACOMPAÑAMIENTO | M32: MONTERIA | N32: 45295 | O32: 45295 | P32: 45656 | Q32: =P32-O32 -> 361 | R32: 2 INVERSIÓN | S32: CDEF-39-2024 | T32: COMUNIDAD ICETEX | U32: 84859899 | V32: IG332911001 | W32: 84859899 | X32: 7111165 | AA32: SECRETARÍA_GENERAL | AB32: =IFERROR(VLOOKUP(AA32,Listas!$A$1:$C$14,2,FALSE),"") -> FREDY CÉSPEDES VILLA | AC32: =IFERROR(VLOOKUP(AA32,Listas!$A$1:$C$14,3,FALSE),"") -> 93363483 | AD32: OFICINA_COMERCIAL_Y_DE_MERCADEO | AE32: JEFE OFICINA COMERCIAL Y DE MERCADEO | AF32: =IFERROR(VLOOKUP(AE32,Listas!$AD$1:$AF$66,2,FALSE),"") -> RODOLFO GIOVANNI CANCHILA SUÁREZ | AG32: =IFERROR(VLOOKUP(AE32,Listas!$AD$1:$AF$65,3,FALSE),"") -> 79672493 | AH32: 1 CONTRATACION DIRECTA | AI32: Participar en la planeación, ejecución y seguimiento de las actividades que requiera el proyecto “Comunidad ICETEX”. 2. Acompañar los procesos precontractuales que le sean asignados para la ejecución de las actividades del proyecto “Comunidad ICETEX”. 3. Hacer seguimiento a la ejecución de recursos del proyecto “Comunidad ICETEX”. 4. Apoyar la gestión administrativa encaminada a facilitar el desarrollo y ejecución de las actividades del proyecto “Comunidad ICETEX”. 5. Apoyar los mecanismos estratégicos que permitan cumplir con los indicadores de gestión, planes de acción y planes de mejora del proyecto “Comunidad ICETEX”. 6. Asistir a reuniones y/o comités de conformidad con las necesidades de la entidad y la designación del supervisor del contrato. 7. Informe mensual de actividades y cumplimiento de los indicadores de gestión establecidos. 8. Apoyar la supervisión de los contratos que le sean asignados, desde el punto de vista técnico y/o administrativo y/o financiero y/o contable, de conformidad con lo establecido en el Manual de Contratación de la Entidad. 9. Las demás obligaciones que se requieran para el cumplimiento a cabalidad del objeto contractual y que sean inherentes a la naturaleza del contrato. | AJ32: 1 SI | AK32: 1 PUBLICADO | AL32: 1 PUBLICADO | AM32: 1 SI | AN32: 33940 | AO32: =IF(YEAR(TODAY())-YEAR(AN32)>100," ",YEAR(TODAY())-YEAR(AN32)) -> 33 | AP32: GRUPO_DE_CONTRATACIÓN | AQ32: CAMILO CEDIEL | BF32: =BC32+BE32 -> 0 | BI32: =BF32+Q32 -> 361 | BJ32: =IF(BH32="",P32+BF32,BH32) -> 45656 | CC32: =BR32+BV32+BZ32 -> 0 | CE32: =IF(Y32=0,(W32+CC32)-CD32,IF(Y32>0,(Y32+CC32)-CD32)) -> 84859899 | CG32: =IFERROR(IF(((CE32/BI32)*(TODAY()-N32))>CE32,CE32,((CE32/BI32)*(TODAY()-N32))),"") -> 84859899 | CH32: =IF(TODAY()>BJ32,1,+(DAYS360(O32,TODAY())/DAYS360(O32,BJ32))) -> 1 | CI32: =+IF(CL32>0,DAYS360(O32,CL32)/DAYS360(O32,BJ32),CH32) -> 1 | CJ32: =IFERROR(IF(((CG32/CE32)*100)>100,100,((CG32/CE32)*100)),"") -> 100 | CK32: =IFERROR((CF32/CE32)*100,"") -> 0 | CM32: =IF(CL32>1/1/6,"LIQUIDADO",IF(BJ32=0,"",IF(BJ32>=TODAY(),"VIGENTE",IF(BJ32<TODAY(),"TERMINADO",)))) -> TERMINADO | CP32: MASCULINO
A33: 13.42 | B33: 2024-0032 | C33: CTO | D33: CD-032-2024 | E33: 9 PRESTACIÓN DE SERVICIOS | F33: 1 PERSONA NATURAL | G33: 3 CÉDULA DE CIUDADANÍA | H33: 52370324 | I33: ANGELA MARÍA GAYÓN MARTÍNEZ | L33: PRESTACIÓN DE SERVICIOS PROFESIONALES ESPECIALIZADOS PARA APOYAR EN EL DESARROLLO Y SEGUIMIENTO DE LOS PLANES Y PROYECTOS DE LA POLÍTICA DE COMPRAS Y CONTRATACIÓN PÚBLICA DE LA ENTIDAD EN EL MARCO DEL PROYECTO DENOMINADO “FORTALECIMIENTO ORGANIZACIONAL" DEL ICETEX. | M33: BOGOTA | N33: 45295 | O33: 45300 | P33: 45481 | Q33: =P33-O33 -> 181 | R33: 2 INVERSIÓN | S33: CDEF-119-2024 | T33: FORTALECIMIENTO ORGANIZACIONAL | U33: 102790731 | V33: IG 332901003 | W33: 102790731 | X33: 8565894 | AA33: SECRETARÍA_GENERAL | AB33: =IFERROR(VLOOKUP(AA33,Listas!$A$1:$C$14,2,FALSE),"") -> FREDY CÉSPEDES VILLA | AC33: =IFERROR(VLOOKUP(AA33,Listas!$A$1:$C$14,3,FALSE),"") -> 93363483 | AD33: SECRETARÍA_GENERAL | AE33: COORDINADOR(A) GRUPO DE CONTRATACIÓN | AF33: =IFERROR(VLOOKUP(AE33,Listas!$AD$1:$AF$66,2,FALSE),"") -> DIANA BARRERA MEDINA | AG33: =IFERROR(VLOOKUP(AE33,Listas!$AD$1:$AF$65,3,FALSE),"") -> 52964360 | AH33: 1 CONTRATACION DIRECTA | AJ33: 1 SI | AK33: 1 PUBLICADO | AL33: 1 PUBLICADO | AM33: 1 SI | AN33: 28292 | AO33: =IF(YEAR(TODAY())-YEAR(AN33)>100," ",YEAR(TODAY())-YEAR(AN33)) -> 48 | AP33: GRUPO_DE_CONTRATACIÓN | AQ33: LAURA NARANJO | BF33: =BC33+BE33 -> 0 | BI33: =BF33+Q33 -> 181 | BJ33: =IF(BH33="",P33+BF33,BH33) -> 45481 | CC33: =BR33+BV33+BZ33 -> 0 | CE33: =IF(Y33=0,(W33+CC33)-CD33,IF(Y33>0,(Y33+CC33)-CD33)) -> 102790731 | CG33: =IFERROR(IF(((CE33/BI33)*(TODAY()-N33))>CE33,CE33,((CE33/BI33)*(TODAY()-N33))),"") -> 102790731 | CH33: =IF(TODAY()>BJ33,1,+(DAYS360(O33,TODAY())/DAYS360(O33,BJ33))) -> 1 | CI33: =+IF(CL33>0,DAYS360(O33,CL33)/DAYS360(O33,BJ33),CH33) -> 1 | CJ33: =IFERROR(IF(((CG33/CE33)*100)>100,100,((CG33/CE33)*100)),"") -> 100 | CK33: =IFERROR((CF33/CE33)*100,"") -> 0 | CM33: =IF(CL33>1/1/6,"LIQUIDADO",IF(BJ33=0,"",IF(BJ33>=TODAY(),"VIGENTE",IF(BJ33<TODAY(),"TERMINADO",)))) -> TERMINADO | CP33: FEMENINO
A34: 12.32 | B34: 2024-0033 | C34: CTO | D34: CD-033-2024 | E34: 9 PRESTACIÓN DE SERVICIOS | F34: 1 PERSONA NATURAL | G34: 3 CÉDULA DE CIUDADANÍA | H34: 1032397330 | I34: SERGIO ERNESTO BUSTOS HERRERA | L34: PRESTAR LOS SERVICIOS PROFESIONALES ESPECIALIZADOS PARA LA ADOPCIÓN DE LOS ESTÁNDARES, BUENAS PRÁCTICAS Y PROCEDIMIENTOS QUE SOPORTAN LA APROPIACIÓN HERRAMIENTAS TECNOLÓGICAS DISPUESTAS POR LA ENTIDAD PARA LA REGULARIZACIÓN Y SOSTENIBILIDAD DE LA INFORMACIÓN FINANCIERA DE LOS RECURSOS ADMINISTRADOS POR EL ICETEX, EN EL MARCO PROYECTO DE INVERSIÓN BANCA ABIERTA Y TRANSPARENTE E INHOUSE BANKING. | M34: BOGOTA | N34: 45300 | O34: 45301 | P34: 45656 | Q34: =P34-O34 -> 355 | R34: 2 INVERSIÓN | S34: CDEF-124-2024 | T34: BANCA ABIERTA Y TRANSPARENTE E INHOUSE B | U34: 97104180 | V34: IG 332902005 | W34: 97104180 | X34: 6130324 | AA34: SECRETARÍA_GENERAL | AB34: =IFERROR(VLOOKUP(AA34,Listas!$A$1:$C$14,2,FALSE),"") -> FREDY CÉSPEDES VILLA | AC34: =IFERROR(VLOOKUP(AA34,Listas!$A$1:$C$14,3,FALSE),"") -> 93363483 | AD34: VICEPRESIDENCIA_FINANCIERA | AE34: DIRECTOR(A) DE CONTABILIDAD | AF34: =IFERROR(VLOOKUP(AE34,Listas!$AD$1:$AF$66,2,FALSE),"") -> MARINA AZUCENA MEDINA SANDOVAL | AG34: =IFERROR(VLOOKUP(AE34,Listas!$AD$1:$AF$65,3,FALSE),"") -> 51842510 | AH34: 1 CONTRATACION DIRECTA | AI34: 1. Apoyar la estructuración de mecanismos de registro, seguimiento y control para la estabilización de la implementación de la herramientas y aplicaciones que soportan el proceso en la regularización de la información contable de los recursos en administración. 2. Apoyar la articulación entre las áreas que intervienen en los procesos de regularización y sostenibilidad de la información financiera de los recursos administrados por el ICETEX, para la estabilización y adopción de las herramientas, lineamientos, estándares y mecanismos para la optimización del proceso de regularización de partidas conciliatorias. 3. Apoyar la elaboración de insumos técnicos para la implementación de las herramientas, lineamientos, estándares y mecanismos para la optimización del procedimiento de conciliación y regularización de la información contable de los recursos en administración. 4. Apoyar la gestión de seguimiento y control de la información, herramientas, y sistemas que soportan la operación recurrente de la información contable de los recursos entregados en administración por los constituyentes de los fondos y alianzas, a través de la verificación y conciliación de los estados de cuenta. 5. Apoyar en la gestión de consolidación, revisión y registro de las partidas conciliatorias derivado del proceso de sostenibilidad y regularización de la información financiera en los estados financieros que apliquen, con el objetivo de garantizar la calidad de la información contable y financiera del Instituto. 6. Apoyar en la gestión y soporte al proceso de reconocimiento contable de las obligaciones a cargo del ICETEX relativas a las cuentas por pagar generadas en la operación de la Entidad. 7. Apoyar en la estructuración y verificación de la exógena de los convenios administrados por la Entidad. 8. Apoyar en la formulación de los insumos técnicos que permitan dar respuesta de forma oportuna, a los requerimientos de información por agentes interno y externos. 9. Apoyar la estructuración de los insumos necesarios para el desarrollo de los procesos en el marco de la implementación de los proyectos de inversión a cargo de la Vicepresidencia Financiera. 10. Las demás obligaciones que se requieran para el cumplimiento a cabalidad del objeto contractual y que sean inherentes a la naturaleza del contrato. | AJ34: 1 SI | AK34: 1 PUBLICADO | AL34: 1 PUBLICADO | AM34: 1 SI | AN34: 32044 | AO34: =IF(YEAR(TODAY())-YEAR(AN34)>100," ",YEAR(TODAY())-YEAR(AN34)) -> 38 | AP34: GRUPO_DE_CONTRATACIÓN | AQ34: SEBASTIAN AYALA | BF34: =BC34+BE34 -> 0 | BI34: =BF34+Q34 -> 355 | BJ34: =IF(BH34="",P34+BF34,BH34) -> 45656 | CC34: =BR34+BV34+BZ34 -> 0 | CE34: =IF(Y34=0,(W34+CC34)-CD34,IF(Y34>0,(Y34+CC34)-CD34)) -> 97104180 | CG34: =IFERROR(IF(((CE34/BI34)*(TODAY()-N34))>CE34,CE34,((CE34/BI34)*(TODAY()-N34))),"") -> 97104180 | CH34: =IF(TODAY()>BJ34,1,+(DAYS360(O34,TODAY())/DAYS360(O34,BJ34))) -> 1 | CI34: =+IF(CL34>0,DAYS360(O34,CL34)/DAYS360(O34,BJ34),CH34) -> 1 | CJ34: =IFERROR(IF(((CG34/CE34)*100)>100,100,((CG34/CE34)*100)),"") -> 100 | CK34: =IFERROR((CF34/CE34)*100,"") -> 0 | CM34: =IF(CL34>1/1/6,"LIQUIDADO",IF(BJ34=0,"",IF(BJ34>=TODAY(),"VIGENTE",IF(BJ34<TODAY(),"TERMINADO",)))) -> TERMINADO | CO34: 20243030000235-I Id: 4085805 | CP34: MASCULINO
A35: 13.37 | B35: 2024-0034 | C35: CTO | D35: CD-034-2024 | E35: 9 PRESTACIÓN DE SERVICIOS | F35: 1 PERSONA NATURAL | G35: 3 CÉDULA DE CIUDADANÍA | H35: 73239241 | I35: ORLANDO ELIAS CURE ALVAREZ | L35: PRESTACIÓN DE SERVICIOS PROFESIONALES ECONÓMICOS ESPECIALIZADOS PARA APOYAR EL DESARROLLO Y SEGUIMIENTO DE LA ACTIVIDAD CONTRACTUAL EN EL MARCO DEL PROYECTO DE FORTALECIMIENTO ORGANIZACIONAL Y LA IMPLEMENTACIÓN DE LA POLÍTICA DE COMPRAS PÚBLICAS Y DE CONTRATACIÓN DEL ICETEX | M35: BOGOTA | N35: 45295 | O35: 45296 | P35: 45656 | Q35: =P35-O35 -> 360 | R35: 2 INVERSIÓN | S35: CDEF-23-2024 | T35: FORTALECIMIENTO ORGANIZACIONAL | U35: 102790731 | V35: IG 332901003 | W35: 102790731 | X35: 8565894 | AA35: SECRETARÍA_GENERAL | AB35: =IFERROR(VLOOKUP(AA35,Listas!$A$1:$C$14,2,FALSE),"") -> FREDY CÉSPEDES VILLA | AC35: =IFERROR(VLOOKUP(AA35,Listas!$A$1:$C$14,3,FALSE),"") -> 93363483 | AD35: SECRETARÍA_GENERAL | AE35: COORDINADOR(A) GRUPO DE CONTRATACIÓN | AF35: =IFERROR(VLOOKUP(AE35,Listas!$AD$1:$AF$66,2,FALSE),"") -> DIANA BARRERA MEDINA | AG35: =IFERROR(VLOOKUP(AE35,Listas!$AD$1:$AF$65,3,FALSE),"") -> 52964360 | AH35: 1 CONTRATACION DIRECTA | AI35: 1. Hacer parte del comité de estructuración y/o apoyar a las diferentes áreas del ICETEX en la estructuración de los estudios previos de los certámenes o tramites contractuales, en especial lo que respecta al análisis del sector y estudio del mercado, así como en la definición de factores de selección que permitan identificar la oferta más favorable desde el punto de vista económico y financiero de las actividades planeadas en el Plan Anual de Adquisiciones 2024. 2. Brindar apoyo en la articulación de los temas financieros que se requieran en las etapas precontractual y contractual de los certámenes o trámites contractuales. 3. Hacer parte del comité evaluador, y/o apoyar cuando se requiera al comité́ ́ evaluador financiero en la revisión de la parte contable- financiera de las propuestas recibidas, teniendo en cuenta los requisitos solicitados en los Términos de Referencia para los certámenes o trámites respectivos. 4. Realizar los Trámites financieros pertinentes de los certámenes, trámites contractuales o liquidaciones relacionados con la ejecución presupuestal y/o balance económico de los contratos o convenios ante la Vicepresidencia Financiera y/o Grupo de Presupuesto, según se requiera. 5. Apoyar en los informes estadísticos de ejecución de presupuesto de los certámenes o trámites contractuales que requiera el supervisor del contrato. | AJ35: 1 SI | AK35: 1 PUBLICADO | AL35: 1 PUBLICADO | AM35: 1 SI | AN35: 28027 | AO35: =IF(YEAR(TODAY())-YEAR(AN35)>100," ",YEAR(TODAY())-YEAR(AN35)) -> 49 | AP35: GRUPO_DE_CONTRATACIÓN | AQ35: LAURA NARANJO | BF35: =BC35+BE35 -> 0 | BI35: =BF35+Q35 -> 360 | BJ35: =IF(BH35="",P35+BF35,BH35) -> 45656 | CC35: =BR35+BV35+BZ35 -> 0 | CE35: =IF(Y35=0,(W35+CC35)-CD35,IF(Y35>0,(Y35+CC35)-CD35)) -> 102790731 | CG35: =IFERROR(IF(((CE35/BI35)*(TODAY()-N35))>CE35,CE35,((CE35/BI35)*(TODAY()-N35))),"") -> 102790731 | CH35: =IF(TODAY()>BJ35,1,+(DAYS360(O35,TODAY())/DAYS360(O35,BJ35))) -> 1 | CI35: =+IF(CL35>0,DAYS360(O35,CL35)/DAYS360(O35,BJ35),CH35) -> 1 | CJ35: =IFERROR(IF(((CG35/CE35)*100)>100,100,((CG35/CE35)*100)),"") -> 100 | CK35: =IFERROR((CF35/CE35)*100,"") -> 0 | CM35: =IF(CL35>1/1/6,"LIQUIDADO",IF(BJ35=0,"",IF(BJ35>=TODAY(),"VIGENTE",IF(BJ35<TODAY(),"TERMINADO",)))) -> TERMINADO | CP35: MASCULINO
A36: 13.44 | B36: 2024-0035 | C36: CTO | D36: CD-035-2024 | E36: 9 PRESTACIÓN DE SERVICIOS | F36: 1 PERSONA NATURAL | G36: 3 CÉDULA DE CIUDADANÍA | H36: 37861231 | I36: ERIKA CLEMENCIA ROMERO GUERRERO | L36: PRESTAR SERVICIOS PROFESIONALES JURIDICOS EN LAS ACTIVIDADES PROPIAS DEL GRUPO DE CONTRATACIÓN | M36: BOGOTA | N36: 45295 | O36: 45295 | P36: 45656 | Q36: =P36-O36 -> 361 | R36: 2 INVERSIÓN | S36: CDEF-29-2024 | T36: FORTALECIMIENTO ORGANIZACIONAL | U36: 92416800 | V36: IG 332901003 | W36: 92416800 | X36: 7701400 | AA36: SECRETARÍA_GENERAL | AB36: =IFERROR(VLOOKUP(AA36,Listas!$A$1:$C$14,2,FALSE),"") -> FREDY CÉSPEDES VILLA | AC36: =IFERROR(VLOOKUP(AA36,Listas!$A$1:$C$14,3,FALSE),"") -> 93363483 | AD36: SECRETARÍA_GENERAL | AE36: COORDINADOR(A) GRUPO DE CONTRATACIÓN | AF36: =IFERROR(VLOOKUP(AE36,Listas!$AD$1:$AF$66,2,FALSE),"") -> DIANA BARRERA MEDINA | AG36: =IFERROR(VLOOKUP(AE36,Listas!$AD$1:$AF$65,3,FALSE),"") -> 52964360 | AH36: 1 CONTRATACION DIRECTA | AI36: 1. Apoyar al Grupo de Contratación en la coordinación y seguimiento para el cumplimiento de los asuntos a su cargo, especialmente en la medición de tiempos de entrega de acuerdo a la planeación estratégica del Grupo y a las necesidades de la Entidad. 2. Acompañar el seguimiento para el cumplimiento de lineamientos y procedimientos jurídicos de la Entidad. 3. Acompañar y asesorar el proceso de planeación estratégica de la Entidad y el seguimiento al Plan de Adquisiciones. 4. Apoyar la organización y desarrollo del Comité de Contratación del ICETEX, elaborar las actas y llevar el control de los asuntos presentados por las distintas áreas interesadas. 5. Cumplir con los indicadores de gestión establecidos. 6. Las demás actividades que le sean asignadas por el Supervisor, en el marco del objeto contractual | AJ36: 1 SI | AK36: 1 PUBLICADO | AL36: 1 PUBLICADO | AM36: 1 SI | AN36: 29274 | AO36: =IF(YEAR(TODAY())-YEAR(AN36)>100," ",YEAR(TODAY())-YEAR(AN36)) -> 45 | AP36: GRUPO_DE_CONTRATACIÓN | AQ36: LAURA NARANJO | BF36: =BC36+BE36 -> 0 | BI36: =BF36+Q36 -> 361 | BJ36: =IF(BH36="",P36+BF36,BH36) -> 45656 | CC36: =BR36+BV36+BZ36 -> 0 | CE36: =IF(Y36=0,(W36+CC36)-CD36,IF(Y36>0,(Y36+CC36)-CD36)) -> 92416800 | CG36: =IFERROR(IF(((CE36/BI36)*(TODAY()-N36))>CE36,CE36,((CE36/BI36)*(TODAY()-N36))),"") -> 92416800 | CH36: =IF(TODAY()>BJ36,1,+(DAYS360(O36,TODAY())/DAYS360(O36,BJ36))) -> 1 | CI36: =+IF(CL36>0,DAYS360(O36,CL36)/DAYS360(O36,BJ36),CH36) -> 1 | CJ36: =IFERROR(IF(((CG36/CE36)*100)>100,100,((CG36/CE36)*100)),"") -> 100 | CK36: =IFERROR((CF36/CE36)*100,"") -> 0 | CM36: =IF(CL36>1/1/6,"LIQUIDADO",IF(BJ36=0,"",IF(BJ36>=TODAY(),"VIGENTE",IF(BJ36<TODAY(),"TERMINADO",)))) -> TERMINADO | CP36: FEMENINO
A37: 9.32 | B37: 2024-0036 | C37: CTO | D37: CD-036-2024 | E37: 9 PRESTACIÓN DE SERVICIOS | F37: 1 PERSONA NATURAL | G37: 3 CÉDULA DE CIUDADANÍA | H37: 53062356 | I37: NELLY JOHANNA GRANADOS AVENDAÑO | L37: PRESTAR LOS SERVICIOS PROFESIONALES ESPECIALIZADOS PARA LA REPRESENTACIÓN EN PROCESOS DE INSOLVENCIA ECONOMICA DE PERSONA NATURAL NO COMERCIANTE,QUE SE NOTIFIQUEN AL ICETEX Y ORIENTAR Y TRAMITAR LOS PROCESOS QUE EN MATERIA DE CONTRATACIÓN DESARROLLE LA VICEPRESIDENCIA DE CRÉDITO Y COBRANZA, HACIENDO SEGUIMIENTO PRE CONTRACTUAL, CONTRACTUAL Y POSCONTRACTUAL REQUERIDO POR EL AREA. | M37: BOGOTA | N37: 45295 | O37: 45296 | P37: 45656 | Q37: =P37-O37 -> 360 | R37: 1 FUNCIONAMIENTO | S37: CDEF-127-2024 | T37: HONORARIOS – VCC | U37: 108874380 | V37: IG312001020600012 | W37: 108874380 | X37: 8874380 | AA37: SECRETARÍA_GENERAL | AB37: =IFERROR(VLOOKUP(AA37,Listas!$A$1:$C$14,2,FALSE),"") -> FREDY CÉSPEDES VILLA | AC37: =IFERROR(VLOOKUP(AA37,Listas!$A$1:$C$14,3,FALSE),"") -> 93363483 | AD37: VICEPRESIDENCIA_DE_CRÉDITO_Y_COBRANZA | AE37: DIRECTOR(A) DE COBRANZAS | AF37: =IFERROR(VLOOKUP(AE37,Listas!$AD$1:$AF$66,2,FALSE),"") -> MARÍA VICTORIA CAMARGO CORTÉS | AG37: =IFERROR(VLOOKUP(AE37,Listas!$AD$1:$AF$65,3,FALSE),"") -> 52496497 | AH37: 1 CONTRATACION DIRECTA | AI37: Asistir o participar en las audiencias de insolvencia económica de persona natural no comerciante que sean notificadas al ICETEX. 2. Realizar seguimiento a los procesos de insolvencia económica, de acuerdo a las audiencias en las que participa o asiste, hasta su finalización. 3. Solicitar a las áreas correspondientes en el ICETEX, la información de los créditos y estado de los mismos para participar en las audiencias de insolvencia a su cargo. 4. Analizar y realizar seguimiento a los acuerdo de pago correspondientes a los procesos de insolvencia económica de persona natural no comerciante. 5. Proyectar los documentos que sean requeridos para los procesos de insolvencia económica. 6. Proyectar estudios previos y verificar la documentación allegada para solicitud de viabilidad de la contratación, aplicando las normas en materia de contratación que operen para el ICETEX. 7. Realizar el apoyo para la publicación de los documentos en el portal SECOP II, inherentes a la ejecución de los contratos de la Dirección de Cobranza y el despacho de la Vicepresidencia. 8. Hacer seguimiento a las diferentes etapas y cumplimiento de términos y cronogramas de los procesos precontractuales, contractuales y post contractuales que adelanta la Vicepresidencia de Crédito y Cobranza. 9. Brindar apoyo en las actividades inherentes a los procesos de contratación de servicios BPO, adelantados por licitación o a través Colombia Compra Eficiente. 10. Organizar la documentación de contenido contractual y demás soportes que conforman el expediente único para ser entregados al Grupo de Contratación o a la persona encargada del Archivo. 11. Apoyar el trámite correspondiente para el efectivo pago a los Contratistas de la Dirección de Cobranza y el despacho de la Vicepresidencia. 12. Las demás obligaciones que se requieran para el cumplimiento a cabalidad del objeto contractual y que sean inherentes a la naturaleza del contrato. 13. Cumplir con los indicadores de gestión establecidos | AJ37: 1 SI | AK37: 1 PUBLICADO | AL37: 1 PUBLICADO | AM37: 1 SI | AN37: 30753 | AO37: =IF(YEAR(TODAY())-YEAR(AN37)>100," ",YEAR(TODAY())-YEAR(AN37)) -> 41 | AP37: GRUPO_DE_CONTRATACIÓN | AQ37: DIANA GONZALEZ | BF37: =BC37+BE37 -> 0 | BI37: =BF37+Q37 -> 360 | BJ37: =IF(BH37="",P37+BF37,BH37) -> 45656 | CC37: =BR37+BV37+BZ37 -> 0 | CE37: =IF(Y37=0,(W37+CC37)-CD37,IF(Y37>0,(Y37+CC37)-CD37)) -> 108874380 | CG37: =IFERROR(IF(((CE37/BI37)*(TODAY()-N37))>CE37,CE37,((CE37/BI37)*(TODAY()-N37))),"") -> 108874380 | CH37: =IF(TODAY()>BJ37,1,+(DAYS360(O37,TODAY())/DAYS360(O37,BJ37))) -> 1 | CI37: =+IF(CL37>0,DAYS360(O37,CL37)/DAYS360(O37,BJ37),CH37) -> 1 | CJ37: =IFERROR(IF(((CG37/CE37)*100)>100,100,((CG37/CE37)*100)),"") -> 100 | CK37: =IFERROR((CF37/CE37)*100,"") -> 0 | CM37: =IF(CL37>1/1/6,"LIQUIDADO",IF(BJ37=0,"",IF(BJ37>=TODAY(),"VIGENTE",IF(BJ37<TODAY(),"TERMINADO",)))) -> TERMINADO | CO37: 20243030000270-I Id: 4085863 | CP37: FEMENINO
A38: 9.33 | B38: 2024-0037 | C38: CTO | D38: CD-037-2024 | E38: 9 PRESTACIÓN DE SERVICIOS | F38: 1 PERSONA NATURAL | G38: 3 CÉDULA DE CIUDADANÍA | H38: 1110562819 | I38: MARIA CLAUDIA ALEJANDRA SAA | L38: PRESTAR LOS SERVICIOS PROFESIONALES PARA EL APOYO A LAS DIFERENTES ACTIVIDADES REQUERIDAS EN EL DESARROLLO DE LA GESTIÓN JUDICIAL Y EFECTUAR LA REPRESENTACIÓN EN PROCESOS DE INSOLVENCIA ECONÓMICA DE PERSONA NATURAL NO COMERCIANTE, QUE SE NOTIFIQUEN AL ICETEX, ASÍ COMO TAMBIEN APOYAR LOS PROCESOS QUE EN MATERIA CONTRACTUAL DESARROLLE LA DIRECCIÓN DE COBRANZA.. | M38: BOGOTA | N38: 45295 | O38: 45296 | P38: 45656 | Q38: =P38-O38 -> 360 | R38: 1 FUNCIONAMIENTO | S38: CDEF-130-2024 | T38: HONORARIOS – VCC | U38: 69149962 | V38: IG312001020600012 | W38: 69149962 | X38: 5762496 | AA38: SECRETARÍA_GENERAL | AB38: =IFERROR(VLOOKUP(AA38,Listas!$A$1:$C$14,2,FALSE),"") -> FREDY CÉSPEDES VILLA | AC38: =IFERROR(VLOOKUP(AA38,Listas!$A$1:$C$14,3,FALSE),"") -> 93363483 | AD38: VICEPRESIDENCIA_DE_CRÉDITO_Y_COBRANZA | AE38: DIRECTOR(A) DE COBRANZAS | AF38: =IFERROR(VLOOKUP(AE38,Listas!$AD$1:$AF$66,2,FALSE),"") -> MARÍA VICTORIA CAMARGO CORTÉS | AG38: =IFERROR(VLOOKUP(AE38,Listas!$AD$1:$AF$65,3,FALSE),"") -> 52496497 | AH38: 1 CONTRATACION DIRECTA | AI38: 1. Asistir o participar en las audiencias de insolvencia económica de persona natural no comerciante que sean notificadas al ICETEX. 2. Realizar seguimiento a los procesos de insolvencia económica, de acuerdo a las audiencias en las que participa o asiste, hasta su finalización. 3. Solicitar a las áreas correspondientes en el ICETEX, la información de los créditos y estado de los mismos para participar en las audiencias de insolvencia a su cargo. 4. Analizar y realizar seguimiento a los acuerdo de pago correspondientes a los procesos de insolvencia económica de persona natural no comerciante. 5. Proyectar los documentos que sean requeridos para los procesos de insolvencia económica. 6. Apoyar actividades requeridas en el desarrollo de las medidas cautelares de los procesos de cobro jurídico, tales como actualizar el estado de las medidas cautelares en la base de cobro judicial. 7. Presentar la propuesta de acción con ocasión al trámite de las medidas cautelares ante el abogado a cargo conforme las actuaciones registradas en la página de la rama judicial y/o información reportada por abogado a cargo del proceso de cobro jurídico. 8. Enviar los oficios de embargo a las entidades bancarias correspondientes vía correo electrónico, así como a los juzgados en los casos requeridos por el abogado a cargo del proceso de cobro jurídico. 9. Solicitar ante los juzgados, los autos por medio de los cuales se decreta la medida cautelar y los oficios de embargo cuando sean requeridos por el abogado a cargo del proceso de cobro jurídico. 10. Evacuar los correos allegados a cobrojudicialcetex.gov.co. 11. Brindar el apoyo que se requiera en los procesos de contratación de la Vicepresidencia de Crédito y Cobranza, en lo correspondiente al trámite precontractual y contractual en los contratos de prestación de servicios y demás contratos del área. 12. Las demás obligaciones que se requieran para el cumplimiento a cabalidad del objeto contractual y que sean inherentes a la naturaleza del contrato. 13. Cumplir con los indicadores de gestión establecidos | AJ38: 1 SI | AK38: 1 PUBLICADO | AL38: 1 PUBLICADO | AM38: 1 SI | AN38: 34870 | AO38: =IF(YEAR(TODAY())-YEAR(AN38)>100," ",YEAR(TODAY())-YEAR(AN38)) -> 30 | AP38: GRUPO_DE_CONTRATACIÓN | AQ38: DIANA GONZALEZ | BF38: =BC38+BE38 -> 0 | BI38: =BF38+Q38 -> 360 | BJ38: =IF(BH38="",P38+BF38,BH38) -> 45656 | CC38: =BR38+BV38+BZ38 -> 0 | CE38: =IF(Y38=0,(W38+CC38)-CD38,IF(Y38>0,(Y38+CC38)-CD38)) -> 69149962 | CG38: =IFERROR(IF(((CE38/BI38)*(TODAY()-N38))>CE38,CE38,((CE38/BI38)*(TODAY()-N38))),"") -> 69149962 | CH38: =IF(TODAY()>BJ38,1,+(DAYS360(O38,TODAY())/DAYS360(O38,BJ38))) -> 1 | CI38: =+IF(CL38>0,DAYS360(O38,CL38)/DAYS360(O38,BJ38),CH38) -> 1 | CJ38: =IFERROR(IF(((CG38/CE38)*100)>100,100,((CG38/CE38)*100)),"") -> 100 | CK38: =IFERROR((CF38/CE38)*100,"") -> 0 | CM38: =IF(CL38>1/1/6,"LIQUIDADO",IF(BJ38=0,"",IF(BJ38>=TODAY(),"VIGENTE",IF(BJ38<TODAY(),"TERMINADO",)))) -> TERMINADO | CO38: 20243030000269-I Id: 4085862 | CP38: FEMENINO
A39: 10.1 | B39: 2024-0038 | C39: CTO | D39: CD-038-2025 | E39: 9 PRESTACIÓN DE SERVICIOS | F39: 1 PERSONA NATURAL | G39: 3 CÉDULA DE CIUDADANÍA | H39: 52884450 | I39: NINI JOHANNA FRANCO MONTOYA | L39: PRESTAR SUS SERVICIOS PROFESIONALES LIDERANDO LA GESTIÓN JURIDICA DE LOS FONDOS A CARGO DE LA VICEPRESIDENCIA DE FONDOS EN ADMINISTRACIÓN; ASÍ COMO LOS TEMAS RELACIONADOS CON LOS PROCESOS DE CONTRATACIÓN A CARGO DE DICHA DEPENDENCIA. | M39: BOGOTA | N39: 45295 | O39: 45296 | P39: 45657 | Q39: =P39-O39 -> 361 | R39: 1 FUNCIONAMIENTO | S39: CDEF-191-2024 | T39: HONORARIOS VFA | U39: 198621600 | V39: IG312001020700012 | W39: 198621600 | X39: 16551800 | AA39: SECRETARÍA_GENERAL | AB39: =IFERROR(VLOOKUP(AA39,Listas!$A$1:$C$14,2,FALSE),"") -> FREDY CÉSPEDES VILLA | AC39: =IFERROR(VLOOKUP(AA39,Listas!$A$1:$C$14,3,FALSE),"") -> 93363483 | AD39: VICEPRESIDENCIA_DE_FONDOS_EN_ADMINISTRACIÓN | AE39: VICEPRESIDENTE DE FONDOS EN ADMINISTRACIÓN | AF39: =IFERROR(VLOOKUP(AE39,Listas!$AD$1:$AF$66,2,FALSE),"") -> DINORAH PATRICIA ABADIA MURILLO | AG39: =IFERROR(VLOOKUP(AE39,Listas!$AD$1:$AF$65,3,FALSE),"") -> 52220857 | AH39: 1 CONTRATACION DIRECTA | AI39: 1. Asesorar al Vicepresidente de Fondos en Administración y a los colaboradores a su cargo en los temas jurídicos relacionados con los fondos administrados por esta dependencia. 2. Orientar desde el punto de vista jurídico la constitución de nuevos fondos a cargo de la Vicepresidencia de Fondos en Administración y la suscripción de convenios, contratos, reglamentos operativos y demás documentos concernientes. 3. Revisar los reglamentos operativos, otrosí, y demás documentos necesarios para la correcta ejecución de los fondos a cargo de la Vicepresidencia de Fondos en Administración. 4. Actuar como enlace entre la Vicepresidencia de Fondos en Administración y la Oficina de Acuerdos Estratégicos del ICETEX. 5. Revisar los proyectos de respuestas de peticiones internas y externas, actos administrativos, conceptos, desde el punto de vista jurídico, que le sean requeridos y que guarden relación con los procesos a cargo de la Vicepresidencia de Fondos en Administración. 6. Apoyar la construcción y actualización del plan de anual de adquisiciones de acuerdo con las competencias de la Vicepresidencia de Fondos en Administración. 7. Revisar los estudios y documentos previos de los procesos contractuales, que se adelanten en la Vicepresidencia de Fondos en Administración, de acuerdo con la normatividad en materia de contratación aplicables a EL ICETEX. 8. Preparar y consolidar la información a presentar en el Comité de Acuerdos Estratégicos en los casos que aplique. 9. Apoyar la supervisión de los contratos y/o convenios que le sean asignados, relacionados con el objeto contractual. 10. Garantizar la confidencialidad, reserva y privacidad de la información que por razón de sus actividades deba manejar en desarrollo del contrato. 11. Asistir y/o participar en los comités, mesas de trabajo y demás reuniones relacionadas con el objeto contractual. 12. Desplazarse en oficinas institucionales ubicadas en ciudades o municipios distintos a Bogotá D.C, por solicitud del supervisor, previo el otorgamiento de la correspondiente autorización de desplazamiento. 13. Las demás asignadas por el supervisor y que tengan relación con el objeto del presente contrato. | AJ39: 1 SI | AK39: 1 PUBLICADO | AL39: 1 PUBLICADO | AM39: 1 SI | AN39: 29947 | AO39: =IF(YEAR(TODAY())-YEAR(AN39)>100," ",YEAR(TODAY())-YEAR(AN39)) -> 44 | AP39: GRUPO_DE_CONTRATACIÓN | AQ39: PATRICIA JALLER | BF39: =BC39+BE39 -> 0 | BI39: =BF39+Q39 -> 361 | BJ39: =IF(BH39="",P39+BF39,BH39) -> 45657 | CC39: =BR39+BV39+BZ39 -> 0 | CE39: =IF(Y39=0,(W39+CC39)-CD39,IF(Y39>0,(Y39+CC39)-CD39)) -> 198621600 | CG39: =IFERROR(IF(((CE39/BI39)*(TODAY()-N39))>CE39,CE39,((CE39/BI39)*(TODAY()-N39))),"") -> 198621600 | CH39: =IF(TODAY()>BJ39,1,+(DAYS360(O39,TODAY())/DAYS360(O39,BJ39))) -> 1 | CI39: =+IF(CL39>0,DAYS360(O39,CL39)/DAYS360(O39,BJ39),CH39) -> 1 | CJ39: =IFERROR(IF(((CG39/CE39)*100)>100,100,((CG39/CE39)*100)),"") -> 100 | CK39: =IFERROR((CF39/CE39)*100,"") -> 0 | CM39: =IF(CL39>1/1/6,"LIQUIDADO",IF(BJ39=0,"",IF(BJ39>=TODAY(),"VIGENTE",IF(BJ39<TODAY(),"TERMINADO",)))) -> TERMINADO | CO39: 20243030000271-I Id: 4085864 | CP39: FEMENINO
A40: 4.26 | B40: 2024-0039 | C40: CTO | D40: CD-039-2024 | E40: 9 PRESTACIÓN DE SERVICIOS | F40: 1 PERSONA NATURAL | G40: 3 CÉDULA DE CIUDADANÍA | H40: 1015428427 | I40: ELIANA STEPHANIA GALINDO PENAGOS | L40: "PRESTAR LOS SERVICIOS PROFESIONALES PARA LA DOCUMENTACIÓN DE PROCESOS, TAREAS, OPERACIONES Y ACTIVIDADES RELACIONADOS CON LAS AUDITORÍAS, POLÍTICAS PÚBLICAS, GESTIÓN DEL RIESGO, GESTIÓN DEL CRÉDITO Y DEMÁS PLANES DE GESTIÓN Y AUTOCONTROL, DE CONFORMIDAD CON LOS REQUERIMIENTOS ORGANIZACIONALES Y NORMATIVOS DEL ICETEX." | M40: BOGOTA | N40: 45296 | O40: 45296 | P40: 45656 | Q40: =P40-O40 -> 360 | R40: 1 FUNCIONAMIENTO | S40: CDEF-054-2024 | T40: HONORARIOS – OCM | U40: 68765786 | V40: IG312001020240012 | W40: 68765786 | X40: 5762496 | AA40: SECRETARÍA_GENERAL | AB40: =IFERROR(VLOOKUP(AA40,Listas!$A$1:$C$14,2,FALSE),"") -> FREDY CÉSPEDES VILLA | AC40: =IFERROR(VLOOKUP(AA40,Listas!$A$1:$C$14,3,FALSE),"") -> 93363483 | AD40: OFICINA_COMERCIAL_Y_DE_MERCADEO | AE40: JEFE OFICINA COMERCIAL Y DE MERCADEO | AF40: =IFERROR(VLOOKUP(AE40,Listas!$AD$1:$AF$66,2,FALSE),"") -> RODOLFO GIOVANNI CANCHILA SUÁREZ | AG40: =IFERROR(VLOOKUP(AE40,Listas!$AD$1:$AF$65,3,FALSE),"") -> 79672493 | AH40: 1 CONTRATACION DIRECTA | AI40: 1. Cumplir con el plan de trabajo entregado por la supervisión en el cual se relacionen los objetivos y metas a desarrollar durante la vigencia del contrato. 2. Gestionar de manera oportuna los requerimientos gerenciales asociados a la planeación estratégica, comités, juntas y demás políticas y demás requerimientos organizacionales y normativos del ICETEX 3. Articular con las dependencias del ICETEX, que, de acuerdo con sus funciones, tengan injerencia sobre los procesos desarrollados de manera integral a través de la ingeniería en los procesos y proyectos (rapidez, solución de problemas, control de ejecución presupuestal operativo, prevención del riesgo, disminución de PQRS, optimización de KPI´S operativos y las demás aplicables) a través de la planificación, diseño y toma de decisiones para la mejora continua y la correcta atención de los grupos de interés del ICETEX. 4. Atender de manera oportuna la gestión de planes y proyectos públicos normativos emitidos por los diferentes entes de control para la correcta atención y gestión de los grupos de interés del ICETEX. 5. Apoyar la gestión de auditorías en el marco de los procesos y procedimientos de la Oficina comercial y de Mercadeo o en las que ella participe. 6. Apoyar la gestión del riesgo en el marco de los procesos y procedimientos de la Oficina comercial y de Mercadeo o en las que ella participe. 7. Aplicar de forma completa, correcta y oportuna la gestión documental para el manejo, organización y evidencia de la documentación producida y recibida desde su origen hasta su destino final con el objeto de facilitar su utilización y conservación como actas, memorias, documentos asociados a la gestión contractual de la oficina comercial y de mercadeo, y las demás asociadas con los lineamientos de la Entidad. 8. Participar activamente en construcción, metodología y gestión de acciones asociadas al Sistema de Atención al Consumidor Financiero en el marco de los procesos y procedimientos de la Oficina comercial y de Mercadeo o en las que ella participe. 9. Desplazarse a las diferentes ciudades del país, en caso de ser necesario para la debida ejecución del contrato, previa coordinación con el supervisor. 10. Las demás que sean inherentes para el logro del objeto contratado, asignadas por el supervisor del contrato. | AJ40: 1 SI | AK40: 1 PUBLICADO | AL40: 1 PUBLICADO | AM40: 1 SI | AN40: 33544 | AO40: =IF(YEAR(TODAY())-YEAR(AN40)>100," ",YEAR(TODAY())-YEAR(AN40)) -> 34 | AP40: GRUPO_DE_CONTRATACIÓN | AQ40: BRESMAN SANCHEZ | BF40: =BC40+BE40 -> 0 | BI40: =BF40+Q40 -> 360 | BJ40: =IF(BH40="",P40+BF40,BH40) -> 45656 | CC40: =BR40+BV40+BZ40 -> 0 | CE40: =IF(Y40=0,(W40+CC40)-CD40,IF(Y40>0,(Y40+CC40)-CD40)) -> 68765786 | CG40: =IFERROR(IF(((CE40/BI40)*(TODAY()-N40))>CE40,CE40,((CE40/BI40)*(TODAY()-N40))),"") -> 68765786 | CH40: =IF(TODAY()>BJ40,1,+(DAYS360(O40,TODAY())/DAYS360(O40,BJ40))) -> 1 | CI40: =+IF(CL40>0,DAYS360(O40,CL40)/DAYS360(O40,BJ40),CH40) -> 1 | CJ40: =IFERROR(IF(((CG40/CE40)*100)>100,100,((CG40/CE40)*100)),"") -> 100 | CK40: =IFERROR((CF40/CE40)*100,"") -> 0 | CM40: =IF(CL40>1/1/6,"LIQUIDADO",IF(BJ40=0,"",IF(BJ40>=TODAY(),"VIGENTE",IF(BJ40<TODAY(),"TERMINADO",)))) -> TERMINADO | CO40: 20243030000272-I Id: 4085865 | CP40: FEMENINO
A41: 4.18 | B41: 2024-0040 | C41: CTO | D41: CD-040-2024 | E41: 9 PRESTACIÓN DE SERVICIOS | F41: 1 PERSONA NATURAL | G41: 3 CÉDULA DE CIUDADANÍA | H41: 53044709 | I41: LUZ YANIRA SALAMANCA MARTINEZ | L41: PRESTAR LOS SERVICIOS PROFESIONALES ESPECIALIZADOS PARA CONTROL Y CUMPLIMIENTO DE LOS PROGRAMAS, PROCESOS, TAREAS, OPERACIONES Y ACTIVIDADES RELACIONADOS CON LOS PROCESOS, AUDITORÍAS, POLÍTICAS PÚBLICAS, GESTIÓN DEL RIESGO, GESTIÓN DEL CRÉDITO Y DEMÁS PLANES DE GESTIÓN Y AUTOCONTROL, DE CONFORMIDAD CON LOS REQUERIMIENTOS ORGANIZACIONALES Y NORMATIVOS DEL ICETEX”, | M41: BOGOTA | N41: 45296 | O41: 45296 | P41: 45656 | Q41: =P41-O41 -> 360 | R41: 1 FUNCIONAMIENTO | S41: CDEF-051-2024 | T41: HONORARIOS – OCM | U41: 96564712 | V41: IG312001020240012 | W41: 96564712 | X41: 8092015 | AA41: SECRETARÍA_GENERAL | AB41: =IFERROR(VLOOKUP(AA41,Listas!$A$1:$C$14,2,FALSE),"") -> FREDY CÉSPEDES VILLA | AC41: =IFERROR(VLOOKUP(AA41,Listas!$A$1:$C$14,3,FALSE),"") -> 93363483 | AD41: OFICINA_COMERCIAL_Y_DE_MERCADEO | AE41: JEFE OFICINA COMERCIAL Y DE MERCADEO | AF41: =IFERROR(VLOOKUP(AE41,Listas!$AD$1:$AF$66,2,FALSE),"") -> RODOLFO GIOVANNI CANCHILA SUÁREZ | AG41: =IFERROR(VLOOKUP(AE41,Listas!$AD$1:$AF$65,3,FALSE),"") -> 79672493 | AH41: 1 CONTRATACION DIRECTA | AI41: 1. Cumplir con el plan de trabajo entregado por la supervisión en el cual se relacionen los objetivos y metas a desarrollar durante la vigencia del contrato. 2. Gestionar la correcta y oportuna gestión de requerimientos gerenciales asociados a la planeación estratégica, comités, juntas y demás políticas y demás requerimientos organizacionales y normativos del ICETEX 3. Planificar, guiar y controlar de forma eficiente y oportuna la gestión de auditorías en el marco de los procesos y procedimientos de la Oficina comercial y de Mercadeo o en el que esta intervenga, teniendo en cuenta de forma integral el esquema establecido en la ingeniería en los procesos y proyectos (rapidez, solución de problemas, control de ejecución presupuestal operativo, prevención del riesgo, disminución de PQRS, optimización de KPI´S operativos y las demás aplicables) para mejora continua y la correcta atención de los grupos de interés del ICETEX. 4. Establecer un esquema de alertas multinivel (gerenciales, administrativas u operativas) que permita adelantar de manera oportuna planes de trabajo para la mejora en la atención de los grupos de interés del ICETEX garantizando el seguimiento y control a las mismas. 5. Apoyar la generación de alertas que así correspondan para la correcta documentación y gestión de los riesgos asociados a la Oficina Comercial y de Mercadeo o los procesos en la que esta dependencia participe. 6. Apoyar las iniciativas de mejora que apunten a la optimización y desarrollo de las actividades operativas y/o administrativas desarrolladas asociadas al Sistema de Atención al Consumidor Financiero en el marco de los procesos y procedimientos de la Oficina comercial y de Mercadeo o en las que ella participe. 7. Cumplir con los lineamientos de la gestión documental para el manejo, organización y evidencia de la documentación producida y recibida desde su origen hasta su destino final con el objeto de facilitar su utilización y conservación como actas, memorias, documentos asociados a la gestión contractual y las demás asociadas. 8. Desplazarse a las diferentes ciudades del país, en caso de ser necesario para la debida ejecución del contrato, previa coordinación con el supervisor. 9. Las demás que sean inherentes para el logro del objeto contratado, asignadas por el supervisor del contrato. | AJ41: 1 SI | AK41: 1 PUBLICADO | AL41: 1 PUBLICADO | AM41: 1 SI | AN41: 30791 | AO41: =IF(YEAR(TODAY())-YEAR(AN41)>100," ",YEAR(TODAY())-YEAR(AN41)) -> 41 | AP41: GRUPO_DE_CONTRATACIÓN | AQ41: BRESMAN SANCHEZ | BF41: =BC41+BE41 -> 0 | BI41: =BF41+Q41 -> 360 | BJ41: =IF(BH41="",P41+BF41,BH41) -> 45656 | CC41: =BR41+BV41+BZ41 -> 0 | CE41: =IF(Y41=0,(W41+CC41)-CD41,IF(Y41>0,(Y41+CC41)-CD41)) -> 96564712 | CG41: =IFERROR(IF(((CE41/BI41)*(TODAY()-N41))>CE41,CE41,((CE41/BI41)*(TODAY()-N41))),"") -> 96564712 | CH41: =IF(TODAY()>BJ41,1,+(DAYS360(O41,TODAY())/DAYS360(O41,BJ41))) -> 1 | CI41: =+IF(CL41>0,DAYS360(O41,CL41)/DAYS360(O41,BJ41),CH41) -> 1 | CJ41: =IFERROR(IF(((CG41/CE41)*100)>100,100,((CG41/CE41)*100)),"") -> 100 | CK41: =IFERROR((CF41/CE41)*100,"") -> 0 | CM41: =IF(CL41>1/1/6,"LIQUIDADO",IF(BJ41=0,"",IF(BJ41>=TODAY(),"VIGENTE",IF(BJ41<TODAY(),"TERMINADO",)))) -> TERMINADO | CO41: 20243030000275-I Id: 4085868 | CP41: FEMENINO
A42: 4.1 | B42: 2024-0041 | C42: CTO | D42: CD-041-2024 | E42: 9 PRESTACIÓN DE SERVICIOS | F42: 1 PERSONA NATURAL | G42: 3 CÉDULA DE CIUDADANÍA | H42: 79623265 | I42: EDGAR MAURICIO CUERVO | L42: PRESTAR SERVICIOS PROFESIONALES ESPECIALIZADOS PARA GARANTIZAR LA MEJORA CONTINUA, DESARROLLOS, AUTOMATIZACIONES Y EFICIENCIAS EN EL MARCO DE LOS PROCESOS DE LA OFICINA COMERCIAL Y DE MERCADEO Y SUS DIFERENTES EQUIPOS DE TRABAJO. | M42: BOGOTA | N42: 45296 | O42: 45296 | P42: 45656 | Q42: =P42-O42 -> 360 | R42: 1 FUNCIONAMIENTO | S42: CDEF-084-2024 | T42: HONORARIOS – OCM | U42: 162406390 | V42: IG312001020240012 | W42: 162406390 | X42: 13609474 | AA42: SECRETARÍA_GENERAL | AB42: =IFERROR(VLOOKUP(AA42,Listas!$A$1:$C$14,2,FALSE),"") -> FREDY CÉSPEDES VILLA | AC42: =IFERROR(VLOOKUP(AA42,Listas!$A$1:$C$14,3,FALSE),"") -> 93363483 | AD42: OFICINA_COMERCIAL_Y_DE_MERCADEO | AE42: JEFE OFICINA COMERCIAL Y DE MERCADEO | AF42: =IFERROR(VLOOKUP(AE42,Listas!$AD$1:$AF$66,2,FALSE),"") -> RODOLFO GIOVANNI CANCHILA SUÁREZ | AG42: =IFERROR(VLOOKUP(AE42,Listas!$AD$1:$AF$65,3,FALSE),"") -> 79672493 | AH42: 1 CONTRATACION DIRECTA | AI42: 1. Elaborar y suscribir conjuntamente con el supervisor del contrato el cronograma de trabajo. 2. Responder ante el supervisor del contrato, por la planeación que permita cumplir con la ejecución del objeto del contrato con oportunidad, cubrimiento, eficacia, y calidad del servicio. 3. Plantear el organigrama de los integrantes de los proyectos mediante la definición de responsabilidades de cada miembro del equipo. 4. Orientar y dirigir el recurso humano para garantizar la mejora continua, desarrollos, automatizaciones y eficiencias en el servicio. 5. Velar por el estricto cumplimiento de los cronogramas de trabajo de los contratistas que hagan parte de los proyectos asociados al curso normal del servicio de la entidad, así como a los programas estratégicos de la entidad y del equipo i3. 6. Realizar seguimiento y control al consumo de recursos, presupuesto, tiempo y cumplimiento de las actividades propuestas dentro de los cronogramas de los proyectos. 7. Integrar los esfuerzos de las distintas áreas del ICETEX y posibles terceros que participen en los proyectos o programas estratégicos. 8. Emitir conceptos técnicos en aquellos asuntos que le sean solicitados por la supervisión del contrato, y que estén relacionados con el objeto contractual. 9. Desplazarse a las diferentes ciudades del país, en caso de ser necesario para la debida ejecución del contrato, previa coordinación con el supervisor. 10. Las demás que sean inherentes para el logro del objeto contratado, asignadas por el supervisor del contrato. | AJ42: 1 SI | AK42: 1 PUBLICADO | AL42: 1 PUBLICADO | AM42: 1 SI | AN42: 27005 | AO42: =IF(YEAR(TODAY())-YEAR(AN42)>100," ",YEAR(TODAY())-YEAR(AN42)) -> 52 | AP42: GRUPO_DE_CONTRATACIÓN | AQ42: BRESMAN SANCHEZ | BF42: =BC42+BE42 -> 0 | BI42: =BF42+Q42 -> 360 | BJ42: =IF(BH42="",P42+BF42,BH42) -> 45656 | CC42: =BR42+BV42+BZ42 -> 0 | CE42: =IF(Y42=0,(W42+CC42)-CD42,IF(Y42>0,(Y42+CC42)-CD42)) -> 162406390 | CG42: =IFERROR(IF(((CE42/BI42)*(TODAY()-N42))>CE42,CE42,((CE42/BI42)*(TODAY()-N42))),"") -> 162406390 | CH42: =IF(TODAY()>BJ42,1,+(DAYS360(O42,TODAY())/DAYS360(O42,BJ42))) -> 1 | CI42: =+IF(CL42>0,DAYS360(O42,CL42)/DAYS360(O42,BJ42),CH42) -> 1 | CJ42: =IFERROR(IF(((CG42/CE42)*100)>100,100,((CG42/CE42)*100)),"") -> 100 | CK42: =IFERROR((CF42/CE42)*100,"") -> 0 | CM42: =IF(CL42>1/1/6,"LIQUIDADO",IF(BJ42=0,"",IF(BJ42>=TODAY(),"VIGENTE",IF(BJ42<TODAY(),"TERMINADO",)))) -> TERMINADO | CO42: 20243030000281-I Id: 4085874 | CP42: MASCULINO
A43: 4.3 | B43: 2024-0042 | C43: CTO | D43: CD-042-2024 | E43: 9 PRESTACIÓN DE SERVICIOS | F43: 1 PERSONA NATURAL | G43: 3 CÉDULA DE CIUDADANÍA | H43: 80513301 | I43: JULIO CESAR CASTAÑO ARIZA | L43: PRESTAR SERVICIOS PROFESIONALES ESPECIALIZADOS PARA LIDERAR EL DESARROLLO, ADMINISTRACIÓN Y GENERACIÓN DE DATA, EN EL MARCO DEL DESARROLLO DE LA GESTIÓN DEL GOBIERNO DE DATOS DE LA OFICINA COMERCIAL Y DE MERCADEO, ASÍ COMO LA ADMINISTRACIÓN FUNCIONAL DEL CRM DE LA ENTIDAD | M43: BOGOTA | N43: 45296 | O43: 45296 | P43: 45656 | Q43: =P43-O43 -> 360 | R43: 1 FUNCIONAMIENTO | S43: CDEF-084-2024 | T43: HONORARIOS – OCM | U43: 107967094 | V43: IG312001020240012 | W43: 107967094 | X43: 9072865 | AA43: SECRETARÍA_GENERAL | AB43: =IFERROR(VLOOKUP(AA43,Listas!$A$1:$C$14,2,FALSE),"") -> FREDY CÉSPEDES VILLA | AC43: =IFERROR(VLOOKUP(AA43,Listas!$A$1:$C$14,3,FALSE),"") -> 93363483 | AD43: OFICINA_COMERCIAL_Y_DE_MERCADEO | AE43: JEFE OFICINA COMERCIAL Y DE MERCADEO | AF43: =IFERROR(VLOOKUP(AE43,Listas!$AD$1:$AF$66,2,FALSE),"") -> RODOLFO GIOVANNI CANCHILA SUÁREZ | AG43: =IFERROR(VLOOKUP(AE43,Listas!$AD$1:$AF$65,3,FALSE),"") -> 79672493 | AH43: 1 CONTRATACION DIRECTA | AI43: 1. Elaborar y entregar plan de trabajo y aprobación por parte del supervisor del contrato, de conformidad con las estipulaciones contractuales. 2. Definir junto con los equipos de la Oficina comercial y de mercadeo los informes y necesidades de datos de acuerdo a las obligaciones y actividades a desarrollar por parte de la Oficina 3. Establecidos los datos requeridos, definir los criterios de fuentes, extracción, visualización, periodicidad y características requeridas para contar con los datos requeridos en el marco de las funciones de la Oficina Comercial y de mercadeo. 4. Liderar la construcción de informes y generación de información requerida de acuerdo a las necesidades de la Oficina comercial y de mercadeo 5. Establecer los parámetros de intercambio de información entre la oficina Comercial y de Mercadeo del Icetex y entidades externas, parámetros y condiciones a establecer a través de mecanismos de ruta segura 6. Liderar el proceso de administración de usuarios de acceso a los sistemas de información del Icetex, para los agentes del proveedor de atencion al usuario 7. Gestionar todas las novedades de los casos registrados en el aplicativo CRM de la Entidad, que se presentan en desarrollo de la operación de atención al usuario y de la gestión comercial y de mercadeo. 8. Mantener, actualizar y depurar los usuarios habilitados del aplicativo CRM-, en concordancia con los procedimientos de seguridad informatica establecidos por la entidad. 9. Administrar funcionalmente el aplicativo CRM de la Entidad 10. Apoyar el acompañamiento, gestión y documentación de procesos y procedimientos, indicadores, planes de acción, planes de mejoramiento, reportes, auditorias de calidad, auditorías externas e internas, eventos de riesgos y demás, resultantes del ejercicio de control y autocontrol de los macroprocesos de la Oficina de Comercial y de Mercadeo. 11. Desplazarse a las diferentes ciudades del país, en caso de ser necesario para la debida ejecución del contrato, previa coordinación con el supervisor. Para tal fin, el ICETEX apropiará y reconocerá con cargo al presupuesto de la presente vigencia fiscal los recursos para cubrir dichos gastos. 12. Presentar, en caso de que aplique, para revisión y aprobación de la supervisión del contrato, propuestas de mejora continua, automatización e innovación de los procesos asociados a la atención de los grupos de interés. 13. Brindar acompañamiento en relación con las actividades que le sean asignadas, en el marco de las funciones de la Oficina de Comercial y de Mercadeo. 14. Brindar apoyo y asesoría técnica en los comités o reuniones a las que sea convocado y que la Entidad requiera acompañamiento. 15. Participar, desde el alcance del objeto y sus obligaciones contractuales, todo el proceso de planeación, implementación y puesta en marcha, de proyectos donde participen una o más dependencias de la Entidad, de acuerdo a lo requerido por el supervisro del contrato. 16. Las demás que sean inherentes para el logro del objeto contratado, asignadas por el supervisor del contrato. | AJ43: 1 SI | AK43: 1 PUBLICADO | AL43: 1 PUBLICADO | AM43: 1 SI | AN43: 27059 | AO43: =IF(YEAR(TODAY())-YEAR(AN43)>100," ",YEAR(TODAY())-YEAR(AN43)) -> 51 | AP43: GRUPO_DE_CONTRATACIÓN | AQ43: BRESMAN SANCHEZ | BF43: =BC43+BE43 -> 0 | BI43: =BF43+Q43 -> 360 | BJ43: =IF(BH43="",P43+BF43,BH43) -> 45656 | CC43: =BR43+BV43+BZ43 -> 0 | CE43: =IF(Y43=0,(W43+CC43)-CD43,IF(Y43>0,(Y43+CC43)-CD43)) -> 107967094 | CG43: =IFERROR(IF(((CE43/BI43)*(TODAY()-N43))>CE43,CE43,((CE43/BI43)*(TODAY()-N43))),"") -> 107967094 | CH43: =IF(TODAY()>BJ43,1,+(DAYS360(O43,TODAY())/DAYS360(O43,BJ43))) -> 1 | CI43: =+IF(CL43>0,DAYS360(O43,CL43)/DAYS360(O43,BJ43),CH43) -> 1 | CJ43: =IFERROR(IF(((CG43/CE43)*100)>100,100,((CG43/CE43)*100)),"") -> 100 | CK43: =IFERROR((CF43/CE43)*100,"") -> 0 | CM43: =IF(CL43>1/1/6,"LIQUIDADO",IF(BJ43=0,"",IF(BJ43>=TODAY(),"VIGENTE",IF(BJ43<TODAY(),"TERMINADO",)))) -> TERMINADO | CO43: 20243030000284-I Id: 4085886 | CP43: MASCULINO
A44: 4.133 | B44: 2024-0043 | C44: CTO | D44: CD-043-2024 | E44: 9 PRESTACIÓN DE SERVICIOS | F44: 1 PERSONA NATURAL | G44: 3 CÉDULA DE CIUDADANÍA | H44: 21469959 | I44: MARITZA VELEZ COORONADO | L44: APOYAR LA GESTIÓN ADMINISTRATIVA, COMERCIAL Y OPERATIVA DE LA TERRITORIAL NOROCCIDENTE EN ARTICULACIÓN CON LA OFICINA COMERCIAL Y DE MERCADEO Y LAS DEMÁS DEPENDENCIAS DEL NIVEL CENTRAL | M44: MEDELLIN | N44: 45296 | O44: 45296 | P44: 45656 | Q44: =P44-O44 -> 360 | R44: 1 FUNCIONAMIENTO | S44: CDEF-165-2024 | T44: OTROS SERVICIOS OPERATIVOS - OCM | U44: 52377402 | V44: IG312001020240014 | W44: 52377402 | X44: 4413826 | AA44: SECRETARÍA_GENERAL | AB44: =IFERROR(VLOOKUP(AA44,Listas!$A$1:$C$14,2,FALSE),"") -> FREDY CÉSPEDES VILLA | AC44: =IFERROR(VLOOKUP(AA44,Listas!$A$1:$C$14,3,FALSE),"") -> 93363483 | AD44: TERRITORIAL_NOROCCIDENTE | AE44: ASESOR TERRITORIAL ZONA NOROCCIDENTE | AF44: =IFERROR(VLOOKUP(AE44,Listas!$AD$1:$AF$66,2,FALSE),"") -> DANIEL ALBERTO CASTAÑO LOPEZ | AG44: =IFERROR(VLOOKUP(AE44,Listas!$AD$1:$AF$65,3,FALSE),"") -> 7544385 | AH44: 1 CONTRATACION DIRECTA | AI44: OBLIGACIONES ESPECÍFICAS DEL CONTRATISTA 1. Apoyar y gestionar las actividades administrativas a cargo de la territorial que propenden con garantizar la debida operación y servicio de las oficinas en su proceso de atención personalizada a los usuarios de la entidad, entre las que se cuenta: a. Realizar seguimiento a las actividades desarrolladas por parte del personal de servicios generales y vigilancia, asignados a las oficinas de la territorial. b. Interactuar con el personal del operador de servicio al cliente en las diferentes oficinas con el fin de atender y gestionar oportunamente las diferentes novedades de servicio en el proceso de atención presencial presentadas con los usuarios de la entidad, así como las mejoras locativas requeridas para la debida operación de las oficinas. c. Gestionar los arreglos locativos requeridos para la óptima operación de las oficinas de la territorial. d. Gestionar con las diferentes áreas a nivel central, la oportuna y eficiente ejecución de los procesos relativos a la gestión del Talento Humano, Seguridad en el trabajo, Riesgos, operación de la plataforma tecnológica, entre otros. e. Apoyar el proceso de pago de servicios públicos, arrendamientos, administraciones y demás rubros correspondientes a la caja menor a cargo de la territorial. f. Apoyar la ejecución del proceso de control, manejo y actualización de inventarios de las oficinas a cargo de la territorial. g. Gestionar la solución oportuna ante las diferentes entidades proveedoras de servicios de las oficinas (servicios públicos, operadores tecnológicos, entre otros) ante las fallas y /o situaciones que afecten la debida operación de la oficina y la continuidad en la atención a los usuarios. h. Atender las visitas de auditorías de control interno y presentación de informes requeridos a la territorial por las diferentes áreas de la entidad. i. Apoyar en la preparación y presentar de los informes requeridos por las diferentes áreas de la entidad a nivel central. 2. Apoyar y ejecutar desde el punto de vista técnico los procedimientos precontractuales, contractuales y poscontractuales requeridos para adelantar las contrataciones de bienes y servicios o aliados estratégicos que se desarrollen en la territorial, y que sean asignados por la supervisión del contrato. 3. Apoyar, cuando sea requerido, la ejecución de las actividades comerciales, de servicio al cliente y/o propias del embudo de conversión comercial a cargo de la territorial en forma personalizada, o por contacto telefónico y/o virtual, entre otros. 4. Consolidar, actualizar y registrar la información, envío de documentación soporte y presentación de informes de las gestiones administrativas y de la actividad comercial, requeridas por las diferentes dependencias del nivel central. 5. Apoyar el acompañamiento, gestión y documentación de proceso (s) y procedimiento (s), cumplimiento de los indicadores, planes de acción, planes de mejoramiento, reportes, auditorias de calidad, auditorías externas e internas, eventos de riesgos y demás resultantes del ejercicio de control y autocontrol de los procesos de calidad a cargo de la territorial. 6. Ejecutar los procedimientos operativos de las tareas asignadas a su cargo y adecuada gestión de los diferentes aplicativos de la entidad, tales como: a) correo electrónico, b) gestión documental, c) aplicativo cosmos, d) archivo único, e) SISGESTION, f) demás aplicativos de gestión definidos por la entidad y asignados por su supervisor. 7. Asesorar y acompañar a los contratistas y/o al personal de operadores logísticos de la territorial respecto a los diferentes procesos administrativos a su cargo y que son requeridos por las diferentes dependencias a nivel central. 8. Realizar el proceso de gestión documental y envío al archivo único de la entidad de las actividades delegadas a su cargo. 9. Colaborar con la ejecución de los distintos procedimientos administrativos a cargo de la territorial que hacen parte del Sistema de Gestión de calidad de la entidad. 10. Desplazarse a las diferentes ciudades del país, en caso de ser necesario para la debida ejecución del contrato, previa coordinación con el supervisor. 11. Las demás que sean inherentes para el logro del objeto contratado, asignadas por el supervisor del contrato. 12. Cumplir con los indicadores de gestión establecidos. | AJ44: 1 SI | AK44: 1 PUBLICADO | AL44: 1 PUBLICADO | AM44: 1 SI | AN44: 28361 | AO44: =IF(YEAR(TODAY())-YEAR(AN44)>100," ",YEAR(TODAY())-YEAR(AN44)) -> 48 | AP44: GRUPO_DE_CONTRATACIÓN | AQ44: DIANA GONZALEZ | BF44: =BC44+BE44 -> 0 | BI44: =BF44+Q44 -> 360 | BJ44: =IF(BH44="",P44+BF44,BH44) -> 45656 | CC44: =BR44+BV44+BZ44 -> 0 | CE44: =IF(Y44=0,(W44+CC44)-CD44,IF(Y44>0,(Y44+CC44)-CD44)) -> 52377402 | CG44: =IFERROR(IF(((CE44/BI44)*(TODAY()-N44))>CE44,CE44,((CE44/BI44)*(TODAY()-N44))),"") -> 52377402 | CH44: =IF(TODAY()>BJ44,1,+(DAYS360(O44,TODAY())/DAYS360(O44,BJ44))) -> 1 | CI44: =+IF(CL44>0,DAYS360(O44,CL44)/DAYS360(O44,BJ44),CH44) -> 1 | CJ44: =IFERROR(IF(((CG44/CE44)*100)>100,100,((CG44/CE44)*100)),"") -> 100 | CK44: =IFERROR((CF44/CE44)*100,"") -> 0 | CM44: =IF(CL44>1/1/6,"LIQUIDADO",IF(BJ44=0,"",IF(BJ44>=TODAY(),"VIGENTE",IF(BJ44<TODAY(),"TERMINADO",)))) -> TERMINADO | CO44: 20243030000286-I Id: 4085894 | CP44: FEMENINO
A45: 13.62 | B45: 2024-0044 | C45: CTO | D45: CD-044-2024 | E45: 9 PRESTACIÓN DE SERVICIOS | F45: 1 PERSONA NATURAL | G45: 3 CÉDULA DE CIUDADANÍA | H45: 79553643 | I45: CESAR ENRIQUE AUCIQUE PEDROZA | L45: PRESTAR SERVICIOS PROFESIONALES AL GRUPO DE DESARROLLO Y TRANSFORMACIÓN ORGANIZACIONAL DE LA SECRETARÍA GENERAL PARA LA IMPLEMENTACIÓN DEL PLAN INSTITUCIONAL DE CAPACITACIÓN DEL ICETEX, ASÍ COMO LA EJECUCIÓN DE LAS ESTRATEGIAS, PLANES, PROGRAMAS Y PROYECTOS EN QUE PARTICIPE EL ÁREA EN EL MARCO DEL PROCESO DE TRANSFORMACIÓN DE LA CULTURA ORGANIZACIONAL QUE ADELANTA LA ENTIDAD | M45: BOGOTA | N45: 45296 | O45: 45300 | P45: 45656 | Q45: =P45-O45 -> 356 | R45: 1 FUNCIONAMIENTO | S45: CDEF-180-2024 | T45: SERVICIOS PARA CAPACITACION | U45: 97800000 | V45: IG1002004020005 | W45: 97800000 | X45: 8150000 | AA45: SECRETARÍA_GENERAL | AB45: =IFERROR(VLOOKUP(AA45,Listas!$A$1:$C$14,2,FALSE),"") -> FREDY CÉSPEDES VILLA | AC45: =IFERROR(VLOOKUP(AA45,Listas!$A$1:$C$14,3,FALSE),"") -> 93363483 | AD45: SECRETARÍA_GENERAL | AE45: COORDINADOR(A) GRUPO DE DESARROLLO Y TRANSFORMACIÓN ORGANIZACIONAL | AF45: =IFERROR(VLOOKUP(AE45,Listas!$AD$1:$AF$66,2,FALSE),"") -> JAIME ANDRES GIL ACOSTA | AG45: =IFERROR(VLOOKUP(AE45,Listas!$AD$1:$AF$65,3,FALSE),"") -> 98622827 | AH45: 1 CONTRATACION DIRECTA | AI45: OBLIGACIONES ESPECÍFICAS DEL CONTRATISTA 1. Realizar el apoyo técnico para la elaboración del diagnóstico de las necesidades de capacitación y formación de los servidores públicos del ICETEX, así como en la construcción del Plan Institucional de Capacitación de la entidad, conforme a la normatividad vigente. 2. Llevar a cabo el acompañamiento técnico en los procesos de contratación, supervisión y seguimiento de las actividades previstas en el Plan Institucional de Capacitación definido por la entidad. 3. Realizar las acciones necesarias para la planeación y seguimiento de la ejecución presupuestal orientada al desarrollo de las actividades contenidas en el Plan Institucional de Capacitación agotando para ello los procesos administrativos pertinentes. 4. Realizar el seguimiento y actualización de los indicadores de los procesos a los que contribuyen las acciones de formación y capacitación a cargo del Grupo de Desarrollo y Transformación Organizacional de la Secretaría General. 5. Participar en las actividades de planificación y desarrollo de los planes, programas y proyectos a cargo de la Secretaría General, relacionados con los procesos de transformación y desarrollo de la cultura organizacional de la entidad, teniendo en cuenta los lineamientos estratégicos establecidos por la entidad para tal fin. 6. Realizar seguimiento a la ejecución presupuestal de la vigencia, en lo concerniente a las diferentes actividades realizadas por el Grupo de Desarrollo y Transformación Organizacional, agotando para ello los procesos administrativos pertinentes. 7. Asistir a las reuniones o actividades que se realicen con los funcionarios, contratistas y demás miembros del Grupo de Desarrollo y Transformación Organizacional de la Secretaría General, relacionados con los procesos de transformación y desarrollo de la cultura organizacional del ICETEX a los que sea convocado o delegado por el-la supervisor-a o el-la secretario-a General de la entidad. 8. Proyectar los actos administrativos relacionados con el quehacer de su objeto contractual, observando los más altos criterios de calidad y asertividad. 9. Elaborar y entregar oportunamente los conceptos, estudios, análisis, recomendaciones e informes que sean solicitados por el-la supervisor-a, la Secretaría General o por los distintos grupos de interés de la institución, garantizando la calidad y confiabilidad de los mismos. 10. Apoyar en la realización de las actividades de formación, sensibilización, socialización y/o difusión de asuntos relacionados con el Código de Integridad y el Plan Anual Anticorrupción. 11. Las demás asignadas por el Supervisor, relacionadas con el objeto y la naturaleza del contrato. | AJ45: 1 SI | AK45: 1 PUBLICADO | AL45: 1 PUBLICADO | AM45: 1 SI | AN45: 25968 | AO45: =IF(YEAR(TODAY())-YEAR(AN45)>100," ",YEAR(TODAY())-YEAR(AN45)) -> 54 | AP45: GRUPO_DE_CONTRATACIÓN | AQ45: DAHIANA ANGARITA | BF45: =BC45+BE45 -> 0 | BI45: =BF45+Q45 -> 356 | BJ45: =IF(BH45="",P45+BF45,BH45) -> 45656 | CC45: =BR45+BV45+BZ45 -> 0 | CE45: =IF(Y45=0,(W45+CC45)-CD45,IF(Y45>0,(Y45+CC45)-CD45)) -> 97800000 | CG45: =IFERROR(IF(((CE45/BI45)*(TODAY()-N45))>CE45,CE45,((CE45/BI45)*(TODAY()-N45))),"") -> 97800000 | CH45: =IF(TODAY()>BJ45,1,+(DAYS360(O45,TODAY())/DAYS360(O45,BJ45))) -> 1 | CI45: =+IF(CL45>0,DAYS360(O45,CL45)/DAYS360(O45,BJ45),CH45) -> 1 | CJ45: =IFERROR(IF(((CG45/CE45)*100)>100,100,((CG45/CE45)*100)),"") -> 100 | CK45: =IFERROR((CF45/CE45)*100,"") -> 0 | CM45: =IF(CL45>1/1/6,"LIQUIDADO",IF(BJ45=0,"",IF(BJ45>=TODAY(),"VIGENTE",IF(BJ45<TODAY(),"TERMINADO",)))) -> TERMINADO | CO45: 20243030000277-I Id: 4085870 | CP45: MASCULINO
A46: 4.134 | B46: 2024-0045 | C46: CTO | D46: CD-045-2024 | E46: 9 PRESTACIÓN DE SERVICIOS | F46: 1 PERSONA NATURAL | G46: 3 CÉDULA DE CIUDADANÍA | H46: 1036600526 | I46: JENNIFER CAMPO RESTREPO | L46: IMPLEMENTAR ESTRATEGIAS PARA LA EJECUCIÓN DEL PLAN COMERCIAL DE LA TERRITORIAL NOROCCIDENTE ASOCIADAS AL PORTAFOLIO DE SERVICIOS DE ICETEX EN LA REGIÓN, EN ARTICULACIÓN CON LA OFICINA COMERCIAL Y DE MERCADEO DEL NIVEL CENTRAL | M46: MEDELLIN | N46: 45296 | O46: 45296 | P46: 45656 | Q46: =P46-O46 -> 360 | R46: 1 FUNCIONAMIENTO | S46: CDEF-166-2024 | T46: HONORARIOS – OCM | U46: 68381619 | V46: IG312001020240012 | W46: 68381619 | X46: 5762496 | AA46: SECRETARÍA_GENERAL | AB46: =IFERROR(VLOOKUP(AA46,Listas!$A$1:$C$14,2,FALSE),"") -> FREDY CÉSPEDES VILLA | AC46: =IFERROR(VLOOKUP(AA46,Listas!$A$1:$C$14,3,FALSE),"") -> 93363483 | AD46: TERRITORIAL_NOROCCIDENTE | AE46: ASESOR TERRITORIAL ZONA NOROCCIDENTE | AF46: =IFERROR(VLOOKUP(AE46,Listas!$AD$1:$AF$66,2,FALSE),"") -> DANIEL ALBERTO CASTAÑO LOPEZ | AG46: =IFERROR(VLOOKUP(AE46,Listas!$AD$1:$AF$65,3,FALSE),"") -> 7544385 | AH46: 1 CONTRATACION DIRECTA | AI46: 1. Elaborar y presentar el plan de trabajo de estrategias comerciales a desarrollar con entidades aliadas como instituciones de educación superior, colegios, entes territoriales, comunidad en general o entidades del sector privado y público, para aprobación por parte del supervisor del contrato, de conformidad con las estipulaciones contractuales. 2. Implementar estrategias con el propósito de cumplir las metas comerciales del portafolio de servicios Icetex con los aliados y/o en los territorios asignados por su supervisor, para lo cual debe: a. Planear y ejecutar actividades de promoción y divulgación del portafolio de servicios de Icetex, en forma presencial y/o virtual. b. Acompañar el proceso de colocación de los servicios del portafolio de Icetex, asesorando en forma grupal y/o individual a los potenciales y actuales usuarios de la entidad en los diferentes procesos operativos a cargo, por medio del desarrollo de actividades en los diferentes canales de servicio como la atención personalizada, telefónica, virtual, por redes sociales, entre otros. c. Realizar el debido escalonamiento y seguimiento en la respuesta oportuna de las novedades de los usuarios asociados al embudo de conversión, de acuerdo con los procesos establecidos por la entidad. 3. Articular con los representantes de los diferentes entes territoriales y grupos de interés en los territorios asignados, en la planeación y ejecución de actividades comerciales de promoción del portafolio de servicios del Icetex en el ámbito de los municipios apartados categorizados como intermedio, rural y rural disperso, de acuerdo con el plan comercial propuesto por parte del supervisor. 4. Apoyar la ejecución de las estrategias comerciales y de servicio dispuestas por la Oficina Comercial y Mercadeo y demás áreas de la entidad, para el logro de las metas y objetivos estratégicos de la entidad. 5. Apoyar el proceso de suscripción de nuevos convenios y demás actividades de seguimiento de las obligaciones contractuales de los actuales convenios suscritos con las Instituciones de Educación Superior y/o demás aliados estratégicos asignados por su supervisor. 6. Capacitar a los funcionarios de las Instituciones de Educación Superior y /o entes territoriales asignados, respecto al portafolio de servicios del Icetex, los procedimientos internos a cargo de las IES, el diligenciamiento y entrega de los diferentes reportes de información requeridos por Icetex para la debida ejecución de los convenios suscritos con dichas entidades. 7. Realizar oportunamente las gestiones administrativas y reportes de información de la actividad comercial y operativa a su cargo, mediante la consolidación, actualización y registro de la información y documentación soporte bajo los procedimientos establecidos y en las plataformas tecnológicas requeridas por la entidad. 8. Apoyar el acompañamiento, gestión y documentación de proceso (s) y procedimiento (s), cumplimiento de los indicadores, planes de acción, planes de mejoramiento, reportes, auditorias de calidad, auditorías externas e internas, eventos de riesgos y demás resultantes del ejercicio de control y autocontrol de los procesos de calidad a cargo de la territorial 9. Consolidar y actualizar bases de datos con la información relativa a la gestión comercial realizada con IES, aliados estratégicos, entes territoriales y demás grupos de interés, en los formatos y medios establecidos por la entidad. 10. Participar en los procesos formativos programados por la entidad. 11. Realizar el debido proceso de gestión documental y envío al archivo único de la entidad de las actividades delegadas a su cargo, al igual que la presentación de los informes requeridos derivados de la ejecución presente contrato. 12. Ejecutar los procedimientos operativos de las tareas asignadas a su cargo y adecuada gestión de los diferentes aplicativos de la entidad, tales como: a) correo electrónico, b) gestión documental, c) aplicativo cosmos, d) archivo único, e) SISGESTION, f) demás aplicativos de gestión definidos por la entidad y asignados por su supervisor. 13. Desplazarse a las diferentes ciudades y municipios del país, en caso de ser necesario para la debida ejecución del contrato, previa coordinación con el supervisor. 14. Las demás que sean inherentes para el logro del objeto contratado, asignadas por el supervisor del contrato. 15. Cumplir con los indicadores de gestión establecidos | AJ46: 1 SI | AK46: 1 PUBLICADO | AL46: 1 PUBLICADO | AM46: 1 SI | AN46: 31562 | AO46: =IF(YEAR(TODAY())-YEAR(AN46)>100," ",YEAR(TODAY())-YEAR(AN46)) -> 39 | AP46: GRUPO_DE_CONTRATACIÓN | AQ46: DIANA GONZALEZ | BF46: =BC46+BE46 -> 0 | BI46: =BF46+Q46 -> 360 | BJ46: =IF(BH46="",P46+BF46,BH46) -> 45656 | CC46: =BR46+BV46+BZ46 -> 0 | CE46: =IF(Y46=0,(W46+CC46)-CD46,IF(Y46>0,(Y46+CC46)-CD46)) -> 68381619 | CG46: =IFERROR(IF(((CE46/BI46)*(TODAY()-N46))>CE46,CE46,((CE46/BI46)*(TODAY()-N46))),"") -> 68381619 | CH46: =IF(TODAY()>BJ46,1,+(DAYS360(O46,TODAY())/DAYS360(O46,BJ46))) -> 1 | CI46: =+IF(CL46>0,DAYS360(O46,CL46)/DAYS360(O46,BJ46),CH46) -> 1 | CJ46: =IFERROR(IF(((CG46/CE46)*100)>100,100,((CG46/CE46)*100)),"") -> 100 | CK46: =IFERROR((CF46/CE46)*100,"") -> 0 | CM46: =IF(CL46>1/1/6,"LIQUIDADO",IF(BJ46=0,"",IF(BJ46>=TODAY(),"VIGENTE",IF(BJ46<TODAY(),"TERMINADO",)))) -> TERMINADO | CO46: 20243030000288-I Id: 4085904 | CP46: FEMENINO
A47: 9.19 | B47: 2024-0046 | C47: CTO | D47: CD-046-2024 | E47: 9 PRESTACIÓN DE SERVICIOS | F47: 1 PERSONA NATURAL | G47: 3 CÉDULA DE CIUDADANÍA | H47: 1031141199 | I47: STEFANIA FAJARDO VELASCO | L47: "PRESTAR LOS SERVICIOS PROFESIONALES ESPECIALIZADOS PARA ORIENTAR Y TRAMITAR LOS PROCESOS QUE EN MATERIA DE CONTRATACIÓN POR PRESTACIÓN DE SERVICIOS REQUIERE EL GRUPO DE CRÉDITO, ASÍ COMO REALIZAR SEGUIMIENTO Y CONTROL DE LOS PROCESOS DEL SISTEMA DE GESTIÓN DE CALIDAD." | M47: BOGOTA | N47: 45296 | O47: 45296 | P47: 45656 | Q47: =P47-O47 -> 360 | R47: 1 FUNCIONAMIENTO | S47: CDEF-125-2024 | T47: HONORARIOS – VCC | U47: 85333976 | V47: IG-312001020600012 | W47: 85333976 | X47: 7111164 | AA47: SECRETARÍA_GENERAL | AB47: =IFERROR(VLOOKUP(AA47,Listas!$A$1:$C$14,2,FALSE),"") -> FREDY CÉSPEDES VILLA | AC47: =IFERROR(VLOOKUP(AA47,Listas!$A$1:$C$14,3,FALSE),"") -> 93363483 | AD47: VICEPRESIDENCIA_DE_CRÉDITO_Y_COBRANZA | AE47: VICEPRESIDENTE DE CRÉDITO Y COBRANZA | AF47: =IFERROR(VLOOKUP(AE47,Listas!$AD$1:$AF$66,2,FALSE),"") -> EDUARDO ELÍAS BARCHA BOLÍVAR | AG47: =IFERROR(VLOOKUP(AE47,Listas!$AD$1:$AF$65,3,FALSE),"") -> 72133921 | AH47: 1 CONTRATACION DIRECTA | AI47: 1. Apoyar administrativamente los procesos pre y pos contractuales de los contratos de prestación de servicios a cargo de la Vicepresidencia de Crédito y Cobranza realizando la validación, verificación, medición y control, así como llevar registro de los mismos. 2. Crear, consolidar y organizar las órdenes de pago de los contratos por contratación directa de acuerdo con el procedimiento establecido. 3. Apoyar en la gestión administrativa en cuanto a las actividades de archivo de los documentos de contractuales, así como entregarlos a la dependencia correspondiente. 4. Realizar programación presupuestal, así como generar seguimiento del mismo. 5. Elaborar desde el punto de vista técnico actas de liquidación, minutas, actas de inicio entre otros documentos y actividades para la suscripción de convenios y contratos. 6. Brindar la información necesaria para la actualización y seguimiento a los trámites registrados en la plataforma Sistema Único de Información de Trámites (SUIT) del departamento administrativo de la función pública, así como apoyar en las propuestas para las acciones de racionalización de los procedimientos del área. 7. Elaborar y apoyar la actualización de procesos y procedimientos, así como lo demás requerimientos que se presenten respecto de las normas técnicas en sistemas de calidad. 8. Realizar seguimiento a los planes de acción y mejoras del Grupo Crédito, en el Sistema Integral calidad del ICETEX de manera coordinada de acuerdo con los procesos y procedimientos. 9. Brindar acompañamiento y participar desde el punto de vista técnico a las auditorías internas y externas, así como apoyar las solicitudes del equipo MECI (Modelo Estándar de Control Interno) de la entidad. 10. Proyectar la respuesta a los requerimientos externos o internos que le sean asignados, dentro del tiempo establecido para ello, a través de los medios que se determinen, así como realizar memorandos en caso de requerirse. 11. Suministrar la información requerida a las áreas de la Entidad para realizar la difusión de los programas de crédito educativo y financiamiento a las Instituciones de Educación Superior (IES). 12. Apoyar en la elaboración de documentos, manuales, guías, etc; requeridos para los procesos de legalización y renovación de créditos, así mismo en caso de ser necesario realizar la respectiva difusión de la información con el fin de mantener la información actualizada de acuerdo con los lineamientos de lenguaje claro. 13. Registrar eventos de riesgos en caso de evidenciar incidencias en el proceso de legalización y renovación de créditos educativos, así como realizar seguimiento a los mismos. 14. Ejecutar las pruebas sobre las plataformas de cargue de documentos, formularios, legalización, renovación que le sean asignadas por la Coordinación de Crédito. 15. Crear Arandas con el fin de mantener la información actualizada, mitigar el riesgo y reducir la cantidad de requerimientos de los procesos. 16. Proyectar o apoyar las capacitaciones que le sean asignadas por la Coordinación de Crédito. 17. Elaborar y presentar los informes de gestión que se requieran y se relacionen con el cumplimiento del objeto contractual. 18. Cumplir con los indicadores de gestión establecidos. 19. Las demás obligaciones que se requieran para el cumplimiento a cabalidad del objeto contractual y que sean inherentes a la naturaleza del contrato. | AJ47: 1 SI | AK47: 1 PUBLICADO | AL47: 1 PUBLICADO | AM47: 1 SI | AN47: 33877 | AO47: =IF(YEAR(TODAY())-YEAR(AN47)>100," ",YEAR(TODAY())-YEAR(AN47)) -> 33 | AP47: GRUPO_DE_CONTRATACIÓN | AQ47: DIANA GONZALEZ | BF47: =BC47+BE47 -> 0 | BI47: =BF47+Q47 -> 360 | BJ47: =IF(BH47="",P47+BF47,BH47) -> 45656 | CC47: =BR47+BV47+BZ47 -> 0 | CE47: =IF(Y47=0,(W47+CC47)-CD47,IF(Y47>0,(Y47+CC47)-CD47)) -> 85333976 | CG47: =IFERROR(IF(((CE47/BI47)*(TODAY()-N47))>CE47,CE47,((CE47/BI47)*(TODAY()-N47))),"") -> 85333976 | CH47: =IF(TODAY()>BJ47,1,+(DAYS360(O47,TODAY())/DAYS360(O47,BJ47))) -> 1 | CI47: =+IF(CL47>0,DAYS360(O47,CL47)/DAYS360(O47,BJ47),CH47) -> 1 | CJ47: =IFERROR(IF(((CG47/CE47)*100)>100,100,((CG47/CE47)*100)),"") -> 100 | CK47: =IFERROR((CF47/CE47)*100,"") -> 0 | CM47: =IF(CL47>1/1/6,"LIQUIDADO",IF(BJ47=0,"",IF(BJ47>=TODAY(),"VIGENTE",IF(BJ47<TODAY(),"TERMINADO",)))) -> TERMINADO | CO47: 20243030000283-I Id: 4085882 | CP47: FEMENINO
A48: 10.2 | B48: 2024-0047 | C48: CTO | D48: CD-047-2024 | E48: 9 PRESTACIÓN DE SERVICIOS | F48: 1 PERSONA NATURAL | G48: 3 CÉDULA DE CIUDADANÍA | H48: 52532443 | I48: CLAUDIA MILENA MELO | L48: PRESTAR SUS SERVICIOS PROFESIONALES ESPECIALIZADOS, APOYANDO LA GESTIÓN JURÍDICA DE LOS FONDOS A CARGO DE LA VICEPRESIDENCIA DE FONDOS EN ADMINISTRACIÓN; ASÍ COMO LOS TEMAS RELACIONADOS CON LOS PROCESOS DE CONTRATACIÓN A SU CARGO | M48: BOGOTA | N48: 45296 | O48: 45296 | P48: 45657 | Q48: =P48-O48 -> 361 | R48: 1 FUNCIONAMIENTO | S48: CDEF-199-2024 | T48: HONORARIOS – VFA | U48: 138244294 | V48: IG312001020700012 | W48: 138244294 | X48: 11649800 | AA48: SECRETARÍA_GENERAL | AB48: =IFERROR(VLOOKUP(AA48,Listas!$A$1:$C$14,2,FALSE),"") -> FREDY CÉSPEDES VILLA | AC48: =IFERROR(VLOOKUP(AA48,Listas!$A$1:$C$14,3,FALSE),"") -> 93363483 | AD48: VICEPRESIDENCIA_DE_FONDOS_EN_ADMINISTRACIÓN | AE48: VICEPRESIDENTE DE FONDOS EN ADMINISTRACIÓN | AF48: =IFERROR(VLOOKUP(AE48,Listas!$AD$1:$AF$66,2,FALSE),"") -> DINORAH PATRICIA ABADIA MURILLO | AG48: =IFERROR(VLOOKUP(AE48,Listas!$AD$1:$AF$65,3,FALSE),"") -> 52220857 | AH48: 1 CONTRATACION DIRECTA | AI48: 1. Revisar los formatos, convenios, contratos, reglamentos operativos y demás documentos concernientes con la constitución de nuevos fondos a cargo de la Vicepresidencia de Fondos en Administración, previo a la radicación en el área de Acuerdos Estratégicos. 2. Revisar los otrosí, y demás documentos necesarios para la correcta ejecución de los fondos a cargo de la Vicepresidencia de Fondos en Administración, previo a la radicación en el área de Acuerdos Estratégicos. 3. Revisar la actualización de los reglamentos Operativos de los fondos administrados por la Vicepresidencia de Fondos en Administración. 4. Emitir conceptos, proyectar y revisar las respuestas de peticiones internas y externas, actos administrativos, que le sean requeridos y que guarden relación con los procesos a cargo de la Vicepresidencia de Fondos en Administración. 5. Proyectar y revisar los estudios y documentos previos de los procesos contractuales requeridos en la Vicepresidencia de Fondos en Administración, de acuerdo con la normatividad en materia de contratación aplicables a EL ICETEX. 6. Brindar acompañamiento en las mesas que se adelanten con los constituyentes y potenciales aliados a fin de resolver inquietudes desde el punto de vista jurídico. 7. Apoyar la supervisión de los contratos y/o convenios que le sean asignados, relacionados con el objeto contractual. 8. Incorporar a los expedientes de los fondos y las carpetas compartidas de la Vicepresidencia de Fondos en Administración la información que surja en el desarrollo del objeto contractual y hacer correcto uso de las mismas. 9. Garantizar la confidencialidad, reserva y privacidad de la información que por razón de sus actividades deba manejar en desarrollo del contrato. 10. Asistir y/o participar en los comités, mesas de trabajo y demás reuniones relacionadas con el objeto contractual. 11. Desplazarse en oficinas institucionales ubicadas en ciudades o municipios distintos a Bogotá D.C, por solicitud del supervisor, previo el otorgamiento de la correspondiente autorización de desplazamiento. 12. Las demás asignadas por el supervisor y que tengan relación con el objeto del presente contrato. | AJ48: 1 SI | AK48: 1 PUBLICADO | AL48: 1 PUBLICADO | AM48: 1 SI | AN48: 28650 | AO48: =IF(YEAR(TODAY())-YEAR(AN48)>100," ",YEAR(TODAY())-YEAR(AN48)) -> 47 | AP48: GRUPO_DE_CONTRATACIÓN | AQ48: JOSE GREGORIO SARMIENTO | BF48: =BC48+BE48 -> 0 | BI48: =BF48+Q48 -> 361 | BJ48: =IF(BH48="",P48+BF48,BH48) -> 45657 | CC48: =BR48+BV48+BZ48 -> 0 | CE48: =IF(Y48=0,(W48+CC48)-CD48,IF(Y48>0,(Y48+CC48)-CD48)) -> 138244294 | CG48: =IFERROR(IF(((CE48/BI48)*(TODAY()-N48))>CE48,CE48,((CE48/BI48)*(TODAY()-N48))),"") -> 138244294 | CH48: =IF(TODAY()>BJ48,1,+(DAYS360(O48,TODAY())/DAYS360(O48,BJ48))) -> 1 | CI48: =+IF(CL48>0,DAYS360(O48,CL48)/DAYS360(O48,BJ48),CH48) -> 1 | CJ48: =IFERROR(IF(((CG48/CE48)*100)>100,100,((CG48/CE48)*100)),"") -> 100 | CK48: =IFERROR((CF48/CE48)*100,"") -> 0 | CM48: =IF(CL48>1/1/6,"LIQUIDADO",IF(BJ48=0,"",IF(BJ48>=TODAY(),"VIGENTE",IF(BJ48<TODAY(),"TERMINADO",)))) -> TERMINADO | CO48: 20243030000295-I Id: 4085932 | CP48: FEMENINO
... A50: 4.32 | B50: 2024-0049 | C50: CTO | D50: CD-049-2024 | E50: 9 PRESTACIÓN DE SERVICIOS | F50: 1 PERSONA NATURAL | G50: 3 CÉDULA DE CIUDADANÍA | H50: 1033727637 | I50: HAZBLEIDY VANESSA HERNANDEZ CORTES | L50: PRESTAR LOS SERVICIOS DE APOYO TÉCNICO PARA LA GESTIÓN DE PROCESOS, TAREAS, OPERACIONES Y ACTIVIDADES RELACIONADOS CON LAS AUDITORÍAS, POLÍTICAS PÚBLICAS, GESTIÓN DEL RIESGO, GESTIÓN DEL CRÉDITO Y DEMÁS PLANES DE GESTIÓN Y AUTOCONTROL, DE CONFORMIDAD CON LOS REQUERIMIENTOS ORGANIZACIONALES Y NORMATIVOS DEL ICETEX | M50: BOGOTA | N50: 45296 | O50: 45302 | P50: 45656 | Q50: =P50-O50 -> 354 | R50: 1 FUNCIONAMIENTO | S50: CDEF-056-2024 | T50: HONORARIOS – OCM | U50: 52524529 | V50: IG312001020240014 | W50: 52524529 | X50: 4413826 | AA50: SECRETARÍA_GENERAL | AB50: =IFERROR(VLOOKUP(AA50,Listas!$A$1:$C$14,2,FALSE),"") -> FREDY CÉSPEDES VILLA | AC50: =IFERROR(VLOOKUP(AA50,Listas!$A$1:$C$14,3,FALSE),"") -> 93363483 | AD50: OFICINA_COMERCIAL_Y_DE_MERCADEO | AE50: JEFE OFICINA COMERCIAL Y DE MERCADEO | AF50: =IFERROR(VLOOKUP(AE50,Listas!$AD$1:$AF$66,2,FALSE),"") -> RODOLFO GIOVANNI CANCHILA SUÁREZ | AG50: =IFERROR(VLOOKUP(AE50,Listas!$AD$1:$AF$65,3,FALSE),"") -> 79672493 | AH50: 1 CONTRATACION DIRECTA | AI50: 1. Cumplir con el plan de trabajo entregado por la supervisión en el cual se relacionen los objetivos y metas a desarrollar durante la vigencia del contrato. 2. Responder oportunamente lo solicitado para la gestión de requerimientos gerenciales asociados a la planeación estratégica, comités, juntas y demás políticas y demás requerimientos organizacionales y normativos del ICETEX 3. Apoyar a la supervisión del contrato en requerimientos asociados a la gestión de auditorías en el marco de los procesos y procedimientos de la Oficina comercial y de Mercadeo o en las que ella participe. 4. Brindar propuestas de valor e insumos para el desarrollo de los procesos y su optimización a través de la ingeniería en los procesos y proyectos (análisis de rapidez, solución de problemas, control de ejecución presupuestal operativo, prevención del riesgo, disminución de PQRS, optimización de KPI´S operativos y las demás aplicables) para la correcta atención de los grupos de interés del ICETEX. 5. Colaborar en la debida gestión de actividades estratégicas asociadas a los planes y proyectos públicos normativos emitidos por los diferentes entes de control para la correcta atención y gestión de los grupos de interés del ICETEX. 6. Validar, documentar y hacer seguimiento a los riesgos identificados en el marco modelo de servicio, así cómo realizar propuestas teniendo como principal objetivo la identificación de las causas y fortalecimiento de controles. 7. Proponer iniciativas de mejora que apunten a la optimización y desarrollo de las actividades operativas y/o administrativas desarrolladas asociadas al Sistema de Atención al Consumidor Financiero en el marco de los procesos y procedimientos de la Oficina comercial y de Mercadeo o en las que ella participe. 8. Dirigir la gestión documental para el manejo, organización y evidencia de la documentación producida y recibida desde su origen hasta su destino final con el objeto de facilitar su utilización y conservación como actas, memorias, documentos asociados a la gestión contractual y las demás asociadas con los lineamientos de la Entidad en el marco de los procesos asociados a la Oficina Comercial y de Mercadeo. 9. Desplazarse a las diferentes ciudades del país, en caso de ser necesario para la debida ejecución del contrato, previa coordinación con el supervisor. 10. Las demás que sean inherentes para el logro del objeto contratado, asignadas por el supervisor del contrato. | AJ50: 1 SI | AK50: 1 PUBLICADO | AL50: 1 PUBLICADO | AM50: 1 SI | AN50: 33125 | AO50: =IF(YEAR(TODAY())-YEAR(AN50)>100," ",YEAR(TODAY())-YEAR(AN50)) -> 35 | AP50: GRUPO_DE_CONTRATACIÓN | AQ50: BRESMAN SANCHEZ | BF50: =BC50+BE50 -> 0 | BI50: =BF50+Q50 -> 354 | BJ50: =IF(BH50="",P50+BF50,BH50) -> 45656 | CC50: =BR50+BV50+BZ50 -> 0 | CE50: =IF(Y50=0,(W50+CC50)-CD50,IF(Y50>0,(Y50+CC50)-CD50)) -> 52524529 | CG50: =IFERROR(IF(((CE50/BI50)*(TODAY()-N50))>CE50,CE50,((CE50/BI50)*(TODAY()-N50))),"") -> 52524529 | CH50: =IF(TODAY()>BJ50,1,+(DAYS360(O50,TODAY())/DAYS360(O50,BJ50))) -> 1 | CI50: =+IF(CL50>0,DAYS360(O50,CL50)/DAYS360(O50,BJ50),CH50) -> 1 | CJ50: =IFERROR(IF(((CG50/CE50)*100)>100,100,((CG50/CE50)*100)),"") -> 100 | CK50: =IFERROR((CF50/CE50)*100,"") -> 0 | CM50: =IF(CL50>1/1/6,"LIQUIDADO",IF(BJ50=0,"",IF(BJ50>=TODAY(),"VIGENTE",IF(BJ50<TODAY(),"TERMINADO",)))) -> TERMINADO | CO50: 20243030000297-I Id: 4085934 | CP50: FEMENINO
A51: 12.22 | B51: 2024-0050 | C51: CTO | D51: CD-050-2024 | E51: 9 PRESTACIÓN DE SERVICIOS | F51: 1 PERSONA NATURAL | G51: 3 CÉDULA DE CIUDADANÍA | H51: 1018486367 | I51: MAYERLY GONZALEZ GORDILLO | L51: PRESTAR LOS SERVICIOS PROFESIONALES ESPECIALIZADOS PARA FORTALECIMIENTO Y OPTIMIZACIÓN DE LOS PROCESOS Y MECANISMOS QUE RESPALDAN LA ADMINISTRACIÓN DE LOS RECURSOS DE LA LEY 1777 DE 2016 MANEJADOS POR EL INSTITUTO, EN EL MARCO DE LA MODERNIZACIÓN DE LAS FUNCIONES FINANCIERAS DEL ICETEX Y EL PROYECTO DE INVERSIÓN DE BANCA ABIERTA Y TRANSPARENTE E INHOUSE BANKING | M51: BOGOTA | N51: 45300 | O51: 45301 | P51: 45656 | Q51: =P51-O51 -> 355 | R51: 1 FUNCIONAMIENTO | S51: CDEF-056-2024 | T51: BANCA ABIERTA Y TRANSPARENTE E INHOUSE B | U51: 102492216 | V51: IG332902005 | W51: 102492216 | X51: 8541018 | AA51: SECRETARÍA_GENERAL | AB51: =IFERROR(VLOOKUP(AA51,Listas!$A$1:$C$14,2,FALSE),"") -> FREDY CÉSPEDES VILLA | AC51: =IFERROR(VLOOKUP(AA51,Listas!$A$1:$C$14,3,FALSE),"") -> 93363483 | AD51: VICEPRESIDENCIA_FINANCIERA | AE51: DIRECTOR(A) DE TESORERÍA | AF51: =IFERROR(VLOOKUP(AE51,Listas!$AD$1:$AF$66,2,FALSE),"") -> DORIS POVEDA BELTRÁN | AG51: =IFERROR(VLOOKUP(AE51,Listas!$AD$1:$AF$65,3,FALSE),"") -> 52049845 | AH51: 1 CONTRATACION DIRECTA | AI51: 1. Apoyar en la estructuración de procesos y datos que permitan la sistematización y automatización de la gestión de inversiones relacionadas con el proyecto "cuentas abandonadas", conforme a lo establecido en la Ley 1777 de 2016. 2. Apoyar en la administración de las herramientas y optimización de procesos que permitan la actualización y verificación del sistema de datos relacionados con la valoración, traslado y devolución de fondos de cuentas en estado de abandono, de acuerdo con la información proporcionada por las instituciones financieras, en el marco del proyecto de Inhouse banking. 3. Apoyar la gestión financiera del área a través de la valoración del portafolio de inversiones administrado por el ICETEX, acorde a las condiciones del mercado. 4. Apoyar la implementación los mejores estándares que permitan la optimización e integración de procesos, normas y pautas para la modernización de las funciones financieras que respaldan las operaciones de la Dirección de Tesorería. 5. Apoyar en la estructuración y adopción de controles para las operaciones de inversión aprobadas por el ICETEX, según lo especificado en el Manual de Inversiones. 6. Estructurar documentos relativos a los procedimientos de cuentas abandonadas y gestión de inversiones. 7. Brindar apoyo a la Vicepresidencia Financiera y a la dirección de Tesoreria en la implementación de iniciativas en el marco del proyecto de inversión Banca Abierta y Transparente e Inhouse Banking y de diversificación de fuentes de fondeo. 8. Apoyar la estructuración de insumos técnicos para dar respuesta a los requerimientos de información solicitados por entes internos y/o externos en el marco del proyecto "cuentas abandonadas", conforme a lo establecido en la Ley 1777 de 2016. 9. Las demás obligaciones que se requieran para el cumplimiento a cabalidad del objeto contractual y que sean inherentes a la naturaleza del contrato. 10. Dar cumplimiento a los indicadores de gestión establecidos en el contrato. | AJ51: 1 SI | AK51: 1 PUBLICADO | AL51: 1 PUBLICADO | AM51: 1 SI | AN51: 35228 | AO51: =IF(YEAR(TODAY())-YEAR(AN51)>100," ",YEAR(TODAY())-YEAR(AN51)) -> 29 | AP51: GRUPO_DE_CONTRATACIÓN | AQ51: SEBASTIAN AYALA | AR51: 45581 | AS51: JHON JAIRO LOZADA LOZANO | AT51: 93400081 | AU51: CESIÓN DEL CONTRATO DE PRESTACIÓN DE SERVICIOS NO. 2024-0050 SUSCRITO ENTRE EL INSTITUTO COLOMBIANO DE CRÉDITO EDUCATIVO Y ESTUDIOS TÉCNICOS EN EL EXTERIOR “MARIANO OSPINA PÉREZ” – ICETEX Y MAYERLY GONZALEZ GORDILLO A JHON JAIRO LOZADA LOZANO | AV51: 21352539 | BF51: =BC51+BE51 -> 0 | BI51: =BF51+Q51 -> 355 | BJ51: =IF(BH51="",P51+BF51,BH51) -> 45656 | CC51: =BR51+BV51+BZ51 -> 0 | CE51: =IF(Y51=0,(W51+CC51)-CD51,IF(Y51>0,(Y51+CC51)-CD51)) -> 102492216 | CG51: =IFERROR(IF(((CE51/BI51)*(TODAY()-N51))>CE51,CE51,((CE51/BI51)*(TODAY()-N51))),"") -> 102492216 | CH51: =IF(TODAY()>BJ51,1,+(DAYS360(O51,TODAY())/DAYS360(O51,BJ51))) -> 1 | CI51: =+IF(CL51>0,DAYS360(O51,CL51)/DAYS360(O51,BJ51),CH51) -> 1 | CJ51: =IFERROR(IF(((CG51/CE51)*100)>100,100,((CG51/CE51)*100)),"") -> 100 | CK51: =IFERROR((CF51/CE51)*100,"") -> 0 | CM51: =IF(CL51>1/1/6,"LIQUIDADO",IF(BJ51=0,"",IF(BJ51>=TODAY(),"VIGENTE",IF(BJ51<TODAY(),"TERMINADO",)))) -> TERMINADO | CO51: 20244100000292-I Id: 4085919 | CP51: FEMENINO
A52: 4.19 | B52: 2024-0051 | C52: CTO | D52: CD-051-2024 | E52: 9 PRESTACIÓN DE SERVICIOS | F52: 1 PERSONA NATURAL | G52: 3 CÉDULA DE CIUDADANÍA | H52: 52153304 | I52: ALBA ADRIANA CHITIVA LOZANO | L52: PRESTAR LOS SERVICIOS PROFESIONALES ESPECIALIZADOS PARA EL SEGUIMIENTO Y CONTROL DE LOS PROGRAMAS, PROCESOS Y ACTIVIDADES RELACIONADOS CON LA GESTIÓN DEL RIESGO, GESTIÓN DEL CRÉDITO Y DEMÁS PLANES DE GESTIÓN Y AUTOCONTROL, DE CONFORMIDAD CON LOS REQUERIMIENTOS ORGANIZACIONALES Y NORMATIVOS DEL ICETEX | M52: BOGOTA | N52: 45296 | O52: 45300 | P52: 45656 | Q52: =P52-O52 -> 356 | R52: 1 FUNCIONAMIENTO | S52: CDEF-057--2024 | T52: HONORARIOS – OCM | U52: 72746393 | V52: IG312001020240012 | W52: 72746393 | X52: 6130314 | AA52: SECRETARÍA_GENERAL | AB52: =IFERROR(VLOOKUP(AA52,Listas!$A$1:$C$14,2,FALSE),"") -> FREDY CÉSPEDES VILLA | AC52: =IFERROR(VLOOKUP(AA52,Listas!$A$1:$C$14,3,FALSE),"") -> 93363483 | AD52: OFICINA_COMERCIAL_Y_DE_MERCADEO | AE52: JEFE OFICINA COMERCIAL Y DE MERCADEO | AF52: =IFERROR(VLOOKUP(AE52,Listas!$AD$1:$AF$66,2,FALSE),"") -> RODOLFO GIOVANNI CANCHILA SUÁREZ | AG52: =IFERROR(VLOOKUP(AE52,Listas!$AD$1:$AF$65,3,FALSE),"") -> 79672493 | AH52: 1 CONTRATACION DIRECTA | AI52: 1. Cumplir con el plan de trabajo entregado por la supervisión en el cual se relacionen los objetivos y metas a desarrollar durante la vigencia del contrato. 2. Gestionar la correcta y oportuna gestión de requerimientos gerenciales asociados a la planeación estratégica, comités, juntas y demás políticas y demás requerimientos organizacionales y normativos del ICETEX. 3. Planificar, guiar y controlar de forma eficiente y oportuna la gestión de auditorías en el marco de los procesos, procedimientos y documentación relacionada con el Defensor del Consumidor Financiero, Manual SAC (Sistema de Atención al Consumidor Financiero), Carta de trato digno al ciudadano y demás documentos que busquen proteger los derechos de las personas usuarias de los servicios de la Entidad. 4. Planificar, guiar y controlar de forma eficiente y oportuna planes de mejora basados en los resultados de las atenciones de PQRS, Defensor del Consumidor Financiero, así como lo establecido en la matriz de hechos y situaciones SAC (Sistema de Atención al Consumidor Financiero), carta de trato digno al ciudadano y demás documentos que busquen proteger los derechos de las personas usuarias de los servicios de la Entidad realizando seguimiento y control de los planes de mejora propuestos. 5. Apoyar la generación de alertas que así correspondan para la correcta documentación y gestión de los riesgos asociados a la Oficina Comercial y de Mercadeo o los procesos en la que esta dependencia participe. 6. Implementar estrategias de capacitación y desarrollo de personas en temas asociados a la protección de los derechos de las personas usuarias de los servicios de la Entidad, en especial Defensor del Consumidor Financiero, Manual SAC (Sistema de Atención al Consumidor Financiero), Carta de trato digno al ciudadano. 7. Dirigir la gestión documental para el manejo, organización y evidencia de la documentación producida y recibida desde su origen hasta su destino final con el objeto de facilitar su utilización y conservación como actas, memorias, documentos asociados a la gestión contractual y las demás asociadas con los lineamientos de la Entidad en el marco de los procesos asociados a la Oficina Comercial y de Mercadeo. 8. Desplazarse a las diferentes ciudades del país, en caso de ser necesario para la debida ejecución del contrato, previa coordinación con el supervisor. 9. Las demás que sean inherentes para el logro del objeto contratado, asignadas por el supervisor del contrato. | AJ52: 1 SI | AK52: 1 PUBLICADO | AL52: 1 PUBLICADO | AM52: 1 SI | AN52: 27595 | AO52: =IF(YEAR(TODAY())-YEAR(AN52)>100," ",YEAR(TODAY())-YEAR(AN52)) -> 50 | AP52: GRUPO_DE_CONTRATACIÓN | AQ52: BRESMAN SANCHEZ | BF52: =BC52+BE52 -> 0 | BI52: =BF52+Q52 -> 356 | BJ52: =IF(BH52="",P52+BF52,BH52) -> 45656 | CC52: =BR52+BV52+BZ52 -> 0 | CE52: =IF(Y52=0,(W52+CC52)-CD52,IF(Y52>0,(Y52+CC52)-CD52)) -> 72746393 | CG52: =IFERROR(IF(((CE52/BI52)*(TODAY()-N52))>CE52,CE52,((CE52/BI52)*(TODAY()-N52))),"") -> 72746393 | CH52: =IF(TODAY()>BJ52,1,+(DAYS360(O52,TODAY())/DAYS360(O52,BJ52))) -> 1 | CI52: =+IF(CL52>0,DAYS360(O52,CL52)/DAYS360(O52,BJ52),CH52) -> 1 | CJ52: =IFERROR(IF(((CG52/CE52)*100)>100,100,((CG52/CE52)*100)),"") -> 100 | CK52: =IFERROR((CF52/CE52)*100,"") -> 0 | CM52: =IF(CL52>1/1/6,"LIQUIDADO",IF(BJ52=0,"",IF(BJ52>=TODAY(),"VIGENTE",IF(BJ52<TODAY(),"TERMINADO",)))) -> TERMINADO | CO52: 20244100000298-I Id: 4085937 | CP52: FEMENINO
A53: 4.117 | B53: 2024-0052 | C53: CTO | D53: CD-053-2024 | E53: 9 PRESTACIÓN DE SERVICIOS | F53: 1 PERSONA NATURAL | G53: 3 CÉDULA DE CIUDADANÍA | H53: 1144144929 | I53: DAVID BERNARDO LONDOÑO ÁLVAREZ | L53: PRESTAR SERVICIOS PROFESIONALES ESPECIALIZADOS PARA LA COORDINACIÓN, DESARROLLO Y EJECUCIÓN DEL PLAN COMERCIAL DE LA TERRITORIAL SUROCCIDENTE QUE FOMENTE LA REGIONALIZACIÓN DEL PORTAFOLIO DE SERVICIOS DE LCETEX, EN ARTICULACIÓN CON LA OFICINA COMERCIAL Y DE MERCADEO DEL NIVEL CENTRAL. | M53: CALI | N53: 45296 | O53: 45300 | P53: 45656 | Q53: =P53-O53 -> 356 | R53: 1 FUNCIONAMIENTO | S53: CDEF-100--2024 | T53: HONORARIOS – OCM | U53: 84622860 | V53: IG312001020240012 | W53: 84622860 | X53: 7111165 | AA53: SECRETARÍA_GENERAL | AB53: =IFERROR(VLOOKUP(AA53,Listas!$A$1:$C$14,2,FALSE),"") -> FREDY CÉSPEDES VILLA | AC53: =IFERROR(VLOOKUP(AA53,Listas!$A$1:$C$14,3,FALSE),"") -> 93363483 | AD53: TERRITORIAL_SUROCCIDENTE | AE53: ASESOR TERRITORIAL ZONA SUROCCIDENTE | AF53: =IFERROR(VLOOKUP(AE53,Listas!$AD$1:$AF$66,2,FALSE),"") -> CESAR AUGUSTO LÓPEZ LÓPEZ | AG53: =IFERROR(VLOOKUP(AE53,Listas!$AD$1:$AF$65,3,FALSE),"") -> 6103856 | AH53: 1 CONTRATACION DIRECTA | AI53: 1. Proponer e implementar iniciativas que propendan la consecución de los metas comerciales de la Territorial a nivel de las Instituciones de Educación Superior, grupos de Interés y entes territoriales. 2. Apoyar la coordinación, gestionar y garantizar la debida y oportuna ejecución de las actividades del plan comercial de la Territorial por parte del equipo de contratistas comerciales. 3. Apoyar la supervisión a nivel territorial de la operación del contratista operador de servicio al cliente y plantear recomendaciones para la mejora del servicio que presta ICETEX en las diferentes comunidades participantes en sus programas e iniciativas. 4. Apoyar la supervisión de los convenios y contratos a cargo de la territorial. 5. Apoyar los procesos de capacitación y supervisión de las actividades comerciales y administrativas a ejecutar por parte de los contratistas comerciales a cargo de la territorial. 6. Implementar iniciativas de acompañamiento a los proyectos de vida de los estudiantes en la territorial Suroccidente, para promover el acceso, permanencia y graduación en la educación superior de calidad. 7. Participar en los escenarios de discusión con grupos de interés de ICETEX para posteriormente analizar las recomendaciones y proponer iniciativas para su implementación en la Entidad, en el marco de los programas de la Planeación Estratégica. 8. Gestionar, participar y trabajar en conjunto con las dependencias de la entidad y actores externos en la implementación de las propuestas y estrategia comerciales y administrativas que sean acogidas por la dirección de ICETEX, tendientes al cumplimiento de las metas comerciales y mejora en la operación de servicio al cliente. 9. Apoyar y/o participar en los comités de evaluación, operativos y/o juntas administradoras de los convenios a cargo de la territorial. 10. Participar en la ejecución de estrategias comerciales para la regionalización del portafolio de Icetex con el propósito de incrementar el alcance y la cobertura de la entidad en los municipios apartados categorizados como intermedio, rural y rural disperso; para el cumplimiento de las metas comerciales asignadas a la territorial. 11. Ejecutar actividades de promoción del portafolio de servicios de Icetex, en forma presencial y/o virtual, con los aliados asignados por su supervisor con el propósito de cumplir la meta establecida. 12. Apoyar a la entidad en la consecución, definición e implementación de alianzas territoriales que permitan complementar las iniciativas o acciones definidas por ICETEX para el territorio asignado. 13. Realizar las gestiones administrativas de la actividad comercial mediante la consolidación, actualización y registro de la información y documentación soporte. 14. Desplazarse a las diferentes ciudades del país, en caso de ser necesario para la debida ejecución del contrato, previa coordinación con el supervisor. 15. Realizar el debido proceso de gestión documental y envío al archivo único de la entidad de las actividades delegadas a su cargo, al igual que la presentación de los informes requeridos derivados de la ejecución presente contrato. 16. Ejecutar los procedimientos operativos de las tareas asignadas a su cargo y adecuada gestión de los diferentes aplicativos de la entidad, tales como: a) correo electrónico, b) gestión documental, c) aplicativo cosmos, d) archivo único, e) SISGESTION, f) demás aplicativos de gestión definidos por la entidad y asignados por su supervisor. 17. Las demás que sean inherentes para el logro del objeto contratado, asignadas por el supervisor del contrato. | AJ53: 1 SI | AK53: 1 PUBLICADO | AL53: 1 PUBLICADO | AM53: 1 SI | AO53: =IF(YEAR(TODAY())-YEAR(AN53)>100," ",YEAR(TODAY())-YEAR(AN53)) | AP53: GRUPO_DE_CONTRATACIÓN | AQ53: PATRICIA JALLER | BF53: =BC53+BE53 -> 0 | BI53: =BF53+Q53 -> 356 | BJ53: =IF(BH53="",P53+BF53,BH53) -> 45656 | CC53: =BR53+BV53+BZ53 -> 0 | CE53: =IF(Y53=0,(W53+CC53)-CD53,IF(Y53>0,(Y53+CC53)-CD53)) -> 84622860 | CG53: =IFERROR(IF(((CE53/BI53)*(TODAY()-N53))>CE53,CE53,((CE53/BI53)*(TODAY()-N53))),"") -> 84622860 | CH53: =IF(TODAY()>BJ53,1,+(DAYS360(O53,TODAY())/DAYS360(O53,BJ53))) -> 1 | CI53: =+IF(CL53>0,DAYS360(O53,CL53)/DAYS360(O53,BJ53),CH53) -> 1 | CJ53: =IFERROR(IF(((CG53/CE53)*100)>100,100,((CG53/CE53)*100)),"") -> 100 | CK53: =IFERROR((CF53/CE53)*100,"") -> 0 | CM53: =IF(CL53>1/1/6,"LIQUIDADO",IF(BJ53=0,"",IF(BJ53>=TODAY(),"VIGENTE",IF(BJ53<TODAY(),"TERMINADO",)))) -> TERMINADO | CO53: 20243030000309-I Id: 4085963 | CP53: MASCULINO
A54: 13.41 | B54: 2024-0053 | C54: CTO | D54: CD-054-2024 | E54: 9 PRESTACIÓN DE SERVICIOS | F54: 1 PERSONA NATURAL | G54: 3 CÉDULA DE CIUDADANÍA | H54: 1047411076 | I54: KATERINE LOPEZ ARNEDO | L54: PRESTACIÓN DE SERVICIOS PARA APOYAR LAS ACTIVIDADES INTERINSTITUCIONALES DE COOPERACIÓN TÉCNICA, REVISIÓN Y GESTIÓN DE ASUNTOS PROPIOS DEL GRUPO DE CONTRATACIÓN DEL ICETEX | M54: BOGOTA | N54: 45296 | O54: 45296 | P54: 45656 | Q54: =P54-O54 -> 360 | R54: 2 INVERSIÓN | S54: CDEF-027-2024 | T54: FORTALECIMIENTO ORGANIZACIONAL | U54: 55908467 | V54: IG 332901003 | W54: 55908467 | X54: 4414700 | AA54: SECRETARÍA_GENERAL | AB54: =IFERROR(VLOOKUP(AA54,Listas!$A$1:$C$14,2,FALSE),"") -> FREDY CÉSPEDES VILLA | AC54: =IFERROR(VLOOKUP(AA54,Listas!$A$1:$C$14,3,FALSE),"") -> 93363483 | AD54: SECRETARÍA_GENERAL | AE54: COORDINADOR(A) GRUPO DE CONTRATACIÓN | AF54: =IFERROR(VLOOKUP(AE54,Listas!$AD$1:$AF$66,2,FALSE),"") -> DIANA BARRERA MEDINA | AG54: =IFERROR(VLOOKUP(AE54,Listas!$AD$1:$AF$65,3,FALSE),"") -> 52964360 | AH54: 1 CONTRATACION DIRECTA | AI54: 1. Realizar acompañamiento a reuniones relacionadas con sus actividades y que le sean asignadas por el supervisor del contrato. 2. Emitir los conceptos que se requieran en el marco del objeto contractual. 3. Apoyar en la promoción de buenas prácticas en desarrollo de las funciones propias del grupo de contratación. 4. Las demás que sean asignadas en el desarrollo de la ejecución contractual relacionadas con el objeto del contrato. | AJ54: 1 SI | AK54: 1 PUBLICADO | AL54: 1 PUBLICADO | AM54: 1 SI | AN54: 32727 | AO54: =IF(YEAR(TODAY())-YEAR(AN54)>100," ",YEAR(TODAY())-YEAR(AN54)) -> 36 | AP54: GRUPO_DE_CONTRATACIÓN | AQ54: LAURA NARANJO | BF54: =BC54+BE54 -> 0 | BI54: =BF54+Q54 -> 360 | BJ54: =IF(BH54="",P54+BF54,BH54) -> 45656 | CC54: =BR54+BV54+BZ54 -> 0 | CE54: =IF(Y54=0,(W54+CC54)-CD54,IF(Y54>0,(Y54+CC54)-CD54)) -> 55908467 | CG54: =IFERROR(IF(((CE54/BI54)*(TODAY()-N54))>CE54,CE54,((CE54/BI54)*(TODAY()-N54))),"") -> 55908467 | CH54: =IF(TODAY()>BJ54,1,+(DAYS360(O54,TODAY())/DAYS360(O54,BJ54))) -> 1 | CI54: =+IF(CL54>0,DAYS360(O54,CL54)/DAYS360(O54,BJ54),CH54) -> 1 | CJ54: =IFERROR(IF(((CG54/CE54)*100)>100,100,((CG54/CE54)*100)),"") -> 100 | CK54: =IFERROR((CF54/CE54)*100,"") -> 0 | CM54: =IF(CL54>1/1/6,"LIQUIDADO",IF(BJ54=0,"",IF(BJ54>=TODAY(),"VIGENTE",IF(BJ54<TODAY(),"TERMINADO",)))) -> TERMINADO | CP54: FEMENINO
A55: 2.15 | B55: 2024-0054 | C55: CTO | D55: CD-055-2024 | E55: 9 PRESTACIÓN DE SERVICIOS | F55: 1 PERSONA NATURAL | G55: 3 CÉDULA DE CIUDADANÍA | H55: 80096101 | I55: JUAN ESNEYDER AVILA ORJUELA | L55: PRESTAR LOS SERVICIOS PROFESIONALES ESPECIALIZADOS COMO LÍDER DEL EQUIPO DE INNOVACIÓN DEL ICETEX, IDENTIFICANDO OPORTUNIDADES PARA LA GENERACIÓN DE CAPACIDADES DE INNOVACIÓN, ASÍ COMO GUIAR LA MEJORA Y CREACIÓN DE PROCESOS, PRODUCTOS Y SERVICIOS EN LA ENTIDAD. | M55: BOGOTA | N55: 45296 | O55: 45300 | P55: 45656 | Q55: =P55-O55 -> 356 | R55: 1 FUNCIONAMIENTO | S55: CDEF-080-2024 | T55: HONORARIOS-OAP | U55: 183909432 | V55: IG312001020240012 | W55: 183909432 | X55: 15325786 | AA55: SECRETARÍA_GENERAL | AB55: =IFERROR(VLOOKUP(AA55,Listas!$A$1:$C$14,2,FALSE),"") -> FREDY CÉSPEDES VILLA | AC55: =IFERROR(VLOOKUP(AA55,Listas!$A$1:$C$14,3,FALSE),"") -> 93363483 | AD55: OFICINA_ASESORA_DE_PLANEACIÓN | AE55: JEFE OFICINA ASESORA DE PLANEACIÓN | AF55: =IFERROR(VLOOKUP(AE55,Listas!$AD$1:$AF$66,2,FALSE),"") -> EDGAR FABIO DÍAZ RAMIREZ | AG55: =IFERROR(VLOOKUP(AE55,Listas!$AD$1:$AF$65,3,FALSE),"") -> 79537198 | AH55: 1 CONTRATACION DIRECTA | AI55: 1. Liderar la identificación de oportunidades para el desarrollo de innovaciones en el portafolio, procesos y estrategia alineados con el Plan Estratégico de la Entidad. 2. Destinar los integrantes del equipo de innovación y su grado de ocupación según las necesidades de cada uno de los proyectos o de las solicitudes de gestión realizadas al equipo. 3. Comunicar a la alta dirección los avances, resultados y logros alcanzados por el equipo de innovación, para conocer su percepción y utilizar la retroalimentación como insumo en los proyectos y acciones que este adelante. 4. Guiar y validar la ejecución de las acciones y proyectos que adelante el equipo de innovación de la entidad con el fin de desarrollar soluciones innovadoras y eficaces para los beneficiarios actuales y potenciales del ICETEX. 5. Liderar la realización de estudios técnicos que soporten el diseño de los nuevos servicios de apoyo educativo, crédito y financiamiento, que otorga la entidad. 6. Promover el trabajo colaborativo con las diferentes áreas de la entidad y el relacionamiento con los grupos de interés del ICETEX para impulsar la innovación. 7. Plantear y/o participar en acciones de ideación, cocreación y promoción de la innovación en ICETEX según como sea requerido por el equipo de innovación de la entidad y en articulación con las demás áreas de la entidad. 8. Cumplir con los indicadores de gestión establecidos. 9. Las demás que sean inherentes a la naturaleza del contrato, así como observar las recomendaciones dadas por el Supervisor de este para asegurar el cumplimiento de la finalidad del contrato, sin afectar la independencia del contratista. | AJ55: 1 SI | AK55: 1 PUBLICADO | AL55: 1 PUBLICADO | AM55: 1 SI | AN55: 30187 | AO55: =IF(YEAR(TODAY())-YEAR(AN55)>100," ",YEAR(TODAY())-YEAR(AN55)) -> 43 | AP55: GRUPO_DE_CONTRATACIÓN | AQ55: LAURA NARANJO | BF55: =BC55+BE55 -> 0 | BH55: 45537 | BI55: =BF55+Q55 -> 356 | BJ55: =IF(BH55="",P55+BF55,BH55) -> 45537 | CC55: =BR55+BV55+BZ55 -> 0 | CE55: =IF(Y55=0,(W55+CC55)-CD55,IF(Y55>0,(Y55+CC55)-CD55)) -> 183909432 | CG55: =IFERROR(IF(((CE55/BI55)*(TODAY()-N55))>CE55,CE55,((CE55/BI55)*(TODAY()-N55))),"") -> 183909432 | CH55: =IF(TODAY()>BJ55,1,+(DAYS360(O55,TODAY())/DAYS360(O55,BJ55))) -> 1 | CI55: =+IF(CL55>0,DAYS360(O55,CL55)/DAYS360(O55,BJ55),CH55) -> 1 | CJ55: =IFERROR(IF(((CG55/CE55)*100)>100,100,((CG55/CE55)*100)),"") -> 100 | CK55: =IFERROR((CF55/CE55)*100,"") -> 0 | CM55: =IF(CL55>1/1/6,"LIQUIDADO",IF(BJ55=0,"",IF(BJ55>=TODAY(),"VIGENTE",IF(BJ55<TODAY(),"TERMINADO",)))) -> TERMINADO | CO55: 20243030000318-I Id: 4085979 | CP55: MASCULINO
